Workbook

Sheet Resumen
C2: Dinero | D2: Cantidad | G2: Dinero | H2: Cantidad
B3: Entregado últimos 12 meses | C3: =AI112 -> 19182031 | D3: =AG112 -> 144 | F3: Stock (+) | G3: =K112 -> 5114246.9 | H3: =J112 -> 49
B4: Entregado 2026 | C4: =Z112 -> 7841236.8 | D4: =X112 -> 59 | F4: Tránsito real (+) | G4: =N112 -> 4840000.5 | H4: =L112 -> 50
B5: Backlog (Abril) | C5: =W112 -> 7438180.9 | D5: =U112 -> 49 | F5: Tránsito proyectado (+) | G5: =Q112 -> 5752411.2 | H5: =O112 -> 64
B6: Cotizado (NEC 3) | C6: =AC112 -> 0 | D6: =AA112 -> 0 | F6: En proceso (+) | G6: =AM112 -> 1783945 | H6: =AK112 -> 17
B7: Presupuesto 2026 | C7: =AF112 -> 22548875 | D7: =AD112 -> 172 | F7: Inventario inicial | G7: =SUM(G3:G6) -> 17490604 | H7: =SUM(H3:H6) -> 180
B8: Cumplimiento presupuesto (Cantidad) | C8: =IFERROR((D4+D5)/D7,"0") -> 0.62790698 | F8: Backlog (-) | G8: =W112 -> 7438180.9 | H8: =U112 -> 49
B9: Cumplimiento presupuesto (Dinero) | C9: =IFERROR((C4+C5)/C7,"0") -> 0.67761331 | F9: Inventario final | G9: =G7-G8 -> 10052423 | H9: =H7-H8 -> 131
B10: Rotación (últimos 12 meses) | C10: =IFERROR((H9/((D3+D5)/12)),"0") -> 8.1450777 | F10: Solicitud de compras (+) | G10: =T112 -> 2069007.4 | H10: =R112 -> 20
B11: Rotación (últimos 12 meses) + solicitud | C11: =IFERROR((H11/((D3+D5)/12)),"0") -> 9.388601 | F11: Inventario final proyectado | G11: =G9+G10 -> 12121430 | H11: =H9+H10 -> 151
I14: Stock | L14: Tránsito Real | O14: Tránsito Proyectado | R14: Solicitud de compras | U14: Backlog | X14: Entregado a cliente (2026) | AA14: NEC | AD14: Presupuesto 2026 | AG14: Entregado últimos 12 meses | AK14: Pesco Producción
A15: # | B15: Código | C15: Origen | D15: Familia | E15: Subfamilia | F15: Descripción | G15: Sobre camión | H15: Código | I15: Costo unitario | J15: Stock | K15: Costo inventario | L15: Cantidad | M15: Costo unitario tránsito | N15: Costo tránsito | O15: Cantidad | P15: Costo unitario tránsito | Q15: Costo tránsito | R15: Cantidad solicitada | S15: Costo unitario solicitud | T15: Costo total solicitud | U15: Cantidad | V15: Precio de venta (u) | W15: Facturación total | X15: Cantidad | Y15: Precio de venta (u) | Z15: Total facturado | AA15: Cantidad | AB15: Precio de venta esperado (u) | AC15: Total proyectado | AD15: Cantidad | AE15: Precio de venta (u) | AF15: Total proyectado | AG15: Cantidad | AH15: Precio de venta (u) | AI15: Total facturado | AJ15: Margen venta | AK15: Cantidad | AL15: Costo unitario | AM15: Costo total
A16: 1 | B16: 70100247 | C16: Venta | D16: Hiab | E16: 1188 | F16: GRUA ARTICULADA HIAB IQ 1188 E-9 JIB | G16: No | H16: 70100247 | I16: 0 | J16: =IFERROR((VLOOKUP(B16,Stock!A:C,3,0)),"0") -> 0 | K16: =J16*I16 -> 0 | L16: =IFERROR((VLOOKUP(H16,Tránsito!A:C,3,0)),"0") -> 0 | M16: 0 | N16: =M16*L16 -> 0 | O16: =IFERROR((VLOOKUP(H16,Tránsito!A:D,4,0)),"0") -> 0 | P16: 0 | Q16: =P16*O16 -> 0 | S16: 0 | T16: =S16*R16 -> 0 | V16: 327000 | W16: =V16*U16 -> 0 | X16: =IFERROR((VLOOKUP(H16,'Entregado (2026)'!A:C,3,0)),"0") -> 0 | Y16: 0 | Z16: =Y16*X16 -> 0 | AB16: 331950 | AC16: =AB16*AA16 -> 0 | AD16: 4 | AE16: 377955 | AF16: =AE16*AD16 -> 1511820 | AG16: =IFERROR((VLOOKUP(H16,'Ventas (2025)'!A:C,3,0)),"0") -> 1 | AH16: 378014.06 | AI16: =AH16*AG16 -> 378014.06 | AM16: =AL16*AK16 -> 0
A17: 2 | B17: 13171051 | C17: Compra | D17: Hiab | E17: 1188 | F17: GRUA ARTICULADA HIAB IQ1188 E-9 JIB | G17: No | H17: 13171051 | I17: 252902.12 | J17: 1 | K17: =J17*I17 -> 252902.12 | L17: =IFERROR((VLOOKUP(H17,Tránsito!A:C,3,0)),"0") -> 0 | M17: 219745 | N17: =M17*L17 -> 0 | O17: =IFERROR((VLOOKUP(H17,Tránsito!A:D,4,0)),"0") -> 2 | P17: 218806.5 | Q17: =P17*O17 -> 437613 | S17: 285000 | T17: =S17*R17 -> 0 | U17: 2 | V17: 377910 | W17: =V17*U17 -> 755820 | X17: =IFERROR((VLOOKUP(H17,'Entregado (2026)'!A:C,3,0)),"0") -> 0 | Y17: 378014.06 | Z17: =Y17*X17 -> 0 | AB17: 280527 | AC17: =AB17*AA17 -> 0 | AE17: 350000 | AF17: =AE17*AD17 -> 0 | AG17: =IFERROR((VLOOKUP(H17,'Ventas (2025)'!A:C,3,0)),"0") -> 0 | AH17: 0 | AI17: =AH17*AG17 -> 0 | AM17: =AL17*AK17 -> 0
A18: 3 | B18: 13171068 | C18: Compra | D18: Hiab | E18: 1188 | F18: GRUA ARTICULADA HIAB IQ 1188 E-8 HIPRO EVO | G18: No | H18: 13171068 | I18: 175584.79 | J18: =IFERROR((VLOOKUP(B18,Stock!A:C,3,0)),"0") -> 4 | K18: =J18*I18 -> 702339.15 | L18: =IFERROR((VLOOKUP(H18,Tránsito!A:C,3,0)),"0") -> 1 | M18: 168375 | N18: =M18*L18 -> 168375 | O18: =IFERROR((VLOOKUP(H18,Tránsito!A:D,4,0)),"0") -> 2 | P18: 168374.74 | Q18: =P18*O18 -> 336749.48 | R18: 0 | S18: 66007.68 | T18: =S18*R18 -> 0 | W18: =V18*U18 -> 0 | X18: =IFERROR((VLOOKUP(H18,'Entregado (2026)'!A:C,3,0)),"0") -> 0 | Z18: =Y18*X18 -> 0 | AB18: 331950 | AC18: =AB18*AA18 -> 0 | AF18: =AE18*AD18 -> 0 | AG18: =IFERROR((VLOOKUP(H18,'Ventas (2025)'!A:C,3,0)),"0") -> 0 | AH18: 0 | AI18: =AH18*AG18 -> 0 | AM18: =AL18*AK18 -> 0
A19: 4 | B19: 13171055 | C19: Compra | D19: Hiab | E19: 1000 | F19: GRUA ARTICULADA EFFER 1000 9S TC JIB | G19: No | H19: 13171055 | I19: 221682.2 | J19: =IFERROR((VLOOKUP(B19,Stock!A:C,3,0)),"0") -> 0 | K19: =J19*I19 -> 0 | L19: =IFERROR((VLOOKUP(H19,Tránsito!A:C,3,0)),"0") -> 0 | M19: 0 | N19: =M19*L19 -> 0 | O19: =IFERROR((VLOOKUP(H19,Tránsito!A:D,4,0)),"0") -> 0 | P19: 0 | Q19: =P19*O19 -> 0 | S19: 0 | T19: =S19*R19 -> 0 | V19: 0 | W19: =V19*U19 -> 0 | X19: =IFERROR((VLOOKUP(H19,'Entregado (2026)'!A:C,3,0)),"0") -> 0 | Y19: 0 | Z19: =Y19*X19 -> 0 | AB19: =Y19 -> 0 | AC19: =AB19*AA19 -> 0 | AE19: 0 | AF19: =AE19*AD19 -> 0 | AG19: =IFERROR((VLOOKUP(H19,'Ventas (2025)'!A:C,3,0)),"0") -> 0 | AH19: 0 | AI19: =AH19*AG19 -> 0 | AM19: =AL19*AK19 -> 0
A20: 5 | B20: 79001005 | C20: Venta | D20: Hiab | E20: 1000 | F20: GRUA ARTICULADA EFFER 1000 9S TC JIB | G20: No | H20: 79001005 | I20: 0 | J20: =IFERROR((VLOOKUP(B20,Stock!A:C,3,0)),"0") -> 0 | K20: =J20*I20 -> 0 | L20: =IFERROR((VLOOKUP(H20,Tránsito!A:C,3,0)),"0") -> 0 | M20: 0 | N20: =M20*L20 -> 0 | O20: =IFERROR((VLOOKUP(H20,Tránsito!A:D,4,0)),"0") -> 0 | P20: 0 | Q20: =P20*O20 -> 0 | S20: 0 | T20: =S20*R20 -> 0 | V20: 0 | W20: =V20*U20 -> 0 | X20: =IFERROR((VLOOKUP(H20,'Entregado (2026)'!A:C,3,0)),"0") -> 0 | Y20: 0 | Z20: =Y20*X20 -> 0 | AB20: =Y20 -> 0 | AC20: =AB20*AA20 -> 0 | AE20: 374000 | AF20: =AE20*AD20 -> 0 | AG20: =IFERROR((VLOOKUP(H20,'Ventas (2025)'!A:C,3,0)),"0") -> 0 | AH20: 0 | AI20: =AH20*AG20 -> 0 | AM20: =AL20*AK20 -> 0
A21: 6 | B21: 79001006 | C21: Venta | D21: Hiab | E21: 1000 | F21: CAMION GRUA ARTICULADA EFFER 1000 9S TC JIB | G21: Sí | H21: 79001006 | J21: =IFERROR((VLOOKUP(B21,Stock!A:C,3,0)),"0") -> 0 | K21: =J21*I21 -> 0 | L21: =IFERROR((VLOOKUP(H21,Tránsito!A:C,3,0)),"0") -> 0 | N21: =M21*L21 -> 0 | O21: =IFERROR((VLOOKUP(H21,Tránsito!A:D,4,0)),"0") -> 0 | Q21: =P21*O21 -> 0 | T21: =S21*R21 -> 0 | W21: =V21*U21 -> 0 | X21: =IFERROR((VLOOKUP(H21,'Entregado (2026)'!A:C,3,0)),"0") -> 0 | Y21: 603967 | Z21: =Y21*X21 -> 0 | AC21: =AB21*AA21 -> 0 | AF21: =AE21*AD21 -> 0 | AG21: =IFERROR((VLOOKUP(H21,'Ventas (2025)'!A:C,3,0)),"0") -> 0 | AH21: 0 | AI21: =AH21*AG21 -> 0 | AM21: =AL21*AK21 -> 0
A22: 7 | B22: 70100221 | C22: Venta | D22: Hiab | E22: 858 | F22: GRUA ARTICULADA HIAB X-HIPRO 858 E-8 | G22: No | H22: 70100221 | I22: 0 | J22: =IFERROR((VLOOKUP(B22,Stock!A:C,3,0)),"0") -> 0 | K22: =J22*I22 -> 0 | L22: =IFERROR((VLOOKUP(H22,Tránsito!A:C,3,0)),"0") -> 0 | M22: 0 | N22: =M22*L22 -> 0 | O22: =IFERROR((VLOOKUP(H22,Tránsito!A:D,4,0)),"0") -> 0 | P22: 0 | Q22: =P22*O22 -> 0 | S22: 0 | T22: =S22*R22 -> 0 | V22: 247702 | W22: =V22*U22 -> 0 | X22: =IFERROR((VLOOKUP(H22,'Entregado (2026)'!A:C,3,0)),"0") -> 6 | Y22: =VLOOKUP(F22,'Entregado (2026)'!$B:$D,3,0) -> 224810.07 | Z22: =Y22*X22 -> 1348860.4 | AB22: 278950 | AC22: =AB22*AA22 -> 0 | AD22: 15 | AE22: 241037 | AF22: =AE22*AD22 -> 3615555 | AG22: =IFERROR((VLOOKUP(H22,'Ventas (2025)'!A:C,3,0)),"0") -> 9 | AH22: 246202.37 | AI22: =AH22*AG22 -> 2215821.4 | AM22: =AL22*AK22 -> 0
A23: 8 | B23: 13171012 | C23: Compra | D23: Hiab | E23: 858 | F23: GRUA ARTICULADA HIAB X-HIPRO 858 E-8 | G23: No | H23: 13171012 | I23: 153295 | J23: =IFERROR((VLOOKUP(B23,Stock!A:C,3,0)),"0") -> 1 | K23: =J23*I23 -> 153295 | L23: =IFERROR((VLOOKUP(H23,Tránsito!A:C,3,0)),"0") -> 4 | M23: 149145.03 | N23: =M23*L23 -> 596580.13 | O23: =IFERROR((VLOOKUP(H23,Tránsito!A:D,4,0)),"0") -> 2 | P23: 150280.8 | Q23: =P23*O23 -> 300561.6 | S23: 149145.03 | T23: =S23*R23 -> 0 | U23: 1 | V23: 217341 | W23: =V23*U23 -> 217341 | X23: =IFERROR((VLOOKUP(H23,'Entregado (2026)'!A:C,3,0)),"0") -> 0 | Y23: 228850 | Z23: =Y23*X23 -> 0 | AB23: 278950 | AC23: =AB23*AA23 -> 0 | AE23: 0 | AF23: =AE23*AD23 -> 0 | AG23: =IFERROR((VLOOKUP(H23,'Ventas (2025)'!A:C,3,0)),"0") -> 0 | AH23: 246202.37 | AI23: =AH23*AG23 -> 0 | AM23: =AL23*AK23 -> 0
A24: 9 | B24: 70100211 | C24: Venta | D24: Hiab | E24: 858 | F24: GRUA ARTICULADA HIAB X-HIPRO 858 E-10 | G24: No | H24: 70100211 | I24: 199611.5 | J24: =IFERROR((VLOOKUP(B24,Stock!A:C,3,0)),"0") -> 0 | K24: =J24*I24 -> 0 | L24: =IFERROR((VLOOKUP(H24,Tránsito!A:C,3,0)),"0") -> 0 | M24: 0 | N24: =M24*L24 -> 0 | O24: =IFERROR((VLOOKUP(H24,Tránsito!A:D,4,0)),"0") -> 0 | P24: 0 | Q24: =P24*O24 -> 0 | S24: 0 | T24: =S24*R24 -> 0 | V24: 0 | W24: =V24*U24 -> 0 | X24: =IFERROR((VLOOKUP(H24,'Entregado (2026)'!A:C,3,0)),"0") -> 0 | Y24: 259857.47 | Z24: =Y24*X24 -> 0 | AB24: =Y24 -> 259857.47 | AC24: =AB24*AA24 -> 0 | AE24: 0 | AF24: =AE24*AD24 -> 0 | AG24: =IFERROR((VLOOKUP(H24,'Ventas (2025)'!A:C,3,0)),"0") -> 1 | AH24: 266178.2 | AI24: =AH24*AG24 -> 266178.2 | AM24: =AL24*AK24 -> 0
A25: 10 | B25: 13171010 | C25: Compra | D25: Hiab | E25: 858 | F25: GRUA ARTICULADA HIAB X-HIPRO 858 E-8 JIB TC2 | G25: No | H25: 13171010 | J25: =IFERROR((VLOOKUP(B25,Stock!A:C,3,0)),"0") -> 0 | K25: =J25*I25 -> 0 | L25: =IFERROR((VLOOKUP(H25,Tránsito!A:C,3,0)),"0") -> 0 | N25: =M25*L25 -> 0 | O25: =IFERROR((VLOOKUP(H25,Tránsito!A:D,4,0)),"0") -> 0 | Q25: =P25*O25 -> 0 | S25: 0 | T25: =S25*R25 -> 0 | V25: 0 | W25: =V25*U25 -> 0 | X25: =IFERROR((VLOOKUP(H25,'Entregado (2026)'!A:C,3,0)),"0") -> 0 | Y25: 0 | Z25: =Y25*X25 -> 0 | AB25: 346700 | AC25: =AB25*AA25 -> 0 | AE25: 0 | AF25: =AE25*AD25 -> 0 | AG25: =IFERROR((VLOOKUP(H25,'Ventas (2025)'!A:C,3,0)),"0") -> 0 | AH25: 0 | AI25: =AH25*AG25 -> 0 | AM25: =AL25*AK25 -> 0
A26: 11 | B26: 13171070 | C26: Compra | D26: Hiab | E26: 708 | F26: HIAB iQ.708 HiPro E9 | G26: No | H26: 13171070 | J26: =IFERROR((VLOOKUP(B26,Stock!A:C,3,0)),"0") -> 0 | K26: =J26*I26 -> 0 | L26: =IFERROR((VLOOKUP(H26,Tránsito!A:C,3,0)),"0") -> 0 | N26: =M26*L26 -> 0 | O26: 2 | P26: 193901 | Q26: =P26*O26 -> 387802 | R26: 2 | S26: 142731 | T26: =S26*R26 -> 285462 | U26: 1 | V26: 626373 | W26: =V26*U26 -> 626373 | X26: =IFERROR((VLOOKUP(H26,'Entregado (2026)'!A:C,3,0)),"0") -> 0 | Z26: =Y26*X26 -> 0 | AC26: =AB26*AA26 -> 0 | AF26: =AE26*AD26 -> 0 | AG26: =IFERROR((VLOOKUP(H26,'Ventas (2025)'!A:C,3,0)),"0") -> 0 | AH26: 0 | AI26: =AH26*AG26 -> 0 | AM26: =AL26*AK26 -> 0
A27: 12 | B27: 70100213 | C27: Venta | D27: Hiab | E27: 638 | F27: CAMION GRUA ARTICULADA HIAB X-HIPRO 638 E-9 | G27: Sí | H27: 70100213 | I27: 0 | J27: =IFERROR((VLOOKUP(B27,Stock!A:C,3,0)),"0") -> 0 | K27: =J27*I27 -> 0 | L27: =IFERROR((VLOOKUP(H27,Tránsito!A:C,3,0)),"0") -> 0 | M27: 0 | N27: =M27*L27 -> 0 | O27: =IFERROR((VLOOKUP(H27,Tránsito!A:D,4,0)),"0") -> 0 | P27: 0 | Q27: =P27*O27 -> 0 | S27: 0 | T27: =S27*R27 -> 0 | V27: 0 | W27: =V27*U27 -> 0 | X27: =IFERROR((VLOOKUP(H27,'Entregado (2026)'!A:C,3,0)),"0") -> 0 | Y27: 399069.34 | Z27: =Y27*X27 -> 0 | AB27: =Y27 -> 399069.34 | AC27: =AB27*AA27 -> 0 | AE27: 0 | AF27: =AE27*AD27 -> 0 | AG27: =IFERROR((VLOOKUP(H27,'Ventas (2025)'!A:C,3,0)),"0") -> 0 | AH27: 399069.34 | AI27: =AH27*AG27 -> 0 | AM27: =AL27*AK27 -> 0
A28: 13 | B28: 13171033 | C28: Compra | D28: Hiab | E28: 638 | F28: GRUA ARTICULADA HIAB X-HIPRO 638 E-9 | G28: No | H28: 13171033 | I28: 149553.31 | J28: =IFERROR((VLOOKUP(B28,Stock!A:C,3,0)),"0") -> 2 | K28: =J28*I28 -> 299106.62 | L28: =IFERROR((VLOOKUP(H28,Tránsito!A:C,3,0)),"0") -> 5 | M28: 142589 | N28: =M28*L28 -> 712945 | O28: =IFERROR((VLOOKUP(H28,Tránsito!A:D,4,0)),"0") -> 0 | P28: 139566.3 | Q28: =P28*O28 -> 0 | S28: 125790 | T28: =S28*R28 -> 0 | V28: 222950 | W28: =V28*U28 -> 0 | X28: =IFERROR((VLOOKUP(H28,'Entregado (2026)'!A:C,3,0)),"0") -> 0 | Y28: =VLOOKUP(F28,'Entregado (2026)'!$B:$D,3,0) -> 210868.91 | Z28: =Y28*X28 -> 0 | AC28: =AB28*AA28 -> 0 | AE28: 0 | AF28: =AE28*AD28 -> 0 | AG28: =IFERROR((VLOOKUP(H28,'Ventas (2025)'!A:C,3,0)),"0") -> 0 | AH28: 188582.39 | AI28: =AH28*AG28 -> 0 | AM28: =AL28*AK28 -> 0
A29: 14 | B29: 70100212 | C29: Venta | D29: Hiab | E29: 638 | F29: GRUA ARTICULADA HIAB X-HIPRO 638 E-9 | G29: No | H29: 70100212 | I29: 142070 | J29: =IFERROR((VLOOKUP(B29,Stock!A:C,3,0)),"0") -> 0 | K29: =J29*I29 -> 0 | L29: =IFERROR((VLOOKUP(H29,Tránsito!A:C,3,0)),"0") -> 0 | M29: 144067.97 | N29: =M29*L29 -> 0 | O29: =IFERROR((VLOOKUP(H29,Tránsito!A:D,4,0)),"0") -> 0 | P29: 144067.97 | Q29: =P29*O29 -> 0 | S29: 0 | T29: =S29*R29 -> 0 | U29: 1 | V29: 221975 | W29: =V29*U29 -> 221975 | X29: 2 | Y29: 210869 | Z29: =Y29*X29 -> 421738 | AB29: 205800 | AC29: =AB29*AA29 -> 0 | AD29: 11 | AE29: 146637 | AF29: =AE29*AD29 -> 1613007 | AG29: 7 | AH29: 188582.39 | AI29: =AH29*AG29 -> 1320076.8 | AM29: =AL29*AK29 -> 0
A30: 15 | B30: 13171066 | C30: Compra | D30: Hiab | E30: 638 | F30: HIAB 638 EP9 (EVO) | G30: Sí | H30: 13171066 | I30: 141079.09 | J30: =IFERROR((VLOOKUP(B30,Stock!A:C,3,0)),"0") -> 2 | K30: =J30*I30 -> 282158.18 | L30: =IFERROR((VLOOKUP(H30,Tránsito!A:C,3,0)),"0") -> 0 | M30: 134799 | N30: =M30*L30 -> 0 | O30: =IFERROR((VLOOKUP(H30,Tránsito!A:D,4,0)),"0") -> 0 | P30: 134799 | Q30: =P30*O30 -> 0 | T30: =S30*R30 -> 0 | W30: =V30*U30 -> 0 | X30: =IFERROR((VLOOKUP(H30,'Entregado (2026)'!A:C,3,0)),"0") -> 0 | Z30: =Y30*X30 -> 0 | AC30: =AB30*AA30 -> 0 | AF30: =AE30*AD30 -> 0 | AG30: =IFERROR((VLOOKUP(H30,'Ventas (2025)'!A:C,3,0)),"0") -> 0 | AH30: 0 | AI30: =AH30*AG30 -> 0 | AM30: =AL30*AK30 -> 0
A31: 16 | B31: 70100206 | C31: Venta | D31: Hiab | E31: 558 | F31: GRUA ARTICULADA HIAB X-HIPRO 558 EP-5 | G31: No | H31: 70100206 | I31: 0 | J31: =IFERROR((VLOOKUP(B31,Stock!A:C,3,0)),"0") -> 0 | K31: =J31*I31 -> 0 | L31: =IFERROR((VLOOKUP(H31,Tránsito!A:C,3,0)),"0") -> 0 | M31: 0 | N31: =M31*L31 -> 0 | O31: =IFERROR((VLOOKUP(H31,Tránsito!A:D,4,0)),"0") -> 0 | P31: 0 | Q31: =P31*O31 -> 0 | S31: 0 | T31: =S31*R31 -> 0 | V31: 168305 | W31: =V31*U31 -> 0 | X31: =IFERROR((VLOOKUP(H31,'Entregado (2026)'!A:C,3,0)),"0") -> 0 | Y31: 163830.01 | Z31: =Y31*X31 -> 0 | AB31: 164973 | AC31: =AB31*AA31 -> 0 | AD31: 12 | AE31: 165036.67 | AF31: =AE31*AD31 -> 1980440 | AG31: =IFERROR((VLOOKUP(H31,'Ventas (2025)'!A:C,3,0)),"0") -> 11 | AH31: 164940.42 | AI31: =AH31*AG31 -> 1814344.6 | AM31: =AL31*AK31 -> 0
A32: 17 | B32: 70100275 | C32: Venta | D32: Hiab | E32: 558 | F32: GRUA ARTICULADA HIAB X HIPRO 558 EP6 | G32: No | H32: 70100275 | I32: 0 | J32: =IFERROR((VLOOKUP(B32,Stock!A:C,3,0)),"0") -> 0 | K32: =J32*I32 -> 0 | L32: =IFERROR((VLOOKUP(H32,Tránsito!A:C,3,0)),"0") -> 0 | M32: 0 | N32: =M32*L32 -> 0 | O32: =IFERROR((VLOOKUP(H32,Tránsito!A:D,4,0)),"0") -> 0 | P32: 0 | Q32: =P32*O32 -> 0 | S32: 0 | T32: =S32*R32 -> 0 | U32: 8 | V32: 154124.44 | W32: =V32*U32 -> 1232995.6 | X32: =IFERROR((VLOOKUP(H32,'Entregado (2026)'!A:C,3,0)),"0") -> 3 | Y32: 142061 | Z32: =Y32*X32 -> 426183 | AC32: =AB32*AA32 -> 0 | AD32: 2 | AE32: 168028 | AF32: =AE32*AD32 -> 336056 | AG32: =IFERROR((VLOOKUP(H32,'Ventas (2025)'!A:C,3,0)),"0") -> 6 | AH32: 171378.09 | AI32: =AH32*AG32 -> 1028268.5 | AM32: =AL32*AK32 -> 0
A33: 18 | B33: 19601024 | C33: Compra | D33: Hiab | E33: 558 | F33: HIAB X-HIPRO 558 EP-5 | G33: No | H33: 19601024 | I33: 99403.325 | J33: =IFERROR((VLOOKUP(B33,Stock!A:C,3,0)),"0") -> 1 | K33: =J33*I33 -> 99403.325 | L33: =IFERROR((VLOOKUP(H33,Tránsito!A:C,3,0)),"0") -> 0 | M33: 92527.325 | N33: =M33*L33 -> 0 | O33: =IFERROR((VLOOKUP(H33,Tránsito!A:D,4,0)),"0") -> 0 | P33: 92527.325 | Q33: =P33*O33 -> 0 | S33: 0 | T33: =S33*R33 -> 0 | U33: 1 | V33: 156912 | W33: =V33*U33 -> 156912 | X33: =IFERROR((VLOOKUP(H33,'Entregado (2026)'!A:C,3,0)),"0") -> 0 | Y33: 164096 | Z33: =Y33*X33 -> 0 | AB33: 184100 | AC33: =AB33*AA33 -> 0 | AE33: 0 | AF33: =AE33*AD33 -> 0 | AG33: =IFERROR((VLOOKUP(H33,'Ventas (2025)'!A:C,3,0)),"0") -> 0 | AH33: 0 | AI33: =AH33*AG33 -> 0 | AL33: 103870 | AM33: =AL33*AK33 -> 0
A34: 19 | B34: 19601036 | C34: Compra | D34: Hiab | E34: 558 | F34: HIAB X-HIPRO 558 EP-6 | G34: No | H34: 19601036 | I34: 107955 | J34: =IFERROR((VLOOKUP(B34,Stock!A:C,3,0)),"0") -> 0 | K34: =J34*I34 -> 0 | L34: =IFERROR((VLOOKUP(H34,Tránsito!A:C,3,0)),"0") -> 7 | M34: 107937.99 | N34: =M34*L34 -> 755565.92 | O34: =IFERROR((VLOOKUP(H34,Tránsito!A:D,4,0)),"0") -> 14 | P34: 107937.99 | Q34: =P34*O34 -> 1511131.8 | T34: =S34*R34 -> 0 | V34: 0 | W34: =V34*U34 -> 0 | X34: =IFERROR((VLOOKUP(H34,'Entregado (2026)'!A:C,3,0)),"0") -> 0 | Y34: 0 | Z34: =Y34*X34 -> 0 | AB34: 167500 | AC34: =AB34*AA34 -> 0 | AE34: 96540 | AF34: =AE34*AD34 -> 0 | AG34: =IFERROR((VLOOKUP(H34,'Ventas (2025)'!A:C,3,0)),"0") -> 0 | AH34: 0 | AI34: =AH34*AG34 -> 0 | AK34: 1 | AL34: 107955 | AM34: =AL34*AK34 -> 107955
A35: 20 | B35: 13171064 | C35: Compra | D35: Hiab | E35: 558 | F35: Hiab 558 EP5 - EVO | G35: No | H35: 13171064 | I35: 122572 | J35: =IFERROR((VLOOKUP(B35,Stock!A:C,3,0)),"0") -> 1 | K35: =J35*I35 -> 122572 | L35: =IFERROR((VLOOKUP(H35,Tránsito!A:C,3,0)),"0") -> 0 | M35: 250168 | N35: =M35*L35 -> 0 | O35: =IFERROR((VLOOKUP(H35,Tránsito!A:D,4,0)),"0") -> 0 | P35: 250168 | Q35: =P35*O35 -> 0 | S35: 119948 | T35: =S35*R35 -> 0 | V35: 0 | W35: =V35*U35 -> 0 | X35: =IFERROR((VLOOKUP(H35,'Entregado (2026)'!A:C,3,0)),"0") -> 0 | Y35: 0 | Z35: =Y35*X35 -> 0 | AC35: =AB35*AA35 -> 0 | AE35: 0 | AF35: =AE35*AD35 -> 0 | AG35: =IFERROR((VLOOKUP(H35,'Ventas (2025)'!A:C,3,0)),"0") -> 0 | AH35: 0 | AI35: =AH35*AG35 -> 0 | AK35: 7 | AL35: 122572 | AM35: =AL35*AK35 -> 858004
A36: 21 | B36: 70100174 | C36: Venta | D36: Hiab | E36: 558 | F36: CAMION GRUA ARTICULADA HIAB X-HIPRO 558 EP-5 | G36: Sí | H36: 70100174 | J36: =IFERROR((VLOOKUP(B36,Stock!A:C,3,0)),"0") -> 0 | K36: =J36*I36 -> 0 | L36: =IFERROR((VLOOKUP(H36,Tránsito!A:C,3,0)),"0") -> 0 | N36: =M36*L36 -> 0 | O36: =IFERROR((VLOOKUP(H36,Tránsito!A:D,4,0)),"0") -> 0 | Q36: =P36*O36 -> 0 | T36: =S36*R36 -> 0 | V36: 382998 | W36: =V36*U36 -> 0 | X36: =IFERROR((VLOOKUP(H36,'Entregado (2026)'!A:C,3,0)),"0") -> 0 | Y36: 337868 | Z36: =Y36*X36 -> 0 | AB36: 378690 | AC36: =AB36*AA36 -> 0 | AF36: =AE36*AD36 -> 0 | AG36: 2 | AH36: 337867.94 | AI36: =AH36*AG36 -> 675735.88 | AM36: =AL36*AK36 -> 0
A37: 22 | B37: 70100160 | C37: Compra | D37: Hiab | E37: 558 | F37: GRUA ARTICULADA HIAB X-HIPRO 558 EP-6 EVO | G37: No | H37: 70100160 | J37: =IFERROR((VLOOKUP(B37,Stock!A:C,3,0)),"0") -> 0 | K37: =J37*I37 -> 0 | L37: =IFERROR((VLOOKUP(H37,Tránsito!A:C,3,0)),"0") -> 0 | N37: =M37*L37 -> 0 | O37: =IFERROR((VLOOKUP(H37,Tránsito!A:D,4,0)),"0") -> 0 | Q37: =P37*O37 -> 0 | T37: =S37*R37 -> 0 | U37: 7 | V37: 149080 | W37: =V37*U37 -> 1043560 | X37: 3 | Y37: 145230.16 | Z37: =Y37*X37 -> 435690.47 | AC37: =AB37*AA37 -> 0 | AF37: =AE37*AD37 -> 0 | AG37: 3 | AH37: 0 | AI37: =AH37*AG37 -> 0 | AM37: =AL37*AK37 -> 0
A38: 23 | B38: 70100205 | C38: Venta | D38: Hiab | E38: 548 | F38: GRUA ARTICULADA HIAB X-HIPRO 548 E-9 | G38: No | H38: 70100205 | I38: 0 | J38: =IFERROR((VLOOKUP(B38,Stock!A:C,3,0)),"0") -> 0 | K38: =J38*I38 -> 0 | L38: =IFERROR((VLOOKUP(H38,Tránsito!A:C,3,0)),"0") -> 0 | M38: 0 | N38: =M38*L38 -> 0 | O38: =IFERROR((VLOOKUP(H38,Tránsito!A:D,4,0)),"0") -> 0 | P38: 0 | Q38: =P38*O38 -> 0 | S38: 103280 | T38: =S38*R38 -> 0 | U38: 2 | V38: 189089.33 | W38: =V38*U38 -> 378178.67 | X38: 1 | Y38: 189673.53 | Z38: =Y38*X38 -> 189673.53 | AB38: 276714.2 | AC38: =AB38*AA38 -> 0 | AD38: 8 | AE38: 186837 | AF38: =AE38*AD38 -> 1494696 | AG38: 3 | AH38: 189737.42 | AI38: =AH38*AG38 -> 569212.27 | AM38: =AL38*AK38 -> 0
A39: 24 | B39: 70901020 | C39: Venta | D39: Hiab | E39: 548 | F39: CAMION GRUA ARTICULADA HIAB X-HIPRO 548 E-9 | G39: Sí | H39: 70901020 | I39: 0 | J39: =IFERROR((VLOOKUP(B39,Stock!A:C,3,0)),"0") -> 0 | K39: =J39*I39 -> 0 | L39: =IFERROR((VLOOKUP(H39,Tránsito!A:C,3,0)),"0") -> 0 | M39: 0 | N39: =M39*L39 -> 0 | O39: =IFERROR((VLOOKUP(H39,Tránsito!A:D,4,0)),"0") -> 0 | P39: 0 | Q39: =P39*O39 -> 0 | S39: 0 | T39: =S39*R39 -> 0 | V39: 0 | W39: =V39*U39 -> 0 | X39: =IFERROR((VLOOKUP(H39,'Entregado (2026)'!A:C,3,0)),"0") -> 0 | Y39: 187791.67 | Z39: =Y39*X39 -> 0 | AB39: =Y39 -> 187791.67 | AC39: =AB39*AA39 -> 0 | AE39: 0 | AF39: =AE39*AD39 -> 0 | AG39: =IFERROR((VLOOKUP(H39,'Ventas (2025)'!A:C,3,0)),"0") -> 0 | AH39: 187791.67 | AI39: =AH39*AG39 -> 0 | AM39: =AL39*AK39 -> 0
A40: 25 | B40: 19502062 | C40: Compra | D40: Hiab | E40: 548 | F40: GRUA ARTICULADA HIAB X-HIPRO 548 E-9 año 2022 | G40: No | H40: 19502062 | I40: 145127.51 | J40: =IFERROR((VLOOKUP(B40,Stock!A:C,3,0)),"0") -> 1 | K40: =J40*I40 -> 145127.51 | L40: =IFERROR((VLOOKUP(H40,Tránsito!A:C,3,0)),"0") -> 0 | M40: 0 | N40: =M40*L40 -> 0 | O40: =IFERROR((VLOOKUP(H40,Tránsito!A:D,4,0)),"0") -> 0 | P40: 0 | Q40: =P40*O40 -> 0 | S40: 0 | T40: =S40*R40 -> 0 | V40: 191500 | W40: =V40*U40 -> 0 | X40: 2 | Y40: 47218.939 | Z40: =Y40*X40 -> 94437.878 | AB40: =Y40 -> 47218.939 | AC40: =AB40*AA40 -> 0 | AE40: 0 | AF40: =AE40*AD40 -> 0 | AG40: =IFERROR((VLOOKUP(H40,'Ventas (2025)'!A:C,3,0)),"0") -> 1 | AH40: 140506.63 | AI40: =AH40*AG40 -> 140506.63 | AM40: =AL40*AK40 -> 0
A41: 26 | B41: 19502041 | C41: Compra | D41: Hiab | E41: 548 | F41: HIAB X-HIPRO 548 E-9 | G41: No | H41: 19502041 | I41: 120585 | J41: 3 | K41: =J41*I41 -> 361755 | L41: =IFERROR((VLOOKUP(H41,Tránsito!A:C,3,0)),"0") -> 4 | M41: 121896.14 | N41: =M41*L41 -> 487584.55 | O41: =IFERROR((VLOOKUP(H41,Tránsito!A:D,4,0)),"0") -> 0 | P41: 121896.14 | Q41: =P41*O41 -> 0 | R41: 4 | S41: 104123.52 | T41: =S41*R41 -> 416494.08 | V41: 0 | W41: =V41*U41 -> 0 | X41: =IFERROR((VLOOKUP(H41,'Entregado (2026)'!A:C,3,0)),"0") -> 0 | Y41: 0 | Z41: =Y41*X41 -> 0 | AB41: 222000 | AC41: =AB41*AA41 -> 0 | AE41: 221581 | AF41: =AE41*AD41 -> 0 | AG41: =IFERROR((VLOOKUP(H41,'Ventas (2025)'!A:C,3,0)),"0") -> 0 | AH41: 0 | AI41: =AH41*AG41 -> 0 | AM41: =AL41*AK41 -> 0
A42: 27 | D42: Hiab | E42: 548 | F42: HIAB X-HIPRO 548 E8 JIB 150X6 | G42: No | J42: =IFERROR((VLOOKUP(B42,Stock!A:C,3,0)),"0") -> 0 | L42: =IFERROR((VLOOKUP(H42,Tránsito!A:C,3,0)),"0") -> 0 | N42: =M42*L42 -> 0 | O42: =IFERROR((VLOOKUP(H42,Tránsito!A:D,4,0)),"0") -> 0 | Q42: =P42*O42 -> 0 | X42: =IFERROR((VLOOKUP(H42,'Entregado (2026)'!A:C,3,0)),"0") -> 0 | Z42: =Y42*X42 -> 0 | AB42: 238000 | AC42: =AB42*AA42 -> 0 | AG42: =IFERROR((VLOOKUP(H42,'Ventas (2025)'!A:C,3,0)),"0") -> 0 | AH42: 0 | AI42: =AH42*AG42 -> 0 | AM42: =AL42*AK42 -> 0
A43: 28 | B43: 13171065 | C43: Compra | D43: Hiab | E43: 548 | F43: HIAB 548 EP 9 (EVO) | G43: Sí | H43: 13171065 | I43: 118916.29 | J43: =IFERROR((VLOOKUP(B43,Stock!A:C,3,0)),"0") -> 2 | K43: =J43*I43 -> 237832.58 | L43: =IFERROR((VLOOKUP(H43,Tránsito!A:C,3,0)),"0") -> 0 | M43: 120467 | N43: =M43*L43 -> 0 | O43: =IFERROR((VLOOKUP(H43,Tránsito!A:D,4,0)),"0") -> 0 | P43: 120467 | Q43: =P43*O43 -> 0 | T43: =S43*R43 -> 0 | W43: =V43*U43 -> 0 | X43: =IFERROR((VLOOKUP(H43,'Entregado (2026)'!A:C,3,0)),"0") -> 0 | Z43: =Y43*X43 -> 0 | AC43: =AB43*AA43 -> 0 | AF43: =AE43*AD43 -> 0 | AG43: =IFERROR((VLOOKUP(H43,'Ventas (2025)'!A:C,3,0)),"0") -> 0 | AH43: 0 | AI43: =AH43*AG43 -> 0 | AM43: =AL43*AK43 -> 0
A44: 29 | B44: 13171022 | C44: Compra | D44: Hiab | E44: 418 | F44: HIAB X-HIPRO 418 EP-5 | G44: No | H44: 13171022 | I44: 87148 | J44: =IFERROR((VLOOKUP(B44,Stock!A:C,3,0)),"0") -> 2 | K44: =J44*I44 -> 174296 | L44: =IFERROR((VLOOKUP(H44,Tránsito!A:C,3,0)),"0") -> 4 | M44: 87428 | N44: =M44*L44 -> 349712 | O44: =IFERROR((VLOOKUP(H44,Tránsito!A:D,4,0)),"0") -> 5 | P44: 86632 | Q44: =P44*O44 -> 433160 | R44: 4 | S44: 154207.68 | T44: =S44*R44 -> 616830.72 | V44: 0 | W44: =V44*U44 -> 0 | X44: =IFERROR((VLOOKUP(H44,'Entregado (2026)'!A:C,3,0)),"0") -> 0 | Y44: 0 | Z44: =Y44*X44 -> 0 | AB44: 157284 | AC44: =AB44*AA44 -> 0 | AE44: 0 | AF44: =AE44*AD44 -> 0 | AG44: =IFERROR((VLOOKUP(H44,'Ventas (2025)'!A:C,3,0)),"0") -> 0 | AH44: 0 | AI44: =AH44*AG44 -> 0 | AK44: 3 | AL44: 89872 | AM44: =AL44*AK44 -> 269616
A45: 30 | B45: 70100165 | C45: Venta | D45: Hiab | E45: 418 | F45: GRUA ARTICULADA HIAB X-HIPRO 418 EP-5 | G45: No | H45: 70100165 | I45: 83750.176 | J45: =IFERROR((VLOOKUP(B45,Stock!A:C,3,0)),"0") -> 0 | K45: =J45*I45 -> 0 | L45: =IFERROR((VLOOKUP(H45,Tránsito!A:C,3,0)),"0") -> 0 | M45: 0 | N45: =M45*L45 -> 0 | O45: =IFERROR((VLOOKUP(H45,Tránsito!A:D,4,0)),"0") -> 0 | P45: 0 | Q45: =P45*O45 -> 0 | S45: 0 | T45: =S45*R45 -> 0 | U45: 2 | V45: 142983.33 | W45: =V45*U45 -> 285966.67 | X45: =IFERROR((VLOOKUP(H45,'Entregado (2026)'!A:C,3,0)),"0") -> 4 | Y45: 146760 | Z45: =Y45*X45 -> 587040 | AC45: =AB45*AA45 -> 0 | AD45: 12 | AE45: 146103.33 | AF45: =AE45*AD45 -> 1753240 | AG45: =IFERROR((VLOOKUP(H45,'Ventas (2025)'!A:C,3,0)),"0") -> 12 | AH45: 149485.92 | AI45: =AH45*AG45 -> 1793831.1 | AM45: =AL45*AK45 -> 0
A46: 31 | C46: Venta | D46: Hiab | E46: 418 | F46: CAMION GRUA ARTICULADA HIAB 418 EP5 | G46: Sí | J46: =IFERROR((VLOOKUP(B46,Stock!A:C,3,0)),"0") -> 0 | K46: =J46*I46 -> 0 | L46: =IFERROR((VLOOKUP(H46,Tránsito!A:C,3,0)),"0") -> 0 | N46: =M46*L46 -> 0 | O46: =IFERROR((VLOOKUP(H46,Tránsito!A:D,4,0)),"0") -> 0 | Q46: =P46*O46 -> 0 | T46: =S46*R46 -> 0 | W46: =V46*U46 -> 0 | X46: =IFERROR((VLOOKUP(H46,'Entregado (2026)'!A:C,3,0)),"0") -> 0 | Z46: =Y46*X46 -> 0 | AC46: =AB46*AA46 -> 0 | AF46: =AE46*AD46 -> 0 | AG46: =IFERROR((VLOOKUP(H46,'Ventas (2025)'!A:C,3,0)),"0") -> 0 | AH46: 0 | AI46: =AH46*AG46 -> 0 | AM46: =AL46*AK46 -> 0
A47: 32 | B47: 70100173 | D47: Hiab | E47: 418 | F47: CAMION GRUA ARTICULADA HIAB X-HIPRO 418 EP-5 | G47: Sí | H47: 70100173 | J47: =IFERROR((VLOOKUP(B47,Stock!A:C,3,0)),"0") -> 0 | K47: =J47*I47 -> 0 | L47: =IFERROR((VLOOKUP(H47,Tránsito!A:C,3,0)),"0") -> 0 | N47: =M47*L47 -> 0 | O47: =IFERROR((VLOOKUP(H47,Tránsito!A:D,4,0)),"0") -> 0 | Q47: =P47*O47 -> 0 | T47: =S47*R47 -> 0 | V47: 160058 | W47: =V47*U47 -> 0 | X47: =IFERROR((VLOOKUP(H47,'Entregado (2026)'!A:C,3,0)),"0") -> 2 | Y47: 319913 | Z47: =Y47*X47 -> 639826 | AB47: 310729 | AC47: =AB47*AA47 -> 0 | AF47: =AE47*AD47 -> 0 | AG47: =IFERROR((VLOOKUP(H47,'Ventas (2025)'!A:C,3,0)),"0") -> 4 | AH47: 299317.19 | AI47: =AH47*AG47 -> 1197268.8 | AM47: =AL47*AK47 -> 0
A48: 33 | B48: 13171021 | C48: Compra | D48: Hiab | E48: 408 | F48: HIAB X-HIPRO 408 E-8 | G48: No | H48: 13171021 | I48: 96529.762 | J48: =IFERROR((VLOOKUP(B48,Stock!A:C,3,0)),"0") -> 2 | K48: =J48*I48 -> 193059.52 | L48: =IFERROR((VLOOKUP(H48,Tránsito!A:C,3,0)),"0") -> 6 | M48: 102480 | N48: =M48*L48 -> 614880 | O48: =IFERROR((VLOOKUP(H48,Tránsito!A:D,4,0)),"0") -> 0 | P48: 102480 | Q48: =P48*O48 -> 0 | R48: 4 | S48: 88544.64 | T48: =S48*R48 -> 354178.56 | V48: 0 | W48: =V48*U48 -> 0 | X48: =IFERROR((VLOOKUP(H48,'Entregado (2026)'!A:C,3,0)),"0") -> 0 | Y48: 0 | Z48: =Y48*X48 -> 0 | AB48: =Y48 -> 0 | AC48: =AB48*AA48 -> 0 | AE48: 0 | AF48: =AE48*AD48 -> 0 | AG48: =IFERROR((VLOOKUP(H48,'Ventas (2025)'!A:C,3,0)),"0") -> 0 | AH48: 0 | AI48: =AH48*AG48 -> 0 | AM48: =AL48*AK48 -> 0
A49: 34 | B49: 70100164 | C49: Venta | D49: Hiab | E49: 408 | F49: GRUA ARTICULADA HIAB X-HIPRO 408 E-8 | G49: No | H49: 70100164 | I49: 117100.02 | J49: =IFERROR((VLOOKUP(B49,Stock!A:C,3,0)),"0") -> 0 | K49: =J49*I49 -> 0 | L49: =IFERROR((VLOOKUP(H49,Tránsito!A:C,3,0)),"0") -> 0 | M49: 101794 | N49: =M49*L49 -> 0 | O49: =IFERROR((VLOOKUP(H49,Tránsito!A:D,4,0)),"0") -> 0 | P49: 101794 | Q49: =P49*O49 -> 0 | S49: 0 | T49: =S49*R49 -> 0 | U49: 1 | V49: 155168 | W49: =V49*U49 -> 155168 | X49: 5 | Y49: 157588 | Z49: =Y49*X49 -> 787940 | AC49: =AB49*AA49 -> 0 | AD49: 14 | AE49: 160703.33 | AF49: =AE49*AD49 -> 2249846.7 | AG49: 9 | AH49: 173645.96 | AI49: =AH49*AG49 -> 1562813.7 | AM49: =AL49*AK49 -> 0
A50: 35 | D50: Hiab | E50: 408 | F50: GRUA HIAB HIPRO 408 E8 + TC2 | G50: No | J50: =IFERROR((VLOOKUP(B50,Stock!A:C,3,0)),"0") -> 0 | L50: =IFERROR((VLOOKUP(H50,Tránsito!A:C,3,0)),"0") -> 0 | N50: =M50*L50 -> 0 | O50: =IFERROR((VLOOKUP(H50,Tránsito!A:D,4,0)),"0") -> 0 | Q50: =P50*O50 -> 0 | X50: =IFERROR((VLOOKUP(H50,'Entregado (2026)'!A:C,3,0)),"0") -> 0 | Z50: =Y50*X50 -> 0 | AC50: =AB50*AA50 -> 0 | AG50: =IFERROR((VLOOKUP(H50,'Ventas (2025)'!A:C,3,0)),"0") -> 0 | AH50: 0 | AI50: =AH50*AG50 -> 0 | AM50: =AL50*AK50 -> 0
A51: 36 | C51: Venta | D51: Hiab | E51: 408 | F51: CAMION GRUA HIAB X-HIPRO 408 E8 | G51: Sí | J51: =IFERROR((VLOOKUP(B51,Stock!A:C,3,0)),"0") -> 0 | K51: =J51*I51 -> 0 | L51: =IFERROR((VLOOKUP(H51,Tránsito!A:C,3,0)),"0") -> 0 | N51: =M51*L51 -> 0 | O51: =IFERROR((VLOOKUP(H51,Tránsito!A:D,4,0)),"0") -> 0 | Q51: =P51*O51 -> 0 | T51: =S51*R51 -> 0 | W51: =V51*U51 -> 0 | X51: =IFERROR((VLOOKUP(H51,'Entregado (2026)'!A:C,3,0)),"0") -> 0 | Z51: =Y51*X51 -> 0 | AB51: 317972 | AC51: =AB51*AA51 -> 0 | AF51: =AE51*AD51 -> 0 | AG51: =IFERROR((VLOOKUP(H51,'Ventas (2025)'!A:C,3,0)),"0") -> 0 | AH51: 0 | AI51: =AH51*AG51 -> 0 | AM51: =AL51*AK51 -> 0
A52: 37 | C52: Venta | D52: Hiab | E52: 408 | F52: GRUA ARTICULADA HIAB X-HIPRO 408 E-8 + MULTILIFT OPTIMA 20S | G52: No | J52: =IFERROR((VLOOKUP(B52,Stock!A:C,3,0)),"0") -> 0 | K52: =J52*I52 -> 0 | L52: =IFERROR((VLOOKUP(H52,Tránsito!A:C,3,0)),"0") -> 0 | N52: =M52*L52 -> 0 | O52: =IFERROR((VLOOKUP(H52,Tránsito!A:D,4,0)),"0") -> 0 | Q52: =P52*O52 -> 0 | T52: =S52*R52 -> 0 | V52: 242101 | W52: =V52*U52 -> 0 | X52: =IFERROR((VLOOKUP(H52,'Entregado (2026)'!A:C,3,0)),"0") -> 0 | Z52: =Y52*X52 -> 0 | AC52: =AB52*AA52 -> 0 | AF52: =AE52*AD52 -> 0 | AG52: =IFERROR((VLOOKUP(H52,'Ventas (2025)'!A:C,3,0)),"0") -> 0 | AH52: 0 | AI52: =AH52*AG52 -> 0 | AM52: =AL52*AK52 -> 0
A53: 38 | B53: 70100253 | C53: Venta | D53: Hiab | E53: 388 | F53: GRUA HIAB X-CLX 388 EP5 | G53: No | H53: 70100253 | I53: 0 | J53: =IFERROR((VLOOKUP(B53,Stock!A:C,3,0)),"0") -> 0 | K53: =J53*I53 -> 0 | L53: =IFERROR((VLOOKUP(H53,Tránsito!A:C,3,0)),"0") -> 0 | M53: 0 | N53: =M53*L53 -> 0 | O53: =IFERROR((VLOOKUP(H53,Tránsito!A:D,4,0)),"0") -> 0 | P53: 0 | Q53: =P53*O53 -> 0 | S53: 0 | T53: =S53*R53 -> 0 | V53: 0 | W53: =V53*U53 -> 0 | X53: =IFERROR((VLOOKUP(H53,'Entregado (2026)'!A:C,3,0)),"0") -> 2 | Y53: =VLOOKUP(F53,'Entregado (2026)'!$B:$D,3,0) -> 72707.461 | Z53: =Y53*X53 -> 145414.92 | AB53: 79195 | AC53: =AB53*AA53 -> 0 | AD53: 2 | AE53: 68400 | AF53: =AE53*AD53 -> 136800 | AG53: =IFERROR((VLOOKUP(H53,'Ventas (2025)'!A:C,3,0)),"0") -> 2 | AH53: 0 | AI53: =AH53*AG53 -> 0 | AM53: =AL53*AK53 -> 0
A54: 39 | B54: 10705003 | C54: Compra | D54: Hiab | E54: 388 | F54: GRUA HIAB X-CLX 388 EP5 | G54: No | H54: 10705003 | I54: 58423.498 | J54: =IFERROR((VLOOKUP(B54,Stock!A:C,3,0)),"0") -> 0 | K54: =J54*I54 -> 0 | L54: =IFERROR((VLOOKUP(H54,Tránsito!A:C,3,0)),"0") -> 0 | M54: 0 | N54: =M54*L54 -> 0 | O54: =IFERROR((VLOOKUP(H54,Tránsito!A:D,4,0)),"0") -> 1 | P54: 53818 | Q54: =P54*O54 -> 53818 | S54: 51873 | T54: =S54*R54 -> 0 | V54: 0 | W54: =V54*U54 -> 0 | X54: =IFERROR((VLOOKUP(H54,'Entregado (2026)'!A:C,3,0)),"0") -> 0 | Y54: 72707.461 | Z54: =Y54*X54 -> 0 | AB54: 72500 | AC54: =AB54*AA54 -> 0 | AE54: 0 | AF54: =AE54*AD54 -> 0 | AG54: =IFERROR((VLOOKUP(H54,'Ventas (2025)'!A:C,3,0)),"0") -> 0 | AH54: 72707 | AI54: =AH54*AG54 -> 0 | AM54: =AL54*AK54 -> 0
A55: 40 | B55: 70100171 | C55: Venta | D55: Hiab | E55: 362 | F55: GRUA ARTICULADA HIAB X-HIPRO 362 EP-5 | G55: No | H55: 70100171 | I55: 0 | J55: =IFERROR((VLOOKUP(B55,Stock!A:C,3,0)),"0") -> 0 | K55: =J55*I55 -> 0 | L55: =IFERROR((VLOOKUP(H55,Tránsito!A:C,3,0)),"0") -> 0 | M55: 0 | N55: =M55*L55 -> 0 | O55: =IFERROR((VLOOKUP(H55,Tránsito!A:D,4,0)),"0") -> 0 | P55: 0 | Q55: =P55*O55 -> 0 | S55: 0 | T55: =S55*R55 -> 0 | V55: 155213.45 | W55: =V55*U55 -> 0 | X55: 5 | Y55: =VLOOKUP(F55,'Entregado (2026)'!$B:$D,3,0) -> 131632.08 | Z55: =Y55*X55 -> 658160.39 | AC55: =AB55*AA55 -> 0 | AD55: 22 | AE55: 94926 | AF55: =AE55*AD55 -> 2088372 | AG55: 12 | AH55: 143765.78 | AI55: =AH55*AG55 -> 1725189.3 | AL55: 77509 | AM55: =AL55*AK55 -> 0
A56: 41 | B56: 70901021 | C56: Venta | D56: Hiab | E56: 362 | F56: CAMION GRUA ARTICULADA HIAB X-HIPRO 362 EP-5 | G56: Sí | H56: 70901021 | I56: 0 | J56: =IFERROR((VLOOKUP(B56,Stock!A:C,3,0)),"0") -> 0 | K56: =J56*I56 -> 0 | L56: =IFERROR((VLOOKUP(H56,Tránsito!A:C,3,0)),"0") -> 0 | M56: 0 | N56: =M56*L56 -> 0 | O56: =IFERROR((VLOOKUP(H56,Tránsito!A:D,4,0)),"0") -> 0 | P56: 0 | Q56: =P56*O56 -> 0 | S56: 0 | T56: =S56*R56 -> 0 | V56: 0 | W56: =V56*U56 -> 0 | X56: =IFERROR((VLOOKUP(H56,'Entregado (2026)'!A:C,3,0)),"0") -> 0 | Y56: 241610.08 | Z56: =Y56*X56 -> 0 | AB56: =Y56 -> 241610.08 | AC56: =AB56*AA56 -> 0 | AE56: 0 | AF56: =AE56*AD56 -> 0 | AG56: 3 | AH56: 241610.08 | AI56: =AH56*AG56 -> 724830.24 | AM56: =AL56*AK56 -> 0
A57: 42 | B57: 13171020 | C57: Compra | D57: Hiab | E57: 362 | F57: HIAB X-HIPRO 362 EP-5 | G57: No | H57: 13171020 | I57: 77008 | J57: =IFERROR((VLOOKUP(B57,Stock!A:C,3,0)),"0") -> 0 | K57: =J57*I57 -> 0 | L57: =IFERROR((VLOOKUP(H57,Tránsito!A:C,3,0)),"0") -> 4 | M57: 77571.638 | N57: =M57*L57 -> 310286.55 | O57: =IFERROR((VLOOKUP(H57,Tránsito!A:D,4,0)),"0") -> 6 | P57: 77571.638 | Q57: =P57*O57 -> 465429.83 | R57: 6 | S57: 66007 | T57: =S57*R57 -> 396042 | U57: 3 | V57: 127992 | W57: =V57*U57 -> 383976 | X57: =IFERROR((VLOOKUP(H57,'Entregado (2026)'!A:C,3,0)),"0") -> 0 | Y57: 131632 | Z57: =Y57*X57 -> 0 | AC57: =AB57*AA57 -> 0 | AE57: 145266 | AF57: =AE57*AD57 -> 0 | AG57: =IFERROR((VLOOKUP(H57,'Ventas (2025)'!A:C,3,0)),"0") -> 0 | AH57: 0 | AI57: =AH57*AG57 -> 0 | AL57: 77509 | AM57: =AL57*AK57 -> 0
A58: 43 | B58: 13171063 | C58: Compra | D58: Hiab | E58: 362 | F58: Hiab 362 EP5 - EVO | G58: No | H58: 13171063 | I58: 91732 | J58: =IFERROR((VLOOKUP(B58,Stock!A:C,3,0)),"0") -> 12 | K58: =J58*I58 -> 1100784 | L58: =IFERROR((VLOOKUP(H58,Tránsito!A:C,3,0)),"0") -> 0 | M58: 90078 | N58: =M58*L58 -> 0 | O58: =IFERROR((VLOOKUP(H58,Tránsito!A:D,4,0)),"0") -> 0 | P58: 89939.642 | Q58: =P58*O58 -> 0 | S58: 89939.642 | T58: =S58*R58 -> 0 | V58: 0 | W58: =V58*U58 -> 0 | X58: =IFERROR((VLOOKUP(H58,'Entregado (2026)'!A:C,3,0)),"0") -> 0 | Y58: 0 | Z58: =Y58*X58 -> 0 | AC58: =AB58*AA58 -> 0 | AE58: 0 | AF58: =AE58*AD58 -> 0 | AG58: 13 | AH58: 0 | AI58: =AH58*AG58 -> 0 | AK58: 6 | AL58: 91395 | AM58: =AL58*AK58 -> 548370
A59: 44 | B59: 70100159 | C59: Compra | D59: Hiab | E59: 362 | F59: GRUA ARTICULADA HIAB X-HIPRO 362 EP-5 EVO | G59: No | H59: 70100159 | J59: =IFERROR((VLOOKUP(B59,Stock!A:C,3,0)),"0") -> 0 | K59: =J59*I59 -> 0 | L59: =IFERROR((VLOOKUP(H59,Tránsito!A:C,3,0)),"0") -> 0 | N59: =M59*L59 -> 0 | O59: =IFERROR((VLOOKUP(H59,Tránsito!A:D,4,0)),"0") -> 0 | Q59: =P59*O59 -> 0 | T59: =S59*R59 -> 0 | U59: 5 | V59: 116822 | W59: =V59*U59 -> 584110 | X59: 13 | Y59: 111276.46 | Z59: =Y59*X59 -> 1446593.9 | AC59: =AB59*AA59 -> 0 | AF59: =AE59*AD59 -> 0 | AG59: 1 | AH59: 0 | AI59: =AH59*AG59 -> 0 | AM59: =AL59*AK59 -> 0
A60: 45 | B60: 13171067 | C60: Compra | D60: Hiab | E60: 355 | F60: GRUA ARTICULADA EFFER IX 355 E-8 HIPRO | G60: No | H60: 13171067 | J60: =IFERROR((VLOOKUP(B60,Stock!A:C,3,0)),"0") -> 0 | K60: =J60*I60 -> 0 | L60: =IFERROR((VLOOKUP(H60,Tránsito!A:C,3,0)),"0") -> 0 | M60: 74792 | N60: =M60*L60 -> 0 | O60: =IFERROR((VLOOKUP(H60,Tránsito!A:D,4,0)),"0") -> 0 | P60: 74792 | Q60: =P60*O60 -> 0 | T60: =S60*R60 -> 0 | W60: =V60*U60 -> 0 | X60: =IFERROR((VLOOKUP(H60,'Entregado (2026)'!A:C,3,0)),"0") -> 0 | Z60: =Y60*X60 -> 0 | AC60: =AB60*AA60 -> 0 | AF60: =AE60*AD60 -> 0 | AG60: =IFERROR((VLOOKUP(H60,'Ventas (2025)'!A:C,3,0)),"0") -> 0 | AH60: 0 | AI60: =AH60*AG60 -> 0 | AM60: =AL60*AK60 -> 0
A61: 46 | B61: 70100222 | C61: Venta | D61: Hiab | E61: 352 | F61: GRUA ARTICULADA HIAB X-HIPRO 352 E-6 | G61: No | H61: 70100222 | I61: 0 | J61: =IFERROR((VLOOKUP(B61,Stock!A:C,3,0)),"0") -> 0 | K61: =J61*I61 -> 0 | L61: =IFERROR((VLOOKUP(H61,Tránsito!A:C,3,0)),"0") -> 0 | M61: 0 | N61: =M61*L61 -> 0 | O61: =IFERROR((VLOOKUP(H61,Tránsito!A:D,4,0)),"0") -> 0 | P61: 0 | Q61: =P61*O61 -> 0 | S61: 0 | T61: =S61*R61 -> 0 | V61: 0 | W61: =V61*U61 -> 0 | X61: =IFERROR((VLOOKUP(H61,'Entregado (2026)'!A:C,3,0)),"0") -> 0 | Y61: 92376.547 | Z61: =Y61*X61 -> 0 | AB61: 182000 | AC61: =AB61*AA61 -> 0 | AD61: 2 | AE61: 135855 | AF61: =AE61*AD61 -> 271710 | AG61: =IFERROR((VLOOKUP(H61,'Ventas (2025)'!A:C,3,0)),"0") -> 0 | AH61: 0 | AI61: =AH61*AG61 -> 0 | AM61: =AL61*AK61 -> 0
A62: 47 | B62: 70100220 | C62: Venta | D62: Hiab | E62: 352 | F62: CAMION GRUA ARTICULADA HIAB X-HIPRO 352 E-6 | G62: Sí | H62: 70100220 | I62: 0 | J62: =IFERROR((VLOOKUP(B62,Stock!A:C,3,0)),"0") -> 0 | K62: =J62*I62 -> 0 | L62: =IFERROR((VLOOKUP(H62,Tránsito!A:C,3,0)),"0") -> 0 | M62: 0 | N62: =M62*L62 -> 0 | O62: =IFERROR((VLOOKUP(H62,Tránsito!A:D,4,0)),"0") -> 0 | P62: 0 | Q62: =P62*O62 -> 0 | S62: 0 | T62: =S62*R62 -> 0 | V62: 0 | W62: =V62*U62 -> 0 | X62: =IFERROR((VLOOKUP(H62,'Entregado (2026)'!A:C,3,0)),"0") -> 0 | Y62: 345059.43 | Z62: =Y62*X62 -> 0 | AB62: =Y62 -> 345059.43 | AC62: =AB62*AA62 -> 0 | AE62: 0 | AF62: =AE62*AD62 -> 0 | AG62: 1 | AH62: 259969.54 | AI62: =AH62*AG62 -> 259969.54 | AM62: =AL62*AK62 -> 0
A63: 48 | B63: 13171045 | C63: Compra | D63: Hiab | E63: 352 | F63: GRUA ARTICULADA HIAB X-HIPRO 352 E-8 | G63: No | H63: 13171045 | I63: 82243.435 | J63: =IFERROR((VLOOKUP(B63,Stock!A:C,3,0)),"0") -> 0 | K63: =J63*I63 -> 0 | L63: =IFERROR((VLOOKUP(H63,Tránsito!A:C,3,0)),"0") -> 0 | M63: 0 | N63: =M63*L63 -> 0 | O63: =IFERROR((VLOOKUP(H63,Tránsito!A:D,4,0)),"0") -> 2 | P63: 90920.061 | Q63: =P63*O63 -> 181840.12 | S63: 82243 | T63: =S63*R63 -> 0 | V63: 345000 | W63: =V63*U63 -> 0 | X63: =IFERROR((VLOOKUP(H63,'Entregado (2026)'!A:C,3,0)),"0") -> 0 | Y63: 345000 | Z63: =Y63*X63 -> 0 | AB63: =Y63 -> 345000 | AC63: =AB63*AA63 -> 0 | AE63: 0 | AF63: =AE63*AD63 -> 0 | AG63: =IFERROR((VLOOKUP(H63,'Ventas (2025)'!A:C,3,0)),"0") -> 0 | AH63: 137124.47 | AI63: =AH63*AG63 -> 0 | AM63: =AL63*AK63 -> 0
A64: 49 | B64: 70100232 | C64: Venta | D64: Hiab | E64: 352 | F64: GRUA ARTICULADA HIAB X-HIPRO 352 E-8 | G64: No | H64: 70100232 | I64: 0 | J64: =IFERROR((VLOOKUP(B64,Stock!A:C,3,0)),"0") -> 0 | K64: =J64*I64 -> 0 | L64: =IFERROR((VLOOKUP(H64,Tránsito!A:C,3,0)),"0") -> 0 | M64: 0 | N64: =M64*L64 -> 0 | O64: =IFERROR((VLOOKUP(H64,Tránsito!A:D,4,0)),"0") -> 0 | P64: 0 | Q64: =P64*O64 -> 0 | S64: 0 | T64: =S64*R64 -> 0 | V64: 0 | W64: =V64*U64 -> 0 | X64: =IFERROR((VLOOKUP(H64,'Entregado (2026)'!A:C,3,0)),"0") -> 0 | Y64: 135078.74 | Z64: =Y64*X64 -> 0 | AB64: 159000 | AC64: =AB64*AA64 -> 0 | AE64: 167376 | AF64: =AE64*AD64 -> 0 | AG64: =IFERROR((VLOOKUP(H64,'Ventas (2025)'!A:C,3,0)),"0") -> 0 | AH64: 137124.47 | AI64: =AH64*AG64 -> 0 | AM64: =AL64*AK64 -> 0
A65: 50 | B65: 70100231 | C65: Venta | D65: Hiab | E65: 328 | F65: GRUA ARTICULADA HIAB X-CLX 328 EP-5 MARINA | G65: No | H65: 70100231 | I65: 0 | J65: =IFERROR((VLOOKUP(B65,Stock!A:C,3,0)),"0") -> 0 | K65: =J65*I65 -> 0 | L65: =IFERROR((VLOOKUP(H65,Tránsito!A:C,3,0)),"0") -> 0 | M65: 0 | N65: =M65*L65 -> 0 | O65: =IFERROR((VLOOKUP(H65,Tránsito!A:D,4,0)),"0") -> 0 | P65: 0 | Q65: =P65*O65 -> 0 | S65: 0 | T65: =S65*R65 -> 0 | V65: 108943 | W65: =V65*U65 -> 0 | X65: =IFERROR((VLOOKUP(H65,'Entregado (2026)'!A:C,3,0)),"0") -> 0 | Y65: 60501.676 | Z65: =Y65*X65 -> 0 | AB65: =Y65 -> 60501.676 | AC65: =AB65*AA65 -> 0 | AE65: 72000 | AF65: =AE65*AD65 -> 0 | AG65: =IFERROR((VLOOKUP(H65,'Ventas (2025)'!A:C,3,0)),"0") -> 0 | AH65: 0 | AI65: =AH65*AG65 -> 0 | AM65: =AL65*AK65 -> 0
A66: 51 | B66: 13171030 | C66: Compra | D66: Hiab | E66: 328 | F66: HIAB X-CLX 328 EP-5 | G66: No | H66: 13171030 | J66: =IFERROR((VLOOKUP(B66,Stock!A:C,3,0)),"0") -> 0 | K66: =J66*I66 -> 0 | L66: =IFERROR((VLOOKUP(H66,Tránsito!A:C,3,0)),"0") -> 0 | M66: 66166 | N66: =M66*L66 -> 0 | O66: =IFERROR((VLOOKUP(H66,Tránsito!A:D,4,0)),"0") -> 0 | P66: 66166 | Q66: =P66*O66 -> 0 | S66: 66166 | T66: =S66*R66 -> 0 | W66: =V66*U66 -> 0 | X66: 1 | Y66: 107285.32 | Z66: =Y66*X66 -> 107285.32 | AC66: =AB66*AA66 -> 0 | AF66: =AE66*AD66 -> 0 | AG66: 1 | AH66: 0 | AI66: =AH66*AG66 -> 0 | AL66: 69180 | AM66: =AL66*AK66 -> 0
A67: 52 | B67: 13171041 | C67: Compra | D67: Hiab | E67: 328 | F67: GRUA ARTICULADA HIAB X-CLX 328 EP-5 MARINA | G67: No | H67: 13171041 | J67: =IFERROR((VLOOKUP(B67,Stock!A:C,3,0)),"0") -> 0 | K67: =J67*I67 -> 0 | L67: =IFERROR((VLOOKUP(H67,Tránsito!A:C,3,0)),"0") -> 0 | N67: =M67*L67 -> 0 | O67: 1 | P67: 56352.001 | Q67: =P67*O67 -> 56352.001 | S67: 48305 | T67: =S67*R67 -> 0 | W67: =V67*U67 -> 0 | X67: =IFERROR((VLOOKUP(H67,'Entregado (2026)'!A:C,3,0)),"0") -> 0 | Z67: =Y67*X67 -> 0 | AC67: =AB67*AA67 -> 0 | AF67: =AE67*AD67 -> 0 | AG67: =IFERROR((VLOOKUP(H67,'Ventas (2025)'!A:C,3,0)),"0") -> 0 | AH67: 0 | AI67: =AH67*AG67 -> 0 | AM67: =AL67*AK67 -> 0
A68: 53 | B68: 13171018 | C68: Compra | D68: Hiab | E68: 302 | F68: HIAB X-HIPRO 302 E-8 | G68: No | H68: 13171018 | I68: 76286.587 | J68: =IFERROR((VLOOKUP(B68,Stock!A:C,3,0)),"0") -> 1 | K68: =J68*I68 -> 76286.587 | L68: =IFERROR((VLOOKUP(H68,Tránsito!A:C,3,0)),"0") -> 0 | M68: 0 | N68: =M68*L68 -> 0 | O68: =IFERROR((VLOOKUP(H68,Tránsito!A:D,4,0)),"0") -> 0 | P68: 0 | Q68: =P68*O68 -> 0 | S68: 73633.9 | T68: =S68*R68 -> 0 | V68: 0 | W68: =V68*U68 -> 0 | X68: =IFERROR((VLOOKUP(H68,'Entregado (2026)'!A:C,3,0)),"0") -> 0 | Y68: 0 | Z68: =Y68*X68 -> 0 | AB68: 136000 | AC68: =AB68*AA68 -> 0 | AE68: 0 | AF68: =AE68*AD68 -> 0 | AG68: =IFERROR((VLOOKUP(H68,'Ventas (2025)'!A:C,3,0)),"0") -> 0 | AH68: 0 | AI68: =AH68*AG68 -> 0 | AM68: =AL68*AK68 -> 0
A69: 54 | B69: 70100169 | C69: Venta | D69: Hiab | E69: 302 | F69: GRUA ARTICULADA HIAB X-HIPRO 302 E-8 | G69: No | H69: 70100169 | I69: 0 | J69: =IFERROR((VLOOKUP(B69,Stock!A:C,3,0)),"0") -> 0 | K69: =J69*I69 -> 0 | L69: =IFERROR((VLOOKUP(H69,Tránsito!A:C,3,0)),"0") -> 0 | M69: 0 | N69: =M69*L69 -> 0 | O69: =IFERROR((VLOOKUP(H69,Tránsito!A:D,4,0)),"0") -> 0 | P69: 0 | Q69: =P69*O69 -> 0 | S69: 0 | T69: =S69*R69 -> 0 | U69: 2 | V69: 127730 | W69: =V69*U69 -> 255460 | X69: =IFERROR((VLOOKUP(H69,'Entregado (2026)'!A:C,3,0)),"0") -> 0 | Y69: 141626.23 | Z69: =Y69*X69 -> 0 | AB69: 136000 | AC69: =AB69*AA69 -> 0 | AD69: 5 | AE69: 122355 | AF69: =AE69*AD69 -> 611775 | AG69: =IFERROR((VLOOKUP(H69,'Ventas (2025)'!A:C,3,0)),"0") -> 1 | AH69: 141626.23 | AI69: =AH69*AG69 -> 141626.23 | AM69: =AL69*AK69 -> 0
A70: 55 | B70: 13171029 | C70: Compra | D70: Hiab | E70: 302 | F70: HIAB eX302 EP-8 | G70: No | H70: 13171029 | J70: =IFERROR((VLOOKUP(B70,Stock!A:C,3,0)),"0") -> 0 | K70: =J70*I70 -> 0 | L70: 3 | M70: 81222 | N70: =M70*L70 -> 243666 | O70: =IFERROR((VLOOKUP(H70,Tránsito!A:D,4,0)),"0") -> 0 | P70: 81222 | Q70: =P70*O70 -> 0 | S70: 73633.9 | T70: =S70*R70 -> 0 | W70: =V70*U70 -> 0 | X70: =IFERROR((VLOOKUP(H70,'Entregado (2026)'!A:C,3,0)),"0") -> 0 | Z70: =Y70*X70 -> 0 | AC70: =AB70*AA70 -> 0 | AF70: =AE70*AD70 -> 0 | AG70: =IFERROR((VLOOKUP(H70,'Ventas (2025)'!A:C,3,0)),"0") -> 0 | AH70: 0 | AI70: =AH70*AG70 -> 0 | AM70: =AL70*AK70 -> 0
A71: 56 | B71: 13171023 | C71: Compra | D71: Hiab | E71: 298 | F71: HIAB iX298 EP-5 | G71: No | H71: 13171023 | I71: 51376 | J71: =IFERROR((VLOOKUP(B71,Stock!A:C,3,0)),"0") -> 0 | K71: =J71*I71 -> 0 | L71: =IFERROR((VLOOKUP(H71,Tránsito!A:C,3,0)),"0") -> 4 | M71: 66235 | N71: =M71*L71 -> 264940 | O71: =IFERROR((VLOOKUP(H71,Tránsito!A:D,4,0)),"0") -> 4 | P71: 66235 | Q71: =P71*O71 -> 264940 | S71: 51376 | T71: =S71*R71 -> 0 | V71: 0 | W71: =V71*U71 -> 0 | X71: =IFERROR((VLOOKUP(H71,'Entregado (2026)'!A:C,3,0)),"0") -> 0 | Y71: 0 | Z71: =Y71*X71 -> 0 | AB71: =Y71 -> 0 | AC71: =AB71*AA71 -> 0 | AE71: 0 | AF71: =AE71*AD71 -> 0 | AG71: =IFERROR((VLOOKUP(H71,'Ventas (2025)'!A:C,3,0)),"0") -> 0 | AH71: 0 | AI71: =AH71*AG71 -> 0 | AM71: =AL71*AK71 -> 0
A72: 57 | B72: 70100167 | C72: Venta | D72: Hiab | E72: 298 | F72: GRUA ARTICULADA HIAB X-HIDUO 298 EP-5 | G72: No | H72: 70100167 | I72: 0 | J72: =IFERROR((VLOOKUP(B72,Stock!A:C,3,0)),"0") -> 0 | K72: =J72*I72 -> 0 | L72: =IFERROR((VLOOKUP(H72,Tránsito!A:C,3,0)),"0") -> 0 | M72: 0 | N72: =M72*L72 -> 0 | O72: =IFERROR((VLOOKUP(H72,Tránsito!A:D,4,0)),"0") -> 0 | P72: 0 | Q72: =P72*O72 -> 0 | S72: 0 | T72: =S72*R72 -> 0 | V72: 115942 | W72: =V72*U72 -> 0 | X72: =IFERROR((VLOOKUP(H72,'Entregado (2026)'!A:C,3,0)),"0") -> 0 | Y72: 105532 | Z72: =Y72*X72 -> 0 | AC72: =AB72*AA72 -> 0 | AD72: 14 | AE72: 106970 | AF72: =AE72*AD72 -> 1497580 | AG72: =IFERROR((VLOOKUP(H72,'Ventas (2025)'!A:C,3,0)),"0") -> 4 | AH72: 104047.12 | AI72: =AH72*AG72 -> 416188.49 | AM72: =AL72*AK72 -> 0
A73: 58 | B73: 70100258 | C73: Venta | D73: Hiab | E73: 298 | F73: CAMION GRUA HIAB X HIDUO 298 EP5 | G73: Sí | H73: 70100258 | I73: 0 | J73: =IFERROR((VLOOKUP(B73,Stock!A:C,3,0)),"0") -> 0 | K73: =J73*I73 -> 0 | L73: =IFERROR((VLOOKUP(H73,Tránsito!A:C,3,0)),"0") -> 0 | M73: 0 | N73: =M73*L73 -> 0 | O73: =IFERROR((VLOOKUP(H73,Tránsito!A:D,4,0)),"0") -> 0 | P73: 0 | Q73: =P73*O73 -> 0 | S73: 0 | T73: =S73*R73 -> 0 | V73: 0 | W73: =V73*U73 -> 0 | X73: =IFERROR((VLOOKUP(H73,'Entregado (2026)'!A:C,3,0)),"0") -> 0 | Y73: 229078.74 | Z73: =Y73*X73 -> 0 | AB73: =Y73 -> 229078.74 | AC73: =AB73*AA73 -> 0 | AE73: 129123 | AF73: =AE73*AD73 -> 0 | AG73: =IFERROR((VLOOKUP(H73,'Ventas (2025)'!A:C,3,0)),"0") -> 0 | AH73: 229079 | AI73: =AH73*AG73 -> 0 | AM73: =AL73*AK73 -> 0
A74: 59 | B74: 70100215 | C74: Venta | D74: Hiab | E74: 298 | F74: GRUA ARTICULADA HIAB X-HIPRO 362 EP-5 | G74: Sí | H74: 70100215 | J74: =IFERROR((VLOOKUP(B74,Stock!A:C,3,0)),"0") -> 0 | K74: =J74*I74 -> 0 | L74: =IFERROR((VLOOKUP(H74,Tránsito!A:C,3,0)),"0") -> 0 | N74: =M74*L74 -> 0 | O74: =IFERROR((VLOOKUP(H74,Tránsito!A:D,4,0)),"0") -> 0 | Q74: =P74*O74 -> 0 | S74: 0 | T74: =S74*R74 -> 0 | V74: 138000 | W74: =V74*U74 -> 0 | X74: =IFERROR((VLOOKUP(H74,'Entregado (2026)'!A:C,3,0)),"0") -> 0 | Y74: =VLOOKUP(F74,'Entregado (2026)'!$B:$D,3,0) -> 131632.08 | Z74: =Y74*X74 -> 0 | AB74: 338600 | AC74: =AB74*AA74 -> 0 | AE74: 0 | AF74: =AE74*AD74 -> 0 | AG74: =IFERROR((VLOOKUP(H74,'Ventas (2025)'!A:C,3,0)),"0") -> 0 | AH74: 143765.78 | AI74: =AH74*AG74 -> 0 | AM74: =AL74*AK74 -> 0
A75: 60 | B75: 13171017 | C75: Compra | D75: Hiab | E75: 298 | F75: HIAB X-HIDUO 298 EP-5 | G75: No | H75: 13171017 | J75: =IFERROR((VLOOKUP(B75,Stock!A:C,3,0)),"0") -> 0 | K75: =J75*I75 -> 0 | L75: =IFERROR((VLOOKUP(H75,Tránsito!A:C,3,0)),"0") -> 0 | N75: =M75*L75 -> 0 | O75: =IFERROR((VLOOKUP(H75,Tránsito!A:D,4,0)),"0") -> 0 | Q75: =P75*O75 -> 0 | S75: 0 | T75: =S75*R75 -> 0 | V75: 0 | W75: =V75*U75 -> 0 | X75: =IFERROR((VLOOKUP(H75,'Entregado (2026)'!A:C,3,0)),"0") -> 0 | Y75: 0 | Z75: =Y75*X75 -> 0 | AB75: 121650 | AC75: =AB75*AA75 -> 0 | AE75: 0 | AF75: =AE75*AD75 -> 0 | AG75: =IFERROR((VLOOKUP(H75,'Ventas (2025)'!A:C,3,0)),"0") -> 0 | AH75: 0 | AI75: =AH75*AG75 -> 0 | AM75: =AL75*AK75 -> 0
A76: 61 | D76: Hiab | E76: 298 | F76: HIAB iX 298 HIDUO EP5 | G76: No | J76: =IFERROR((VLOOKUP(B76,Stock!A:C,3,0)),"0") -> 0 | L76: =IFERROR((VLOOKUP(H76,Tránsito!A:C,3,0)),"0") -> 0 | N76: =M76*L76 -> 0 | O76: =IFERROR((VLOOKUP(H76,Tránsito!A:D,4,0)),"0") -> 0 | Q76: =P76*O76 -> 0 | X76: =IFERROR((VLOOKUP(H76,'Entregado (2026)'!A:C,3,0)),"0") -> 0 | Z76: =Y76*X76 -> 0 | AB76: 119031 | AC76: =AB76*AA76 -> 0 | AG76: =IFERROR((VLOOKUP(H76,'Ventas (2025)'!A:C,3,0)),"0") -> 0 | AH76: 0 | AI76: =AH76*AG76 -> 0 | AM76: =AL76*AK76 -> 0
A77: 62 | B77: 13171059 | C77: Compra | D77: Hiab | E77: 288 | F77: GRUA ARTICULADA HIAB X-CLX 288 EP-5 MARINA | G77: No | H77: 13171059 | I77: 42615.977 | J77: =IFERROR((VLOOKUP(B77,Stock!A:C,3,0)),"0") -> 3 | K77: =J77*I77 -> 127847.93 | L77: =IFERROR((VLOOKUP(H77,Tránsito!A:C,3,0)),"0") -> 0 | M77: 53393.206 | N77: =M77*L77 -> 0 | O77: =IFERROR((VLOOKUP(H77,Tránsito!A:D,4,0)),"0") -> 0 | P77: 53393.206 | Q77: =P77*O77 -> 0 | S77: 0 | T77: =S77*R77 -> 0 | V77: 0 | W77: =V77*U77 -> 0 | X77: 1 | Y77: 55288.111 | Z77: =Y77*X77 -> 55288.111 | AC77: =AB77*AA77 -> 0 | AD77: 4 | AE77: 53000 | AF77: =AE77*AD77 -> 212000 | AG77: 2 | AH77: 53393.206 | AI77: =AH77*AG77 -> 106786.41 | AM77: =AL77*AK77 -> 0
A78: 63 | B78: 70100195 | C78: Venta | D78: Hiab | E78: 288 | F78: GRUA ARTICULADA HIAB X-CLX 288 EP-4 MARINA | G78: No | H78: 70100195 | I78: 0 | J78: =IFERROR((VLOOKUP(B78,Stock!A:C,3,0)),"0") -> 0 | K78: =J78*I78 -> 0 | L78: =IFERROR((VLOOKUP(H78,Tránsito!A:C,3,0)),"0") -> 0 | M78: 0 | N78: =M78*L78 -> 0 | O78: =IFERROR((VLOOKUP(H78,Tránsito!A:D,4,0)),"0") -> 0 | P78: 0 | Q78: =P78*O78 -> 0 | S78: 0 | T78: =S78*R78 -> 0 | V78: 0 | W78: =V78*U78 -> 0 | X78: =IFERROR((VLOOKUP(H78,'Entregado (2026)'!A:C,3,0)),"0") -> 0 | Y78: 53504.385 | Z78: =Y78*X78 -> 0 | AB78: =Y78 -> 53504.385 | AC78: =AB78*AA78 -> 0 | AE78: 58000 | AF78: =AE78*AD78 -> 0 | AG78: =IFERROR((VLOOKUP(H78,'Ventas (2025)'!A:C,3,0)),"0") -> 1 | AH78: 53504.385 | AI78: =AH78*AG78 -> 53504.385 | AM78: =AL78*AK78 -> 0
A79: 64 | B79: 13171024 | C79: Compra | D79: Hiab | E79: 288 | F79: GRUA ARTICULADA HIAB X-CLX 288 EP-4 MARINA | G79: No | H79: 13171024 | I79: 43938.202 | J79: =IFERROR((VLOOKUP(B79,Stock!A:C,3,0)),"0") -> 1 | K79: =J79*I79 -> 43938.202 | L79: =IFERROR((VLOOKUP(H79,Tránsito!A:C,3,0)),"0") -> 0 | M79: 53504.385 | N79: =M79*L79 -> 0 | O79: =IFERROR((VLOOKUP(H79,Tránsito!A:D,4,0)),"0") -> 0 | P79: 53504.385 | Q79: =P79*O79 -> 0 | S79: 0 | T79: =S79*R79 -> 0 | V79: 0 | W79: =V79*U79 -> 0 | X79: =IFERROR((VLOOKUP(H79,'Entregado (2026)'!A:C,3,0)),"0") -> 0 | Y79: 53504.385 | Z79: =Y79*X79 -> 0 | AB79: =Y79 -> 53504.385 | AC79: =AB79*AA79 -> 0 | AE79: 0 | AF79: =AE79*AD79 -> 0 | AG79: =IFERROR((VLOOKUP(H79,'Ventas (2025)'!A:C,3,0)),"0") -> 0 | AH79: 53504.385 | AI79: =AH79*AG79 -> 0 | AM79: =AL79*AK79 -> 0
A80: 65 | B80: 13171016 | C80: Compra | D80: Hiab | E80: 258 | F80: HIAB X-HIDUO 258 EP-5 | G80: No | H80: 13171016 | I80: 53494.221 | J80: =IFERROR((VLOOKUP(B80,Stock!A:C,3,0)),"0") -> 0 | K80: =J80*I80 -> 0 | L80: =IFERROR((VLOOKUP(H80,Tránsito!A:C,3,0)),"0") -> 0 | M80: 0 | N80: =M80*L80 -> 0 | O80: =IFERROR((VLOOKUP(H80,Tránsito!A:D,4,0)),"0") -> 0 | P80: 0 | Q80: =P80*O80 -> 0 | S80: 53494.221 | T80: =S80*R80 -> 0 | V80: 0 | W80: =V80*U80 -> 0 | X80: =IFERROR((VLOOKUP(H80,'Entregado (2026)'!A:C,3,0)),"0") -> 0 | Y80: 0 | Z80: =Y80*X80 -> 0 | AB80: =Y80 -> 0 | AC80: =AB80*AA80 -> 0 | AE80: 124277 | AF80: =AE80*AD80 -> 0 | AG80: =IFERROR((VLOOKUP(H80,'Ventas (2025)'!A:C,3,0)),"0") -> 0 | AH80: 0 | AI80: =AH80*AG80 -> 0 | AM80: =AL80*AK80 -> 0
A81: 66 | B81: 70100170 | C81: Venta | D81: Hiab | E81: 258 | F81: CAMION GRUA ARTICULADA HIAB X-HIDUO 258 EP-5 | G81: Sí | H81: 70100170 | I81: 43151.112 | J81: =IFERROR((VLOOKUP(B81,Stock!A:C,3,0)),"0") -> 0 | K81: =J81*I81 -> 0 | L81: =IFERROR((VLOOKUP(H81,Tránsito!A:C,3,0)),"0") -> 0 | M81: 0 | N81: =M81*L81 -> 0 | O81: =IFERROR((VLOOKUP(H81,Tránsito!A:D,4,0)),"0") -> 0 | P81: 0 | Q81: =P81*O81 -> 0 | S81: 0 | T81: =S81*R81 -> 0 | V81: 195000 | W81: =V81*U81 -> 0 | X81: =IFERROR((VLOOKUP(H81,'Entregado (2026)'!A:C,3,0)),"0") -> 0 | Y81: 183545.42 | Z81: =Y81*X81 -> 0 | AB81: =Y81 -> 183545.42 | AC81: =AB81*AA81 -> 0 | AD81: 12 | AE81: 102391 | AF81: =AE81*AD81 -> 1228692 | AG81: 2 | AH81: 183545.42 | AI81: =AH81*AG81 -> 367090.85 | AM81: =AL81*AK81 -> 0
A82: 67 | B82: 70100166 | C82: Venta | D82: Hiab | E82: 258 | F82: GRUA ARTICULADA HIAB X-HIDUO 258 EP-5 | G82: No | H82: 70100166 | I82: 69741.515 | J82: =IFERROR((VLOOKUP(B82,Stock!A:C,3,0)),"0") -> 0 | K82: =J82*I82 -> 0 | L82: =IFERROR((VLOOKUP(H82,Tránsito!A:C,3,0)),"0") -> 0 | M82: 0 | N82: =M82*L82 -> 0 | O82: =IFERROR((VLOOKUP(H82,Tránsito!A:D,4,0)),"0") -> 0 | P82: 0 | Q82: =P82*O82 -> 0 | S82: 0 | T82: =S82*R82 -> 0 | U82: 10 | V82: 87840 | W82: =V82*U82 -> 878400 | X82: =IFERROR((VLOOKUP(H82,'Entregado (2026)'!A:C,3,0)),"0") -> 1 | Y82: 85988.42 | Z82: =Y82*X82 -> 85988.42 | AC82: =AB82*AA82 -> 0 | AE82: 124277 | AF82: =AE82*AD82 -> 0 | AG82: =IFERROR((VLOOKUP(H82,'Ventas (2025)'!A:C,3,0)),"0") -> 7 | AH82: 102509.68 | AI82: =AH82*AG82 -> 717567.73 | AM82: =AL82*AK82 -> 0
A83: 68 | B83: 13171025 | C83: Compra | D83: Hiab | E83: 258 | F83: HIAB iX258 EP-5 | G83: No | H83: 13171025 | I83: 64770.205 | J83: 3 | K83: =J83*I83 -> 194310.62 | L83: =IFERROR((VLOOKUP(H83,Tránsito!A:C,3,0)),"0") -> 0 | M83: 64851.794 | N83: =M83*L83 -> 0 | O83: 15 | P83: 64851.794 | Q83: =P83*O83 -> 972776.91 | T83: =S83*R83 -> 0 | W83: =V83*U83 -> 0 | X83: =IFERROR((VLOOKUP(H83,'Entregado (2026)'!A:C,3,0)),"0") -> 0 | Z83: =Y83*X83 -> 0 | AC83: =AB83*AA83 -> 0 | AF83: =AE83*AD83 -> 0 | AG83: =IFERROR((VLOOKUP(H83,'Ventas (2025)'!A:C,3,0)),"0") -> 0 | AH83: 0 | AI83: =AH83*AG83 -> 0 | AM83: =AL83*AK83 -> 0
A84: 69 | B84: 13171028 | C84: Compra | D84: Hiab | E84: 248 | F84: GRUA ARTICULADA HIAB X-CLX 248 EP-4 MARINA | G84: No | H84: 13171028 | I84: 34571.749 | J84: =IFERROR((VLOOKUP(B84,Stock!A:C,3,0)),"0") -> 0 | K84: =J84*I84 -> 0 | L84: =IFERROR((VLOOKUP(H84,Tránsito!A:C,3,0)),"0") -> 0 | M84: 0 | N84: =M84*L84 -> 0 | O84: =IFERROR((VLOOKUP(H84,Tránsito!A:D,4,0)),"0") -> 0 | P84: 0 | Q84: =P84*O84 -> 0 | S84: 0 | T84: =S84*R84 -> 0 | V84: 43952.555 | W84: =V84*U84 -> 0 | X84: =IFERROR((VLOOKUP(H84,'Entregado (2026)'!A:C,3,0)),"0") -> 0 | Y84: 43944.303 | Z84: =Y84*X84 -> 0 | AB84: =Y84 -> 43944.303 | AC84: =AB84*AA84 -> 0 | AE84: 0 | AF84: =AE84*AD84 -> 0 | AG84: =IFERROR((VLOOKUP(H84,'Ventas (2025)'!A:C,3,0)),"0") -> 0 | AH84: 43944.303 | AI84: =AH84*AG84 -> 0 | AM84: =AL84*AK84 -> 0
A85: 70 | B85: 70100200 | C85: Venta | D85: Hiab | E85: 248 | F85: GRUA ARTICULADA HIAB X-CLX 248 EP-4 MARINA | G85: No | H85: 70100200 | I85: 0 | J85: =IFERROR((VLOOKUP(B85,Stock!A:C,3,0)),"0") -> 0 | K85: =J85*I85 -> 0 | L85: =IFERROR((VLOOKUP(H85,Tránsito!A:C,3,0)),"0") -> 0 | M85: 0 | N85: =M85*L85 -> 0 | O85: =IFERROR((VLOOKUP(H85,Tránsito!A:D,4,0)),"0") -> 0 | P85: 0 | Q85: =P85*O85 -> 0 | S85: 0 | T85: =S85*R85 -> 0 | V85: 0 | W85: =V85*U85 -> 0 | X85: =IFERROR((VLOOKUP(H85,'Entregado (2026)'!A:C,3,0)),"0") -> 0 | Y85: 43944.303 | Z85: =Y85*X85 -> 0 | AB85: =Y85 -> 43944.303 | AC85: =AB85*AA85 -> 0 | AE85: 55000 | AF85: =AE85*AD85 -> 0 | AG85: =IFERROR((VLOOKUP(H85,'Ventas (2025)'!A:C,3,0)),"0") -> 1 | AH85: 43944.303 | AI85: =AH85*AG85 -> 43944.303 | AM85: =AL85*AK85 -> 0
A86: 71 | B86: 13171050 | C86: Compra | D86: Hiab | E86: 232 | F86: GRÚA ARTICULADA HIAB EX 232 HIPRO E5 ELÉCTRICA | G86: No | H86: 13171050 | J86: =IFERROR((VLOOKUP(B86,Stock!A:C,3,0)),"0") -> 0 | K86: =J86*I86 -> 0 | L86: =IFERROR((VLOOKUP(H86,Tránsito!A:C,3,0)),"0") -> 0 | N86: =M86*L86 -> 0 | O86: =IFERROR((VLOOKUP(H86,Tránsito!A:D,4,0)),"0") -> 1 | P86: 72075 | Q86: =P86*O86 -> 72075 | S86: 90980 | T86: =S86*R86 -> 0 | W86: =V86*U86 -> 0 | X86: =IFERROR((VLOOKUP(H86,'Entregado (2026)'!A:C,3,0)),"0") -> 0 | Z86: =Y86*X86 -> 0 | AC86: =AB86*AA86 -> 0 | AF86: =AE86*AD86 -> 0 | AG86: =IFERROR((VLOOKUP(H86,'Ventas (2025)'!A:C,3,0)),"0") -> 0 | AH86: 0 | AI86: =AH86*AG86 -> 0 | AM86: =AL86*AK86 -> 0
A87: 72 | B87: 70502121 | C87: Venta | D87: Hiab | E87: 201 | F87: GRUA ARTICULADA HIAB SEA CRANE 201-3 | G87: No | H87: 70502121 | I87: 0 | J87: =IFERROR((VLOOKUP(B87,Stock!A:C,3,0)),"0") -> 0 | K87: =J87*I87 -> 0 | L87: =IFERROR((VLOOKUP(H87,Tránsito!A:C,3,0)),"0") -> 0 | M87: 0 | N87: =M87*L87 -> 0 | O87: =IFERROR((VLOOKUP(H87,Tránsito!A:D,4,0)),"0") -> 0 | P87: 0 | Q87: =P87*O87 -> 0 | S87: 0 | T87: =S87*R87 -> 0 | V87: 0 | W87: =V87*U87 -> 0 | X87: =IFERROR((VLOOKUP(H87,'Entregado (2026)'!A:C,3,0)),"0") -> 0 | Y87: 135941.29 | Z87: =Y87*X87 -> 0 | AB87: =Y87 -> 135941.29 | AC87: =AB87*AA87 -> 0 | AD87: 4 | AE87: 61200 | AF87: =AE87*AD87 -> 244800 | AG87: =IFERROR((VLOOKUP(H87,'Ventas (2025)'!A:C,3,0)),"0") -> 0 | AH87: 135941.29 | AI87: =AH87*AG87 -> 0 | AM87: =AL87*AK87 -> 0
A88: 73 | B88: 13171054 | C88: Compra | D88: Hiab | E88: 201 | F88: GRUA ARTICULADA HIAB SEA CRANE 201-3 | G88: No | H88: 13171054 | I88: 53205.641 | J88: =IFERROR((VLOOKUP(B88,Stock!A:C,3,0)),"0") -> 1 | K88: =J88*I88 -> 53205.641 | L88: =IFERROR((VLOOKUP(H88,Tránsito!A:C,3,0)),"0") -> 0 | M88: 0 | N88: =M88*L88 -> 0 | O88: =IFERROR((VLOOKUP(H88,Tránsito!A:D,4,0)),"0") -> 0 | P88: 0 | Q88: =P88*O88 -> 0 | S88: 0 | T88: =S88*R88 -> 0 | V88: 0 | W88: =V88*U88 -> 0 | X88: =IFERROR((VLOOKUP(H88,'Entregado (2026)'!A:C,3,0)),"0") -> 0 | Y88: 135941.29 | Z88: =Y88*X88 -> 0 | AB88: =Y88 -> 135941.29 | AC88: =AB88*AA88 -> 0 | AE88: 0 | AF88: =AE88*AD88 -> 0 | AG88: =IFERROR((VLOOKUP(H88,'Ventas (2025)'!A:C,3,0)),"0") -> 0 | AH88: 135941.29 | AI88: =AH88*AG88 -> 0 | AM88: =AL88*AK88 -> 0
A89: 74 | B89: | | C89: Compra | D89: Hiab | E89: 188 | F89: GRUA ARTICULADA HIAB X-HIDUO 188 E-5 | G89: No | H89: 13171039 | I89: 51376.467 | J89: =IFERROR((VLOOKUP(B89,Stock!A:C,3,0)),"0") -> 0 | K89: =J89*I89 -> 0 | L89: =IFERROR((VLOOKUP(H89,Tránsito!A:C,3,0)),"0") -> 0 | M89: 0 | N89: =M89*L89 -> 0 | O89: =IFERROR((VLOOKUP(H89,Tránsito!A:D,4,0)),"0") -> 0 | P89: 0 | Q89: =P89*O89 -> 0 | S89: 49653.1 | T89: =S89*R89 -> 0 | U89: 3 | V89: 87315 | W89: =V89*U89 -> 261945 | X89: =IFERROR((VLOOKUP(H89,'Entregado (2026)'!A:C,3,0)),"0") -> 0 | Y89: 87278 | Z89: =Y89*X89 -> 0 | AC89: =AB89*AA89 -> 0 | AE89: 0 | AF89: =AE89*AD89 -> 0 | AG89: =IFERROR((VLOOKUP(H89,'Ventas (2025)'!A:C,3,0)),"0") -> 0 | AH89: 0 | AI89: =AH89*AG89 -> 0 | AM89: =AL89*AK89 -> 0
A90: 75 | B90: 70100259 | C90: Venta | D90: Hiab | E90: 188 | F90: CAMION GRUA ARTICULADA HIAB X-HIDUO 188 E5 | G90: Sí | H90: 70100259 | I90: 240598 | J90: =IFERROR((VLOOKUP(B90,Stock!A:C,3,0)),"0") -> 1 | K90: =J90*I90 -> 240598 | L90: =IFERROR((VLOOKUP(H90,Tránsito!A:C,3,0)),"0") -> 0 | M90: 0 | N90: =M90*L90 -> 0 | O90: =IFERROR((VLOOKUP(H90,Tránsito!A:D,4,0)),"0") -> 0 | P90: 0 | Q90: =P90*O90 -> 0 | S90: 0 | T90: =S90*R90 -> 0 | V90: 291327 | W90: =V90*U90 -> 0 | X90: =IFERROR((VLOOKUP(H90,'Entregado (2026)'!A:C,3,0)),"0") -> 0 | Y90: 291256.26 | Z90: =Y90*X90 -> 0 | AC90: =AB90*AA90 -> 0 | AE90: 0 | AF90: =AE90*AD90 -> 0 | AG90: =IFERROR((VLOOKUP(H90,'Ventas (2025)'!A:C,3,0)),"0") -> 1 | AH90: 291256.26 | AI90: =AH90*AG90 -> 291256.26 | AM90: =AL90*AK90 -> 0
A91: 76 | B91: 70100251 | C91: Venta | D91: Hiab | E91: 188 | F91: GRUA ARTICULADA HIAB X-HIDUO 188 E-5 | G91: No | H91: 70100251 | I91: 0 | J91: =IFERROR((VLOOKUP(B91,Stock!A:C,3,0)),"0") -> 0 | K91: =J91*I91 -> 0 | L91: =IFERROR((VLOOKUP(H91,Tránsito!A:C,3,0)),"0") -> 0 | M91: 0 | N91: =M91*L91 -> 0 | O91: =IFERROR((VLOOKUP(H91,Tránsito!A:D,4,0)),"0") -> 0 | P91: 0 | Q91: =P91*O91 -> 0 | S91: 0 | T91: =S91*R91 -> 0 | V91: 0 | W91: =V91*U91 -> 0 | X91: =IFERROR((VLOOKUP(H91,'Entregado (2026)'!A:C,3,0)),"0") -> 1 | Y91: =VLOOKUP(F91,'Entregado (2026)'!$B:$D,3,0) -> 87277.857 | Z91: =Y91*X91 -> 87277.857 | AB91: 119865 | AC91: =AB91*AA91 -> 0 | AD91: 7 | AE91: 86355 | AF91: =AE91*AD91 -> 604485 | AG91: =IFERROR((VLOOKUP(H91,'Ventas (2025)'!A:C,3,0)),"0") -> 1 | AH91: 0 | AI91: =AH91*AG91 -> 0 | AM91: =AL91*AK91 -> 0
A92: 77 | B92: 13171027 | C92: Compra | D92: Hiab | E92: 188 | F92: HIAB iX188 EP-5 | G92: No | H92: 13171027 | I92: 55192.327 | J92: 1 | K92: =J92*I92 -> 55192.327 | L92: 4 | M92: 57304 | N92: =M92*L92 -> 229216 | O92: 3 | P92: 57304 | Q92: =P92*O92 -> 171912 | S92: 51090 | T92: =S92*R92 -> 0 | W92: =V92*U92 -> 0 | X92: =IFERROR((VLOOKUP(H92,'Entregado (2026)'!A:C,3,0)),"0") -> 0 | Z92: =Y92*X92 -> 0 | AC92: =AB92*AA92 -> 0 | AF92: =AE92*AD92 -> 0 | AG92: =IFERROR((VLOOKUP(H92,'Ventas (2025)'!A:C,3,0)),"0") -> 0 | AH92: 0 | AI92: =AH92*AG92 -> 0 | AM92: =AL92*AK92 -> 0
A93: 78 | B93: 13171053 | C93: Compra | D93: Hiab | E93: 178 | F93: GRUA ARTICULADA HIAB X-CLX 178 E-4 | G93: No | H93: 13171053 | I93: 46338.739 | J93: =IFERROR((VLOOKUP(B93,Stock!A:C,3,0)),"0") -> 0 | K93: =J93*I93 -> 0 | L93: =IFERROR((VLOOKUP(H93,Tránsito!A:C,3,0)),"0") -> 0 | M93: 0 | N93: =M93*L93 -> 0 | O93: =IFERROR((VLOOKUP(H93,Tránsito!A:D,4,0)),"0") -> 0 | P93: 0 | Q93: =P93*O93 -> 0 | S93: 0 | T93: =S93*R93 -> 0 | V93: 91722 | W93: =V93*U93 -> 0 | X93: =IFERROR((VLOOKUP(H93,'Entregado (2026)'!A:C,3,0)),"0") -> 0 | Y93: 89935 | Z93: =Y93*X93 -> 0 | AB93: 77750 | AC93: =AB93*AA93 -> 0 | AE93: 0 | AF93: =AE93*AD93 -> 0 | AG93: =IFERROR((VLOOKUP(H93,'Ventas (2025)'!A:C,3,0)),"0") -> 0 | AH93: 95475.23 | AI93: =AH93*AG93 -> 0 | AM93: =AL93*AK93 -> 0
A94: 79 | B94: 70100249 | C94: Venta | D94: Hiab | E94: 178 | F94: GRUA ARTICULADA HIAB X-CLX 178 E-4 | G94: No | H94: 70100249 | I94: 0 | J94: =IFERROR((VLOOKUP(B94,Stock!A:C,3,0)),"0") -> 0 | K94: =J94*I94 -> 0 | L94: =IFERROR((VLOOKUP(H94,Tránsito!A:C,3,0)),"0") -> 0 | M94: 0 | N94: =M94*L94 -> 0 | O94: =IFERROR((VLOOKUP(H94,Tránsito!A:D,4,0)),"0") -> 0 | P94: 0 | Q94: =P94*O94 -> 0 | S94: 0 | T94: =S94*R94 -> 0 | V94: 0 | W94: =V94*U94 -> 0 | X94: =IFERROR((VLOOKUP(H94,'Entregado (2026)'!A:C,3,0)),"0") -> 2 | Y94: 76733 | Z94: =Y94*X94 -> 153466 | AC94: =AB94*AA94 -> 0 | AE94: 0 | AF94: =AE94*AD94 -> 0 | AG94: =IFERROR((VLOOKUP(H94,'Ventas (2025)'!A:C,3,0)),"0") -> 9 | AH94: 95475.23 | AI94: =AH94*AG94 -> 859277.07 | AM94: =AL94*AK94 -> 0
A95: 80 | B95: 70100276 | C95: Venta | D95: Hiab | E95: 178 | F95: CAMION GRUA ARTICULADA HIAB X-CLX 178 E-4 | G95: Sí | H95: 70100276 | I95: 134207 | J95: =IFERROR((VLOOKUP(B95,Stock!A:C,3,0)),"0") -> 1 | K95: =J95*I95 -> 134207 | L95: =IFERROR((VLOOKUP(H95,Tránsito!A:C,3,0)),"0") -> 0 | M95: 173099 | N95: =M95*L95 -> 0 | O95: =IFERROR((VLOOKUP(H95,Tránsito!A:D,4,0)),"0") -> 0 | P95: 173099 | Q95: =P95*O95 -> 0 | S95: 0 | T95: =S95*R95 -> 0 | V95: 0 | W95: =V95*U95 -> 0 | X95: =IFERROR((VLOOKUP(H95,'Entregado (2026)'!A:C,3,0)),"0") -> 0 | Y95: 204019.29 | Z95: =Y95*X95 -> 0 | AB95: =Y95 -> 204019.29 | AC95: =AB95*AA95 -> 0 | AE95: 85000 | AF95: =AE95*AD95 -> 0 | AG95: =IFERROR((VLOOKUP(H95,'Ventas (2025)'!A:C,3,0)),"0") -> 0 | AH95: 248045.42 | AI95: =AH95*AG95 -> 0 | AM95: =AL95*AK95 -> 0
A96: 81 | B96: 70100234 | C96: Venta | D96: Hiab | E96: 148 | F96: GRUA ARTICULADA HIAB X-CLX 148 B-3 | G96: No | H96: 70100234 | I96: 0 | J96: =IFERROR((VLOOKUP(B96,Stock!A:C,3,0)),"0") -> 0 | K96: =J96*I96 -> 0 | L96: =IFERROR((VLOOKUP(H96,Tránsito!A:C,3,0)),"0") -> 0 | M96: 0 | N96: =M96*L96 -> 0 | O96: =IFERROR((VLOOKUP(H96,Tránsito!A:D,4,0)),"0") -> 0 | P96: 0 | Q96: =P96*O96 -> 0 | S96: 0 | T96: =S96*R96 -> 0 | V96: 0 | W96: =V96*U96 -> 0 | X96: =IFERROR((VLOOKUP(H96,'Entregado (2026)'!A:C,3,0)),"0") -> 0 | Y96: 0 | Z96: =Y96*X96 -> 0 | AB96: =Y96 -> 0 | AC96: =AB96*AA96 -> 0 | AE96: 0 | AF96: =AE96*AD96 -> 0 | AG96: =IFERROR((VLOOKUP(H96,'Ventas (2025)'!A:C,3,0)),"0") -> 0 | AH96: 0 | AI96: =AH96*AG96 -> 0 | AM96: =AL96*AK96 -> 0
A97: 82 | B97: 13171034 | C97: Compra | D97: Hiab | E97: 88 | F97: HIAB X-CLX 088 E-4 | G97: No | H97: 13171034 | I97: 0 | J97: =IFERROR((VLOOKUP(B97,Stock!A:C,3,0)),"0") -> 0 | K97: =J97*I97 -> 0 | L97: =IFERROR((VLOOKUP(H97,Tránsito!A:C,3,0)),"0") -> 0 | M97: 0 | N97: =M97*L97 -> 0 | O97: =IFERROR((VLOOKUP(H97,Tránsito!A:D,4,0)),"0") -> 0 | P97: 0 | Q97: =P97*O97 -> 0 | S97: 0 | T97: =S97*R97 -> 0 | V97: 0 | W97: =V97*U97 -> 0 | X97: =IFERROR((VLOOKUP(H97,'Entregado (2026)'!A:C,3,0)),"0") -> 0 | Y97: 0 | Z97: =Y97*X97 -> 0 | AB97: =Y97 -> 0 | AC97: =AB97*AA97 -> 0 | AE97: 0 | AF97: =AE97*AD97 -> 0 | AG97: =IFERROR((VLOOKUP(H97,'Ventas (2025)'!A:C,3,0)),"0") -> 0 | AH97: 0 | AI97: =AH97*AG97 -> 0 | AM97: =AL97*AK97 -> 0
A98: 83 | B98: 70100225 | C98: Venta | D98: Hiab | E98: 88 | F98: GRUA ARTICULADA HIAB X-CLX 088 E-4 | G98: No | H98: 70100225 | I98: 0 | J98: =IFERROR((VLOOKUP(B98,Stock!A:C,3,0)),"0") -> 0 | K98: =J98*I98 -> 0 | L98: =IFERROR((VLOOKUP(H98,Tránsito!A:C,3,0)),"0") -> 0 | M98: 65629.41 | N98: =M98*L98 -> 0 | O98: =IFERROR((VLOOKUP(H98,Tránsito!A:D,4,0)),"0") -> 0 | P98: 65629.41 | Q98: =P98*O98 -> 0 | S98: 0 | T98: =S98*R98 -> 0 | V98: 65621 | W98: =V98*U98 -> 0 | X98: =IFERROR((VLOOKUP(H98,'Entregado (2026)'!A:C,3,0)),"0") -> 0 | Y98: 65621 | Z98: =Y98*X98 -> 0 | AB98: =Y98 -> 65621 | AC98: =AB98*AA98 -> 0 | AD98: 2 | AE98: 46800 | AF98: =AE98*AD98 -> 93600 | AG98: =IFERROR((VLOOKUP(H98,'Ventas (2025)'!A:C,3,0)),"0") -> 1 | AH98: 65629.41 | AI98: =AH98*AG98 -> 65629.41 | AM98: =AL98*AK98 -> 0
A99: 84 | B99: 70100250 | C99: Venta | D99: Hiab | E99: 88 | F99: GRUA ARTICULADA HIAB X-CLX 088 E-3 | G99: No | H99: 70100250 | I99: 0 | J99: =IFERROR((VLOOKUP(B99,Stock!A:C,3,0)),"0") -> 0 | K99: =J99*I99 -> 0 | L99: =IFERROR((VLOOKUP(H99,Tránsito!A:C,3,0)),"0") -> 0 | M99: 0 | N99: =M99*L99 -> 0 | O99: =IFERROR((VLOOKUP(H99,Tránsito!A:D,4,0)),"0") -> 0 | P99: 0 | Q99: =P99*O99 -> 0 | S99: 0 | T99: =S99*R99 -> 0 | V99: 0 | W99: =V99*U99 -> 0 | X99: =IFERROR((VLOOKUP(H99,'Entregado (2026)'!A:C,3,0)),"0") -> 0 | Y99: 0 | Z99: =Y99*X99 -> 0 | AB99: =Y99 -> 0 | AC99: =AB99*AA99 -> 0 | AE99: 53000 | AF99: =AE99*AD99 -> 0 | AG99: =IFERROR((VLOOKUP(H99,'Ventas (2025)'!A:C,3,0)),"0") -> 0 | AH99: 0 | AI99: =AH99*AG99 -> 0 | AM99: =AL99*AK99 -> 0
A100: 85 | B100: 13171048 | C100: Compra | D100: Hiab | E100: 88 | F100: HIAB X-CLX 088 E-3 | G100: No | H100: 13171048 | I100: 25888.557 | J100: =IFERROR((VLOOKUP(B100,Stock!A:C,3,0)),"0") -> 0 | K100: =J100*I100 -> 0 | L100: =IFERROR((VLOOKUP(H100,Tránsito!A:C,3,0)),"0") -> 0 | M100: 0 | N100: =M100*L100 -> 0 | O100: =IFERROR((VLOOKUP(H100,Tránsito!A:D,4,0)),"0") -> 0 | P100: 0 | Q100: =P100*O100 -> 0 | S100: 0 | T100: =S100*R100 -> 0 | V100: 0 | W100: =V100*U100 -> 0 | X100: =IFERROR((VLOOKUP(H100,'Entregado (2026)'!A:C,3,0)),"0") -> 0 | Y100: 0 | Z100: =Y100*X100 -> 0 | AB100: =Y100 -> 0 | AC100: =AB100*AA100 -> 0 | AE100: 0 | AF100: =AE100*AD100 -> 0 | AG100: =IFERROR((VLOOKUP(H100,'Ventas (2025)'!A:C,3,0)),"0") -> 0 | AH100: 0 | AI100: =AH100*AG100 -> 0 | AM100: =AL100*AK100 -> 0
A101: 86 | B101: 70100290 | C101: Venta | D101: Hiab | E101: 44 | F101: GRUA ARTICULADA HIAB X-CLX 044 D-3 | G101: No | H101: 70100290 | I101: 0 | J101: =IFERROR((VLOOKUP(B101,Stock!A:C,3,0)),"0") -> 0 | K101: =J101*I101 -> 0 | L101: =IFERROR((VLOOKUP(H101,Tránsito!A:C,3,0)),"0") -> 0 | M101: 0 | N101: =M101*L101 -> 0 | O101: =IFERROR((VLOOKUP(H101,Tránsito!A:D,4,0)),"0") -> 0 | P101: 0 | Q101: =P101*O101 -> 0 | S101: 0 | T101: =S101*R101 -> 0 | V101: 32988.109 | W101: =V101*U101 -> 0 | X101: =IFERROR((VLOOKUP(H101,'Entregado (2026)'!A:C,3,0)),"0") -> 0 | Y101: 32988.109 | Z101: =Y101*X101 -> 0 | AB101: =Y101 -> 32988.109 | AC101: =AB101*AA101 -> 0 | AE101: 0 | AF101: =AE101*AD101 -> 0 | AG101: =IFERROR((VLOOKUP(H101,'Ventas (2025)'!A:C,3,0)),"0") -> 0 | AH101: 32988.109 | AI101: =AH101*AG101 -> 0 | AM101: =AL101*AK101 -> 0
A102: 87 | B102: 70100184 | C102: Venta | D102: Hiab | E102: 29 | F102: GRUA ARTICULADA HIAB T-CLX 029 B-3 | G102: No | H102: 70100184 | I102: 0 | J102: =IFERROR((VLOOKUP(B102,Stock!A:C,3,0)),"0") -> 0 | K102: =J102*I102 -> 0 | L102: =IFERROR((VLOOKUP(H102,Tránsito!A:C,3,0)),"0") -> 0 | M102: 0 | N102: =M102*L102 -> 0 | O102: =IFERROR((VLOOKUP(H102,Tránsito!A:D,4,0)),"0") -> 0 | P102: 0 | Q102: =P102*O102 -> 0 | S102: 0 | T102: =S102*R102 -> 0 | V102: 17986 | W102: =V102*U102 -> 0 | X102: =IFERROR((VLOOKUP(H102,'Entregado (2026)'!A:C,3,0)),"0") -> 0 | Y102: 17986 | Z102: =Y102*X102 -> 0 | AB102: =Y102 -> 17986 | AC102: =AB102*AA102 -> 0 | AE102: 0 | AF102: =AE102*AD102 -> 0 | AG102: =IFERROR((VLOOKUP(H102,'Ventas (2025)'!A:C,3,0)),"0") -> 0 | AH102: 17986 | AI102: =AH102*AG102 -> 0 | AM102: =AL102*AK102 -> 0
A103: 88 | B103: 70100289 | C103: Venta | D103: Hiab | E103: 23 | F103: GRUA ARTICULADA HIAB X-CL 23 B-4 | G103: No | H103: 70100289 | I103: 0 | J103: =IFERROR((VLOOKUP(B103,Stock!A:C,3,0)),"0") -> 0 | K103: =J103*I103 -> 0 | L103: =IFERROR((VLOOKUP(H103,Tránsito!A:C,3,0)),"0") -> 0 | M103: 0 | N103: =M103*L103 -> 0 | O103: =IFERROR((VLOOKUP(H103,Tránsito!A:D,4,0)),"0") -> 0 | P103: 0 | Q103: =P103*O103 -> 0 | S103: 0 | T103: =S103*R103 -> 0 | V103: 0 | W103: =V103*U103 -> 0 | X103: =IFERROR((VLOOKUP(H103,'Entregado (2026)'!A:C,3,0)),"0") -> 1 | Y103: =VLOOKUP(F103,'Entregado (2026)'!$B:$D,3,0) -> 39031.678 | Z103: =Y103*X103 -> 39031.678 | AB103: =Y103 -> 39031.678 | AC103: =AB103*AA103 -> 0 | AD103: 6 | AE103: 33300 | AF103: =AE103*AD103 -> 199800 | AG103: =IFERROR((VLOOKUP(H103,'Ventas (2025)'!A:C,3,0)),"0") -> 5 | AH103: 37234.824 | AI103: =AH103*AG103 -> 186174.12 | AM103: =AL103*AK103 -> 0
...

Sheet Glosario códigos
A4: # | B4: Código | C4: Origen | D4: Familia | E4: Subfamilia | F4: Descripción | G4: Sobre camión | H4: Código | I4: Subfamilia
A5: 1 | B5: 13171051 | C5: Compra | D5: Hiab | E5: 1188 | F5: GRUA ARTICULADA HIAB IQ 1188 E-9 JIB | G5: No | H5: 13171051 | I5: 1188
A6: 2 | B6: 70100247 | C6: Venta | D6: Hiab | E6: 1188 | F6: GRUA ARTICULADA HIAB IQ 1188 E-9 JIB | G6: No | H6: 70100247 | I6: 1188
A7: 3 | B7: 13171068 | C7: Compra | D7: Hiab | E7: 1188 | F7: GRUA ARTICULADA HIAB IQ 1188 E-8 HIPRO EVO | G7: No | H7: 13171068 | I7: 1188
A8: 4 | B8: 79001005 | C8: Venta | D8: Effer | E8: 1000 | F8: GRUA ARTICULADA EFFER 1000 9S TC JIB | G8: No | H8: 79001005 | I8: 1000
A9: 5 | B9: 13171055 | C9: Compra | D9: Effer | E9: 1000 | F9: GRUA ARTICULADA EFFER 1000 9S TC JIB | G9: No | H9: 13171055 | I9: 1000
A10: 6 | B10: 79001006 | C10: Venta | D10: Hiab | E10: 1000 | F10: CAMION GRUA ARTICULADA EFFER 1000 9S TC JIB | G10: Sí | H10: 79001006 | I10: 1000
A11: 7 | B11: 13171012 | C11: Compra | D11: Hiab | E11: 858 | F11: GRUA ARTICULADA HIAB X-HIPRO 858 E-8 | G11: No | H11: 13171012 | I11: 858
A12: 8 | B12: 70100211 | C12: Venta | D12: Hiab | E12: 858 | F12: GRUA ARTICULADA HIAB X-HIPRO 858 E-10 | G12: No | H12: 70100211 | I12: 858
A13: 9 | B13: 70100221 | C13: Venta | D13: Hiab | E13: 858 | F13: GRUA ARTICULADA HIAB X-HIPRO 858 E-8 | G13: No | H13: 70100221 | I13: 858
A14: 10 | B14: 70100212 | C14: Venta | D14: Hiab | E14: 638 | F14: GRUA ARTICULADA HIAB X-HIPRO 638 E-9 | G14: No | H14: 70100212 | I14: 638
A15: 11 | B15: 13171033 | C15: Compra | D15: Hiab | E15: 638 | F15: GRUA ARTICULADA HIAB X-HIPRO 638 E-9 | G15: No | H15: 13171033 | I15: 638
A16: 12 | B16: 70100213 | C16: Venta | D16: Hiab | E16: 638 | F16: CAMION GRUA ARTICULADA HIAB X-HIPRO 638 E-9 | G16: Sí | H16: 70100213 | I16: 638
A17: 13 | B17: 13171066 | C17: Compra | D17: Hiab | E17: 638 | F17: HIAB 638 EP9 (EVO) | G17: No | H17: 13171066 | I17: 638
A18: 14 | B18: 19601036 | C18: Compra | D18: Hiab | E18: 558 | F18: GRUA ARTICULADA HIAB X-HIPRO 558 EP-6 | G18: No | H18: 19601036 | I18: 558
A19: 15 | B19: 19601024 | C19: Compra | D19: Hiab | E19: 558 | F19: GRUA ARTICULADA HIAB X-HIPRO 558 EP-5 | G19: No | H19: 19601024 | I19: 558
A20: 16 | B20: 70100206 | C20: Venta | D20: Hiab | E20: 558 | F20: GRUA ARTICULADA HIAB X-HIPRO 558 EP-5 | G20: No | H20: 70100206 | I20: 558
A21: 17 | B21: 70100275 | C21: Venta | D21: Hiab | E21: 558 | F21: GRUA ARTICULADA HIAB X HIPRO 558 EP6 | G21: No | H21: 70100275 | I21: 558
A22: 18 | B22: 13171064 | C22: Compra | D22: Hiab | E22: 558 | F22: Hiab 558 EP5 - EVO | G22: No | H22: 13171064 | I22: 558
A23: 19 | C23: Venta | D23: Hiab | E23: 558 | F23: CAMION GRUA ARTICULADA HIAB X-HIPRO 558 EP-5 | G23: Sí | I23: 558
A24: 20 | B24: 70901020 | C24: Venta | D24: Hiab | E24: 548 | F24: CAMION GRUA ARTICULADA HIAB X-HIPRO 548 E-9 | G24: Sí | H24: 70901020 | I24: 548
A25: 21 | B25: 70100205 | C25: Venta | D25: Hiab | E25: 548 | F25: GRUA ARTICULADA HIAB X-HIPRO 548 E-9 | G25: No | H25: 70100205 | I25: 548
A26: 22 | B26: 19502041 | C26: Compra | D26: Hiab | E26: 548 | F26: HIAB X-HIPRO 548 E-9 | G26: No | H26: 19502041 | I26: 548
A27: 23 | B27: 19502062 | C27: Compra | D27: Hiab | E27: 548 | F27: GRUA ARTICULADA HIAB X-HIPRO 548 E-9 año 2022 | G27: No | H27: 19502062 | I27: 548
A28: 24 | B28: 13171065 | C28: Compra | D28: Hiab | E28: 548 | F28: HIAB 548 EP 9 (EVO) | G28: No | H28: 13171065 | I28: 548
A29: 25 | B29: 13171022 | C29: Compra | D29: Hiab | E29: 418 | F29: HIAB X-HIPRO 418 EP-5 | G29: No | H29: 13171022 | I29: 418
A30: 26 | B30: 70100165 | C30: Venta | D30: Hiab | E30: 418 | F30: GRUA ARTICULADA HIAB X-HIPRO 418 EP-5 | G30: No | H30: 70100165 | I30: 418
A31: 27 | B31: 70100173 | C31: Venta | D31: Hiab | E31: 418 | F31: CAMION GRUA ARTICULADA HIAB X-HIPRO 418 EP-5 | G31: Sí | H31: 70100173 | I31: 418
A32: 28 | B32: 70100164 | C32: Venta | D32: Hiab | E32: 408 | F32: GRUA ARTICULADA HIAB X-HIPRO 408 E-8 | G32: No | H32: 70100164 | I32: 408
A33: 29 | B33: 13171021 | C33: Compra | D33: Hiab | E33: 408 | F33: HIAB X-HIPRO 408 E-8 | G33: No | H33: 13171021 | I33: 408
A34: 30 | C34: Venta | D34: Hiab | E34: 408 | F34: CAMION GRUA HIAB X-HIPRO 408 E8 | G34: Sí | I34: 408
A35: 31 | C35: Venta | D35: Hiab | E35: 408 | F35: GRUA ARTICULADA HIAB X-HIPRO 408 E-8 + MULTILIFT OPTIMA 20S | G35: No | I35: 408
A36: 32 | B36: 10705003 | C36: Compra | D36: Hiab | E36: 388 | F36: GRUA HIAB X-CLX 388 EP5 | G36: No | H36: 10705003 | I36: 388
A37: 33 | B37: 70100253 | C37: Venta | D37: Hiab | E37: 388 | F37: GRUA HIAB X-CLX 388 EP5 | G37: No | H37: 70100253 | I37: 388
A38: 34 | B38: 70901021 | C38: Venta | D38: Hiab | E38: 362 | F38: CAMION GRUA ARTICULADA HIAB X-HIPRO 362 EP-5 | G38: Sí | H38: 70901021 | I38: 362
A39: 35 | B39: 13171020 | C39: Compra | D39: Hiab | E39: 362 | F39: GRUA ARTICULADA HIAB X-HIPRO 362 EP-5 | G39: No | H39: 13171020 | I39: 362
A40: 36 | B40: 70100171 | C40: Venta | D40: Hiab | E40: 362 | F40: GRUA ARTICULADA HIAB X-HIPRO 362 EP-5 | G40: No | H40: 70100171 | I40: 362
A41: 37 | B41: 13171063 | C41: Compra | D41: Hiab | E41: 362 | F41: Hiab 362 EP5 - EVO | G41: No | H41: 13171063 | I41: 362
A42: 38 | B42: 13171067 | C42: Compra | D42: Hiab | E42: 355 | F42: GRUA ARTICULADA EFFER IX 355 E-8 HIPRO | G42: No | H42: 13171067 | I42: 355
A43: 39 | B43: 70100222 | C43: Venta | D43: Hiab | E43: 352 | F43: GRUA ARTICULADA HIAB X-HIPRO 352 E-6 | G43: No | H43: 70100222 | I43: 352
A44: 40 | B44: 70100232 | C44: Venta | D44: Hiab | E44: 352 | F44: GRUA ARTICULADA HIAB X-HIPRO 352 E-8 | G44: No | H44: 70100232 | I44: 352
A45: 41 | B45: 13171045 | C45: Compra | D45: Hiab | E45: 352 | F45: GRUA ARTICULADA HIAB X-HIPRO 352 E-8 | G45: No | H45: 13171045 | I45: 352
A46: 42 | B46: 70100220 | C46: Venta | D46: Hiab | E46: 352 | F46: CAMION GRUA ARTICULADA HIAB X-HIPRO 352 E-6 | G46: Sí | H46: 70100220 | I46: 352
A47: 43 | B47: 70100231 | C47: Venta | D47: Hiab | E47: 328 | F47: GRUA ARTICULADA HIAB X-CLX 328 EP-5 MARINA | G47: No | H47: 70100231 | I47: 328
A48: 44 | B48: 13171041 | C48: Compra | D48: Hiab | E48: 328 | F48: GRUA ARTICULADA HIAB X-CLX 328 EP-5 MARINA | G48: No | H48: 13171041 | I48: 328
A49: 45 | B49: 13171030 | C49: Compra | D49: Hiab | E49: 328 | F49: HIAB X-CLX 328 EP-5 | G49: No | H49: 13171030 | I49: 328
A50: 46 | B50: 13171018 | C50: Compra | D50: Hiab | E50: 302 | F50: HIAB X-HIPRO 302 E-8 | G50: No | H50: 13171018 | I50: 302
A51: 47 | B51: 70100169 | C51: Venta | D51: Hiab | E51: 302 | F51: GRUA ARTICULADA HIAB X-HIPRO 302 E-8 | G51: No | H51: 70100169 | I51: 302
A52: 48 | B52: 70100167 | C52: Venta | D52: Hiab | E52: 298 | F52: GRUA ARTICULADA HIAB X-HIDUO 298 EP-5 | G52: No | H52: 70100167 | I52: 298
A53: 49 | B53: 13171023 | C53: Compra | D53: Hiab | E53: 298 | F53: HIAB iX298 EP-5 | G53: No | H53: 13171023 | I53: 298
A54: 50 | B54: 70100258 | C54: Venta | D54: Hiab | E54: 298 | F54: CAMION GRUA HIAB X HIDUO 298 EP5 | G54: Sí | H54: 70100258 | I54: 298
A55: 51 | B55: 70100215 | C55: Venta | D55: Hiab | E55: 298 | F55: CAMIÓN GRUA ARTICULADA HIAB 298 EP5 | G55: Sí | H55: 70100215 | I55: 298
A56: 52 | B56: 13171024 | C56: Compra | D56: Hiab | E56: 288 | F56: GRUA ARTICULADA HIAB X-CLX 288 EP-4 MARINA | G56: No | H56: 13171024 | I56: 288
A57: 53 | B57: 13171059 | C57: Compra | D57: Hiab | E57: 288 | F57: GRUA ARTICULADA HIAB X-CLX 288 EP-5 MARINA | G57: No | H57: 13171059 | I57: 288
A58: 54 | B58: 70100195 | C58: Venta | D58: Hiab | E58: 288 | F58: GRUA ARTICULADA HIAB X-CLX 288 EP-4 MARINA | G58: No | H58: 70100195 | I58: 288
A59: 55 | B59: 70100170 | C59: Venta | D59: Hiab | E59: 258 | F59: CAMION GRUA ARTICULADA HIAB X-HIDUO 258 EP-5 | G59: Sí | H59: 70100170 | I59: 258
A60: 56 | B60: 13171016 | C60: Compra | D60: Hiab | E60: 258 | F60: HIAB X-HIDUO 258 EP-5 | G60: No | H60: 13171016 | I60: 258
A61: 57 | B61: 70100166 | C61: Venta | D61: Hiab | E61: 258 | F61: GRUA ARTICULADA HIAB X-HIDUO 258 EP-5 | G61: No | H61: 70100166 | I61: 258
A62: 58 | B62: 13171028 | C62: Compra | D62: Hiab | E62: 248 | F62: GRUA ARTICULADA HIAB X-CLX 248 EP-4 MARINA | G62: No | H62: 13171028 | I62: 248
A63: 59 | B63: 70100200 | C63: Venta | D63: Hiab | E63: 248 | F63: GRUA ARTICULADA HIAB X-CLX 248 EP-4 MARINA | G63: No | H63: 70100200 | I63: 248
A64: 60 | B64: 13171054 | C64: Compra | D64: Hiab | E64: 201 | F64: GRUA ARTICULADA HIAB SEA CRANE 201-3 | G64: No | H64: 13171054 | I64: 201
A65: 61 | B65: 70502121 | C65: Venta | D65: Hiab | E65: 201 | F65: GRUA ARTICULADA HIAB SEA CRANE 201-3 | G65: No | H65: 70502121 | I65: 201
A66: 62 | B66: 13171039 | C66: Compra | D66: Hiab | E66: 188 | F66: GRUA ARTICULADA HIAB X-HIDUO 188 E-5 | G66: No | H66: 13171039 | I66: 188
A67: 63 | B67: 70100251 | C67: Venta | D67: Hiab | E67: 188 | F67: GRUA ARTICULADA HIAB X-HIDUO 188 E-5 | G67: No | H67: 70100251 | I67: 188
A68: 64 | B68: 70100259 | C68: Venta | D68: Hiab | E68: 188 | F68: CAMION GRUA ARTICULADA HIAB X-HIDUO 188 E5 | G68: Sí | H68: 70100259 | I68: 188
A69: 65 | B69: 13171053 | C69: Compra | D69: Hiab | E69: 178 | F69: GRUA ARTICULADA HIAB X-CLX 178 E-4 | G69: No | H69: 13171053 | I69: 178
A70: 66 | B70: 70100249 | C70: Venta | D70: Hiab | E70: 178 | F70: GRUA ARTICULADA HIAB X-CLX 178 E-4 | G70: No | H70: 70100249 | I70: 178
A71: 67 | B71: 70100276 | C71: Venta | D71: Hiab | E71: 178 | F71: CAMION GRUA ARTICULADA HIAB X-CLX 178 E-4 | G71: Sí | H71: 70100276 | I71: 178
... A76: 72 | B76: 70100250 | C76: Venta | D76: Hiab | E76: 88 | F76: GRUA ARTICULADA HIAB X-CLX 088 E-3 | G76: No | H76: 70100250 | I76: 88
A77: 73 | B77: 13171026 | C77: Compra | D77: Hiab | E77: 44 | F77: GRUA ARTICULADA HIAB X-CLX 044 D-3 | G77: No | H77: 13171026 | I77: 44
A78: 74 | B78: 70100290 | C78: Venta | D78: Hiab | E78: 44 | F78: GRUA ARTICULADA HIAB X-CLX 044 D-3 | G78: No | H78: 70100290 | I78: 44
A79: 75 | B79: 70100184 | C79: Venta | D79: Hiab | E79: 29 | F79: GRUA ARTICULADA HIAB T-CLX 029 B-3 | G79: No | H79: 70100184 | I79: 29
A80: 76 | B80: 13171057 | C80: Compra | D80: Hiab | E80: 23 | F80: GRUA ARTICULADA HIAB X-CL 23 B-4 | G80: No | H80: 13171057 | I80: 23
A81: 77 | B81: 70100289 | C81: Venta | D81: Hiab | E81: 23 | F81: GRUA ARTICULADA HIAB X-CL 23 B-4 | G81: No | H81: 70100289 | I81: 23
A82: 78 | B82: 13171060 | C82: Compra | D82: Hiab | E82: 16 | F82: GRUA ARTICULADA HIAB X-CL 16 B-3 | G82: No | H82: 13171060 | I82: 16
A83: 79 | B83: 70100293 | C83: Venta | D83: Hiab | E83: 16 | F83: GRUA ARTICULADA HIAB X-CL 16 B-4 | G83: No | H83: 70100293 | I83: 16
A84: 80 | B84: 70100294 | C84: Venta | D84: Hiab | E84: 16 | F84: GRUA HIAB X-CL 16 B-3 | G84: No | H84: 70100294 | I84: 16
A85: 81 | B85: 13171062 | C85: Compra | D85: Hiab | E85: 12 | F85: GRUA HIAB X-CL 12 B3 | G85: No | H85: 13171062 | I85: 12
A86: 82 | B86: 13171061 | C86: Compra | D86: Hiab | E86: 8 | F86: GRÚA HIAB X-CL 8 B3 | G86: No | H86: 13171061 | I86: 8
A87: 83 | B87: 13171027 | C87: Compra | D87: Hiab | E87: 188 | F87: HIAB iX188 EP-5 | G87: No | H87: 13171027 | I87: 188
A88: 84 | B88: 13171029 | C88: Compra | D88: Hiab | E88: 302 | F88: HIAB eX302 EP-8 | G88: No | H88: 13171029 | I88: 302
A89: 85 | B89: 13171025 | C89: Compra | D89: Hiab | E89: 258 | F89: HIAB iX258 EP-5 | G89: No | H89: 13171025 | I89: 258
A90: 86 | B90: 70100159 | C90: Compra | D90: Hiab | E90: 362 | F90: GRUA ARTICULADA HIAB X-HIPRO 362 EP-5 EVO | G90: No | H90: 70100159 | I90: 362
A91: 87 | B91: 70100160 | C91: Compra | D91: Hiab | E91: 558 | F91: GRUA ARTICULADA HIAB X-HIPRO 558 EP-6 EVO | G91: No | H91: 70100160 | I91: 558
A92: 88 | C92: Compra | D92: Hiab | E92: 708 | F92: HIAB iQ.708 HiPro E9 | G92: No | I92: 708
A93: 89 | C93: Compra | D93: Hiab | E93: 232 | F93: HIAB eX.232 HiPro E5 (Eléctrica) | G93: No | I93: 232
A94: 90 | D94: Hiab
A95: 91 | D95: Hiab
A96: 92 | D96: Hiab
A97: 93 | D97: Hiab

Sheet Flujo de caja
C3: Flujo de caja consolidado:
C4: Categoría | D4: Enero | E4: Febrero | F4: Marzo | G4: Abril | H4: Mayo | I4: Junio | J4: Julio | K4: Agosto | L4: Septiembre | M4: Octubre | N4: Noviembre | O4: Diciembre | P4: Total
C5: Compra | D5: 0 | E5: 0 | F5: 0 | G5: 0 | H5: 0 | I5: 0 | J5: 0 | K5: 0 | L5: 0 | M5: 0 | N5: 0 | O5: 0 | P5: =SUM(D5:O5) -> 0
C6: Venta | D6: 0 | E6: 0 | F6: 0 | G6: 0 | H6: 0 | I6: 0 | J6: 0 | K6: 0 | L6: 0 | M6: 0 | N6: 0 | O6: 0 | P6: =SUM(D6:O6) -> 0
C7: Flete | D7: 0 | E7: 0 | F7: 0 | G7: 0 | H7: 0 | I7: 0 | J7: 0 | K7: 0 | L7: 0 | M7: 0 | N7: 0 | O7: 0 | P7: =SUM(D7:O7) -> 0
C8: *Considerar mes 2 | P8: =P6-P5-P7 -> 0
B11: 1) | C11: Subfamilia: | D11: 1188
C12: Familia: | D12: Hiab
C13: Categoría | D13: Enero | E13: Febrero | F13: Marzo | G13: Abril | H13: Mayo | I13: Junio | J13: Julio | K13: Agosto | L13: Septiembre | M13: Octubre | N13: Noviembre | O13: Diciembre | P13: Total
C14: Compra | D14: 0 | E14: 0 | F14: 0 | G14: 0 | H14: 0 | I14: 0 | J14: 0 | K14: 0 | L14: 0 | M14: 0 | N14: 0 | O14: 0 | P14: =SUM(D14:O14) -> 0
C15: Venta | D15: 0 | E15: 0 | F15: 0 | G15: 0 | H15: 0 | I15: 0 | J15: 0 | K15: 0 | L15: 0 | M15: 0 | N15: 0 | O15: 0 | P15: =SUM(D15:O15) -> 0
C16: Flete | D16: 0 | E16: 0 | F16: 0 | G16: 0 | H16: 0 | I16: 0 | J16: 0 | K16: 0 | L16: 0 | M16: 0 | N16: 0 | O16: 0 | P16: =SUM(D16:O16) -> 0
P17: =P15-P14-P16 -> 0
B19: 2) | C19: Subfamilia: | D19: 1000
C20: Marca: | D20: Effer
C21: Categoría | D21: Enero | E21: Febrero | F21: Marzo | G21: Abril | H21: Mayo | I21: Junio | J21: Julio | K21: Agosto | L21: Septiembre | M21: Octubre | N21: Noviembre | O21: Diciembre | P21: Total
C22: Compra | D22: 0 | E22: 0 | F22: 0 | G22: 0 | H22: 0 | I22: 0 | J22: 0 | K22: 0 | L22: 0 | M22: 0 | N22: 0 | O22: 0 | P22: =SUM(D22:O22) -> 0
C23: Venta | D23: 0 | E23: 0 | F23: 0 | G23: 0 | H23: 0 | I23: 0 | J23: 0 | K23: 0 | L23: 0 | M23: 0 | N23: 0 | O23: 0 | P23: =SUM(D23:O23) -> 0
C24: Flete | D24: 0 | E24: 0 | F24: 0 | G24: 0 | H24: 0 | I24: 0 | J24: 0 | K24: 0 | L24: 0 | M24: 0 | N24: 0 | O24: 0 | P24: =SUM(D24:O24) -> 0
P25: =P23-P22-P24 -> 0
B27: 3) | C27: Subfamilia: | D27: 858
C28: Marca: | D28: Hiab
C29: Categoría | D29: Enero | E29: Febrero | F29: Marzo | G29: Abril | H29: Mayo | I29: Junio | J29: Julio | K29: Agosto | L29: Septiembre | M29: Octubre | N29: Noviembre | O29: Diciembre | P29: Total
C30: Compra | D30: 0 | E30: 0 | F30: 0 | G30: 0 | H30: 0 | I30: 0 | J30: 0 | K30: 0 | L30: 0 | M30: 0 | N30: 0 | O30: 0 | P30: =SUM(D30:O30) -> 0
C31: Venta | D31: 0 | E31: 0 | F31: 0 | G31: 0 | H31: 0 | I31: 0 | J31: 0 | K31: 0 | L31: 0 | M31: 0 | N31: 0 | O31: 0 | P31: =SUM(D31:O31) -> 0
C32: Flete | D32: 0 | E32: 0 | F32: 0 | G32: 0 | H32: 0 | I32: 0 | J32: 0 | K32: 0 | L32: 0 | M32: 0 | N32: 0 | O32: 0 | P32: =SUM(D32:O32) -> 0
P33: =P31-P30-P32 -> 0
B35: 4) | C35: Subfamilia: | D35: 638
C36: Marca: | D36: Hiab
C37: Categoría | D37: Enero | E37: Febrero | F37: Marzo | G37: Abril | H37: Mayo | I37: Junio | J37: Julio | K37: Agosto | L37: Septiembre | M37: Octubre | N37: Noviembre | O37: Diciembre | P37: Total
C38: Compra | D38: 0 | E38: 0 | F38: 0 | G38: 0 | H38: 0 | I38: 0 | J38: 0 | K38: 0 | L38: 0 | M38: 0 | N38: 0 | O38: 0 | P38: =SUM(D38:O38) -> 0
C39: Venta | D39: 0 | E39: 0 | F39: 0 | G39: 0 | H39: 0 | I39: 0 | J39: 0 | K39: 0 | L39: 0 | M39: 0 | N39: 0 | O39: 0 | P39: =SUM(D39:O39) -> 0
C40: Flete | D40: 0 | E40: 0 | F40: 0 | G40: 0 | H40: 0 | I40: 0 | J40: 0 | K40: 0 | L40: 0 | M40: 0 | N40: 0 | O40: 0 | P40: =SUM(D40:O40) -> 0
P41: =P39-P38-P40 -> 0
B43: 5) | C43: Subfamilia: | D43: 558
C44: Marca: | D44: Hiab
C45: Categoría | D45: Enero | E45: Febrero | F45: Marzo | G45: Abril | H45: Mayo | I45: Junio | J45: Julio | K45: Agosto | L45: Septiembre | M45: Octubre | N45: Noviembre | O45: Diciembre | P45: Total
C46: Compra | D46: 0 | E46: 0 | F46: 0 | G46: 0 | H46: 0 | I46: 0 | J46: 0 | K46: 0 | L46: 0 | M46: 0 | N46: 0 | O46: 0 | P46: =SUM(D46:O46) -> 0
C47: Venta | D47: 0 | E47: 0 | F47: 0 | G47: 0 | H47: 0 | I47: 0 | J47: 0 | K47: 0 | L47: 0 | M47: 0 | N47: 0 | O47: 0 | P47: =SUM(D47:O47) -> 0
C48: Flete | D48: 0 | E48: 0 | F48: 0 | G48: 0 | H48: 0 | I48: 0 | J48: 0 | K48: 0 | L48: 0 | M48: 0 | N48: 0 | O48: 0 | P48: =SUM(D48:O48) -> 0
P49: =P47-P46-P48 -> 0
B51: 6) | C51: Subfamilia: | D51: 548
C52: Marca: | D52: Hiab
C53: Categoría | D53: Enero | E53: Febrero | F53: Marzo | G53: Abril | H53: Mayo | I53: Junio | J53: Julio | K53: Agosto | L53: Septiembre | M53: Octubre | N53: Noviembre | O53: Diciembre | P53: Total
C54: Compra | D54: 0 | E54: 0 | F54: 0 | G54: 0 | H54: 0 | I54: 0 | J54: 0 | K54: 0 | L54: 0 | M54: 0 | N54: 0 | O54: 0 | P54: =SUM(D54:O54) -> 0
C55: Venta | D55: 0 | E55: 0 | F55: 0 | G55: 0 | H55: 0 | I55: 0 | J55: 0 | K55: 0 | L55: 0 | M55: 0 | N55: 0 | O55: 0 | P55: =SUM(D55:O55) -> 0
C56: Flete | D56: 0 | E56: 0 | F56: 0 | G56: 0 | H56: 0 | I56: 0 | J56: 0 | K56: 0 | L56: 0 | M56: 0 | N56: 0 | O56: 0 | P56: =SUM(D56:O56) -> 0
P57: =P55-P54-P56 -> 0
B59: 7) | C59: Subfamilia: | D59: 418
C60: Marca: | D60: Hiab
C61: Categoría | D61: Enero | E61: Febrero | F61: Marzo | G61: Abril | H61: Mayo | I61: Junio | J61: Julio | K61: Agosto | L61: Septiembre | M61: Octubre | N61: Noviembre | O61: Diciembre | P61: Total
C62: Compra | D62: 0 | E62: 0 | F62: 0 | G62: 0 | H62: 0 | I62: 0 | J62: 0 | K62: 0 | L62: 0 | M62: 0 | N62: 0 | O62: 0 | P62: =SUM(D62:O62) -> 0
C63: Venta | D63: 0 | E63: 0 | F63: 0 | G63: 0 | H63: 0 | I63: 0 | J63: 0 | K63: 0 | L63: 0 | M63: 0 | N63: 0 | O63: 0 | P63: =SUM(D63:O63) -> 0
C64: Flete | D64: 0 | E64: 0 | F64: 0 | G64: 0 | H64: 0 | I64: 0 | J64: 0 | K64: 0 | L64: 0 | M64: 0 | N64: 0 | O64: 0 | P64: =SUM(D64:O64) -> 0
P65: =P63-P62-P64 -> 0
B67: 8) | C67: Subfamilia: | D67: 408
C68: Marca: | D68: Hiab
C69: Categoría | D69: Enero | E69: Febrero | F69: Marzo | G69: Abril | H69: Mayo | I69: Junio | J69: Julio | K69: Agosto | L69: Septiembre | M69: Octubre | N69: Noviembre | O69: Diciembre | P69: Total
C70: Compra | D70: 0 | E70: 0 | F70: 0 | G70: 0 | H70: 0 | I70: 0 | J70: 0 | K70: 0 | L70: 0 | M70: 0 | N70: 0 | O70: 0 | P70: =SUM(D70:O70) -> 0
C71: Venta | D71: 0 | E71: 0 | F71: 0 | G71: 0 | H71: 0 | I71: 0 | J71: 0 | K71: 0 | L71: 0 | M71: 0 | N71: 0 | O71: 0 | P71: =SUM(D71:O71) -> 0
C72: Flete | D72: 0 | E72: 0 | F72: 0 | G72: 0 | H72: 0 | I72: 0 | J72: 0 | K72: 0 | L72: 0 | M72: 0 | N72: 0 | O72: 0 | P72: =SUM(D72:O72) -> 0
P73: =P71-P70-P72 -> 0
B75: 9) | C75: Subfamilia: | D75: 388
C76: Marca: | D76: Hiab
C77: Categoría | D77: Enero | E77: Febrero | F77: Marzo | G77: Abril | H77: Mayo | I77: Junio | J77: Julio | K77: Agosto | L77: Septiembre | M77: Octubre | N77: Noviembre | O77: Diciembre | P77: Total
C78: Compra | D78: 0 | E78: 0 | F78: 0 | G78: 0 | H78: 0 | I78: 0 | J78: 0 | K78: 0 | L78: 0 | M78: 0 | N78: 0 | O78: 0 | P78: =SUM(D78:O78) -> 0
C79: Venta | D79: 0 | E79: 0 | F79: 0 | G79: 0 | H79: 0 | I79: 0 | J79: 0 | K79: 0 | L79: 0 | M79: 0 | N79: 0 | O79: 0 | P79: =SUM(D79:O79) -> 0
C80: Flete | D80: 0 | E80: 0 | F80: 0 | G80: 0 | H80: 0 | I80: 0 | J80: 0 | K80: 0 | L80: 0 | M80: 0 | N80: 0 | O80: 0 | P80: =SUM(D80:O80) -> 0
P81: =P79-P78-P80 -> 0
B83: 10) | C83: Subfamilia: | D83: 362
C84: Marca: | D84: Hiab
C85: Categoría | D85: Enero | E85: Febrero | F85: Marzo | G85: Abril | H85: Mayo | I85: Junio | J85: Julio | K85: Agosto | L85: Septiembre | M85: Octubre | N85: Noviembre | O85: Diciembre | P85: Total
C86: Compra | D86: 0 | E86: 0 | F86: 0 | G86: 0 | H86: 0 | I86: 0 | J86: 0 | K86: 0 | L86: 0 | M86: 0 | N86: 0 | O86: 0 | P86: =SUM(D86:O86) -> 0
C87: Venta | D87: 0 | E87: 0 | F87: 0 | G87: 0 | H87: 0 | I87: 0 | J87: 0 | K87: 0 | L87: 0 | M87: 0 | N87: 0 | O87: 0 | P87: =SUM(D87:O87) -> 0
C88: Flete | D88: 0 | E88: 0 | F88: 0 | G88: 0 | H88: 0 | I88: 0 | J88: 0 | K88: 0 | L88: 0 | M88: 0 | N88: 0 | O88: 0 | P88: =SUM(D88:O88) -> 0
P89: =P87-P86-P88 -> 0
B91: 11) | C91: Subfamilia: | D91: 352
C92: Marca: | D92: Hiab
C93: Categoría | D93: Enero | E93: Febrero | F93: Marzo | G93: Abril | H93: Mayo | I93: Junio | J93: Julio | K93: Agosto | L93: Septiembre | M93: Octubre | N93: Noviembre | O93: Diciembre | P93: Total
C94: Compra | D94: 0 | E94: 0 | F94: 0 | G94: 0 | H94: 0 | I94: 0 | J94: 0 | K94: 0 | L94: 0 | M94: 0 | N94: 0 | O94: 0 | P94: =SUM(D94:O94) -> 0
C95: Venta | D95: 0 | E95: 0 | F95: 0 | G95: 0 | H95: 0 | I95: 0 | J95: 0 | K95: 0 | L95: 0 | M95: 0 | N95: 0 | O95: 0 | P95: =SUM(D95:O95) -> 0
C96: Flete | D96: 0 | E96: 0 | F96: 0 | G96: 0 | H96: 0 | I96: 0 | J96: 0 | K96: 0 | L96: 0 | M96: 0 | N96: 0 | O96: 0 | P96: =SUM(D96:O96) -> 0
P97: =P95-P94-P96 -> 0
B99: 12) | C99: Subfamilia: | D99: 328
C100: Marca: | D100: Hiab
C101: Categoría | D101: Enero | E101: Febrero | F101: Marzo | G101: Abril | H101: Mayo | I101: Junio | J101: Julio | K101: Agosto | L101: Septiembre | M101: Octubre | N101: Noviembre | O101: Diciembre | P101: Total
C102: Compra | D102: 0 | E102: 0 | F102: 0 | G102: 0 | H102: 0 | I102: 0 | J102: 0 | K102: 0 | L102: 0 | M102: 0 | N102: 0 | O102: 0 | P102: =SUM(D102:O102) -> 0
C103: Venta | D103: 0 | E103: 0 | F103: 0 | G103: 0 | H103: 0 | I103: 0 | J103: 0 | K103: 0 | L103: 0 | M103: 0 | N103: 0 | O103: 0 | P103: =SUM(D103:O103) -> 0
C104: Flete | D104: 0 | E104: 0 | F104: 0 | G104: 0 | H104: 0 | I104: 0 | J104: 0 | K104: 0 | L104: 0 | M104: 0 | N104: 0 | O104: 0 | P104: =SUM(D104:O104) -> 0
P105: =P103-P102-P104 -> 0
B107: 13) | C107: Subfamilia: | D107: 302
C108: Marca: | D108: Hiab
C109: Categoría | D109: Enero | E109: Febrero | F109: Marzo | G109: Abril | H109: Mayo | I109: Junio | J109: Julio | K109: Agosto | L109: Septiembre | M109: Octubre | N109: Noviembre | O109: Diciembre | P109: Total
C110: Compra | D110: 0 | E110: 0 | F110: 0 | G110: 0 | H110: 0 | I110: 0 | J110: 0 | K110: 0 | L110: 0 | M110: 0 | N110: 0 | O110: 0 | P110: =SUM(D110:O110) -> 0
C111: Venta | D111: 0 | E111: 0 | F111: 0 | G111: 0 | H111: 0 | I111: 0 | J111: 0 | K111: 0 | L111: 0 | M111: 0 | N111: 0 | O111: 0 | P111: =SUM(D111:O111) -> 0
C112: Flete | D112: 0 | E112: 0 | F112: 0 | G112: 0 | H112: 0 | I112: 0 | J112: 0 | K112: 0 | L112: 0 | M112: 0 | N112: 0 | O112: 0 | P112: =SUM(D112:O112) -> 0
P113: =P111-P110-P112 -> 0
B115: 14) | C115: Subfamilia: | D115: 298
C116: Marca: | D116: Hiab
C117: Categoría | D117: Enero | E117: Febrero | F117: Marzo | G117: Abril | H117: Mayo | I117: Junio | J117: Julio | K117: Agosto | L117: Septiembre | M117: Octubre | N117: Noviembre | O117: Diciembre | P117: Total
...

Sheet Solicitud de compra
B2: Proveedor | C2: Código compra | D2: Descripción | E2: Cantidad | F2: % | G2: Costo unitario | H2: costo total
B3: HIAB | C3: 13171020 | D3: HIAB X-HIPRO 362 EP-5 | E3: 6 | F3: 0.08 | G3: 66007.68 | H3: =G3*E3 -> 396046.08
B4: HIAB | C4: 13171021 | D4: HIAB X-HIPRO 408 E-8 | E4: 4 | F4: 0.09 | G4: 88544.64 | H4: =G4*E4 -> 354178.56
B5: HIAB | C5: 13171022 | D5: HIAB X-HIPRO 418 EP-5 | E5: 4 | F5: 0.1 | G5: 154207.68 | H5: =G5*E5 -> 616830.72
B6: HIAB | C6: 19502041 | D6: HIAB X-HIPRO 548 E9 | E6: 4 | F6: 0.08 | G6: 104123.52 | H6: =G6*E6 -> 416494.08
B7: HIAB | C7: 13171070 | D7: HIAB iQ.708 HiPro E9 | E7: 2 | F7: 0.09 | G7: 142731 | H7: =G7*E7 -> 285462
G8: Total | H8: =SUM(H3:H7) -> 2069011.4

Sheet Ventas (2025)
A1: Código | B1: Descripción | C1: Cantidad | D1: Precio unitario | E1: Facturación total | F1: Margen bruto promedio | H1: Año | I1: NroMes | J1: Proyecto | K1: NombreProyecto | L1: NombreAreaNegocio | M1: NombreCentroCosto | N1: NombreLineaNegocio | O1: NombreSubLineaNegocio | P1: Vendedor | Q1: Venta Real ML | R1: Costo Real ML | S1: Margen Bruto Real ML | T1: Margen Bruto Real ML (%) | U1: CodArticulo | V1: Last DescripcionArticuloMayor | W1: Last NombreUsuario | X1: TipoCosto | Y1: Last Glosa | Z1: Max of NroAsiento | AA1: Latest FechaActualizacion | AB1: NombreClienteFinalBI | AC1: GuiaAdjunta | AD1: Rut | AE1: CodArticulo | AF1: CodArticulo | AI1: CodArticulo | AJ1: Last DescripcionArticuloMayor
A2: 70100211 | B2: GRUA ARTICULADA HIAB X-HIPRO 858 E-10 | C2: =COUNTIF(U:U,A2) -> 1 | D2: 266178.2 | E2: =D2*C2 -> 266178.2 | F2: =AVERAGEIF(U:U,A2,T:T) -> 0.2500832 | H2: 2025 | I2: 9 | J2: 2503036 | K2: SISTEMA DE TRANSMISION DEL NORTE S.A | L2: COMERCIAL ZONA CENTRO | M2: IZAJE | P2: FRANCO MODINGER | Q2: 345.05943 | R2: -240.99951 | S2: 104.05991 | T2: 0.301571 | U2: 79001011 | V2: CAMION GRUA HIAB 352 E8 X-HIPRO | W2: Estrella Rodriguez | X2: 1-PROYECTO COMERCIAL | Y2: Facturas clientes - 76410374C | Z2: 417038 | AA2: 45929 | AB2: SISTEMA DE TRANSMISION DEL NORTE S.A | AC2: 74389 | AD2: 96572360-9 | AE2: 70100211 | AF2: 70100211 | AI2: 70100211 | AJ2: GRUA ARTICULADA HIAB X-HIPRO 858 E-10
A3: 79001011 | B3: CAMION GRUA HIAB 352 E8 X-HIPRO | C3: =COUNTIF(U:U,A3) -> 1 | D3: 345059.43 | E3: =D3*C3 -> 345059.43 | F3: =AVERAGEIF(U:U,A3,T:T) -> 0.301571 | H3: 2026 | I3: 2 | J3: 2602197 | K3: SOC COMERCIAL E INDUSTRIAL JOMAR LIMITADA | L3: CANAL PROPIO | M3: IZAJE | O3: ZONA SUR - PTO MONTT | P3: EDUARDO OÑATE | Q3: 25.586496 | R3: -19.504933 | S3: 6.0815631 | T3: 0.23768644 | U3: 70100294 | V3: GRUA HIAB CL 16 B-3 MARINA | W3: Estrella Rodriguez | X3: 1-PROYECTO COMERCIAL | Y3: Facturas clientes - 76263360C | Z3: 485855 | AA3: 46079 | AB3: SOC COMERCIAL E INDUSTRIAL JOMAR LIMITADA | AC3: 86182 | AD3: 76410374-2 | AE3: 79001011 | AF3: 79001011 | AI3: 79001011 | AJ3: CAMION GRUA HIAB 352 E8 X-HIPRO
A4: 70100170 | B4: CAMION GRUA ARTICULADA HIAB X-HIDUO 258 EP-5 | C4: =COUNTIF(U:U,A4) -> 2 | D4: 183545.42 | E4: =D4*C4 -> 367090.85 | F4: =AVERAGEIF(U:U,A4,T:T) -> 0.13728171 | H4: 2026 | I4: 4 | J4: 2604201 | K4: GERMAN ROBINSON GUERRERO AYANCAN | L4: CANAL PROPIO | M4: IZAJE | P4: EDUARDO OÑATE | Q4: 25.774664 | R4: -18.582324 | S4: 7.19234 | T4: 0.2790469 | U4: 70100294 | V4: GRUA HIAB CL 16 B-3 MARINA | W4: Estrella Rodriguez | X4: 1-PROYECTO COMERCIAL | Y4: Orden fabricación: 70100294 | Z4: 508539 | AA4: 46128 | AB4: GERMAN ROBINSON GUERRERO AYANCAN | AC4: 91861 | AD4: 61106000-9 | AE4: 70100170 | AF4: 70100170 | AI4: 70100170 | AJ4: CAMION GRUA ARTICULADA HIAB X-HIDUO 258 EP-5
A5: 70100206 | B5: GRUA ARTICULADA HIAB X-HIPRO 558 EP-5 | C5: =COUNTIF(U:U,A5) -> 11 | D5: 165626.19 | E5: =D5*C5 -> 1821888.1 | F5: =AVERAGEIF(U:U,A5,T:T) -> 0.25234891 | H5: 2026 | I5: 4 | J5: 2604204 | K5: ALGEMARIN SPA. | L5: CANAL PROPIO | M5: IZAJE | P5: EDUARDO OÑATE | Q5: 25.537146 | R5: -18.571614 | S5: 6.9655322 | T5: 0.2727608 | U5: 70100294 | V5: GRUA HIAB CL 16 B-3 MARINA | W5: Estrella Rodriguez | X5: 1-PROYECTO COMERCIAL | Y5: Orden fabricación: 70100294 | Z5: 504510 | AA5: 46125 | AB5: ALGEMARIN SPA. | AC5: 91859 | AD5: 76741387-4 | AE5: 70100206 | AF5: 70100206 | AI5: 70100206 | AJ5: GRUA ARTICULADA HIAB X-HIPRO 558 EP-5
A6: 70100165 | B6: GRUA ARTICULADA HIAB X-HIPRO 418 EP-5 | C6: =COUNTIF(U:U,A6) -> 12 | D6: 148036.7 | E6: =D6*C6 -> 1776440.4 | F6: =AVERAGEIF(U:U,A6,T:T) -> 0.26565906 | H6: 2025 | I6: 10 | J6: 2510566 | K6: FRANCISCO ALEJANDRO LEVICAN ANCAHUAI | L6: COMERCIAL ZONA SUR | M6: IZAJE | P6: EDUARDO OÑATE | Q6: 25.498986 | R6: -18.758439 | S6: 6.7405479 | T6: 0.26434572 | U6: 70100294 | V6: GRUA HIAB CL 16 B-3 MARINA | W6: Estrella Rodriguez | X6: 1-PROYECTO COMERCIAL | Y6: Orden fabricación: 70100294 | Z6: 433953 | AA6: 45958 | AB6: FRANCISCO ALEJANDRO LEVICAN ANCAHUAI | AC6: 76985 | AD6: 76741387-4 | AE6: 70100206 | AF6: 70100206 | AI6: 70100165 | AJ6: GRUA ARTICULADA HIAB X-HIPRO 418 EP-5
A7: 70100220 | B7: CAMION GRUA ARTICULADA HIAB X-HIPRO 352 E-6 | C7: =COUNTIF(U:U,A7) -> 1 | D7: 259969.54 | E7: =D7*C7 -> 259969.54 | F7: =AVERAGEIF(U:U,A7,T:T) -> 0.23863632 | H7: 2025 | I7: 12 | J7: 2512426 | K7: LILIANA INES MENDOZA VARGAS SERVICIOS ACUICOLAS TRANSPORTE Y TURISMO EIRL | L7: COMERCIAL ZONA SUR | M7: IZAJE | P7: EDUARDO OÑATE | Q7: 26.239504 | R7: -19.117289 | S7: 7.1222156 | T7: 0.27143103 | U7: 70100294 | V7: GRUA HIAB CL 16 B-3 MARINA | W7: Estrella Rodriguez | X7: 1-PROYECTO COMERCIAL | Y7: Orden fabricación: 70100294 | Z7: 461065 | AA7: 46014 | AB7: LILIANA INES MENDOZA VARGAS SERVICIOS ACUICOLAS TRANSPORTE Y TURISMO EIRL | AC7: 81606 | AD7: 76741387-4 | AE7: 70100206 | AF7: 70100206 | AI7: 70100220 | AJ7: CAMION GRUA ARTICULADA HIAB X-HIPRO 352 E-6
A8: 70100221 | B8: GRUA ARTICULADA HIAB X-HIPRO 858 E-8 | C8: =COUNTIF(U:U,A8) -> 9 | D8: 231940.84 | E8: =D8*C8 -> 2087467.5 | F8: =AVERAGEIF(U:U,A8,T:T) -> 0.2158699 | H8: 2026 | I8: 1 | J8: 2601273 | K8: TRANSPORTE MARITIMO JUAN CARLOS SALAS BORQUEZ EMPRESA INDIVIDUAL DE RESPONSABILIDAD LIMITADA | L8: CANAL PROPIO | M8: IZAJE | P8: EDUARDO OÑATE | Q8: 39.031678 | R8: -27.76635 | S8: 11.265327 | T8: 0.28862012 | U8: 70100289 | V8: GRUA ARTICULADA HIAB X-CL 23 B-4 | W8: Estrella Rodriguez | X8: 1-PROYECTO COMERCIAL | Y8: Facturas clientes - 77062982C | Z8: 476177 | AA8: 46049 | AB8: TRANSPORTE MARITIMO JUAN CARLOS SALAS BORQUEZ EMPRESA INDIVIDUAL DE RESPONSABILIDAD LIMITADA | AC8: 84283 | AD8: 76741387-4 | AE8: 70100206 | AF8: 70100206 | AI8: 70100221 | AJ8: GRUA ARTICULADA HIAB X-HIPRO 858 E-8
A9: 70100171 | B9: GRUA ARTICULADA HIAB X-HIPRO 362 EP-5 | C9: =COUNTIF(U:U,A9) -> 12 | D9: 133753.01 | E9: =D9*C9 -> 1605036.1 | F9: =AVERAGEIF(U:U,A9,T:T) -> 0.33065486 | H9: 2025 | I9: 7 | J9: 2507116 | K9: FIDEL MARTIN BENAVIDES HERRERA | L9: COMERCIAL ZONA SUR | M9: IZAJE | P9: EDUARDO OÑATE | Q9: 37.182278 | R9: -26.192337 | S9: 10.989941 | T9: 0.29556934 | U9: 70100289 | V9: GRUA ARTICULADA HIAB X-CL 23 B-4 | W9: Estrella Rodriguez | X9: 1-PROYECTO COMERCIAL | Y9: Facturas clientes - 12524230C | Z9: 386707 | AA9: 45863 | AB9: FIDEL MARTIN BENAVIDES HERRERA | AC9: 68801 | AD9: 76741387-4 | AE9: 70100165 | AF9: 70100165 | AI9: 70100171 | AJ9: GRUA ARTICULADA HIAB X-HIPRO 362 EP-5
A10: 70100164 | B10: GRUA ARTICULADA HIAB X-HIPRO 408 E-8 | C10: =COUNTIF(U:U,A10) -> 9 | D10: 170285.84 | E10: =D10*C10 -> 1532572.5 | F10: =AVERAGEIF(U:U,A10,T:T) -> 0.25448369 | H10: 2025 | I10: 10 | J10: 2510380 | K10: PESQUERA JUAN SOTO OJEDA E.I.R.L | L10: COMERCIAL ZONA SUR | M10: IZAJE | P10: EDUARDO OÑATE | Q10: 37.135395 | R10: -27.635217 | S10: 9.500178 | T10: 0.25582542 | U10: 70100289 | V10: GRUA ARTICULADA HIAB X-CL 23 B-4 | W10: Jose Pablo Alberto Angulo Procuriza | X10: 1-PROYECTO COMERCIAL | Y10: Orden fabricación: 70100289 | Z10: 430992 | AA10: 45951 | AB10: PESQUERA JUAN SOTO OJEDA E.I.R.L | AC10: 76987 | AD10: 76741387-4 | AE10: 70100165 | AF10: 70100165 | AI10: 70100164 | AJ10: GRUA ARTICULADA HIAB X-HIPRO 408 E-8
A11: 19502062 | B11: GRUA ARTICULADA HIAB X-HIPRO 548 E-9 año 2022 | C11: =COUNTIF(U:U,A11) -> 1 | D11: 191180.5 | E11: =D11*C11 -> 191180.5 | F11: =AVERAGEIF(U:U,A11,T:T) -> 0.25703386 | H11: 2025 | I11: 11 | J11: 2511060 | K11: SOCIEDAD DE SERVICIOS AQUASMART SPA | L11: COMERCIAL ZONA SUR | M11: IZAJE | P11: EDUARDO OÑATE | Q11: 37.500353 | R11: -26.185421 | S11: 11.314932 | T11: 0.30172869 | U11: 70100289 | V11: GRUA ARTICULADA HIAB X-CL 23 B-4 | W11: Jose Pablo Alberto Angulo Procuriza | X11: 1-PROYECTO COMERCIAL | Y11: Orden fabricación: 70100289 | Z11: 447902 | AA11: 45988 | AB11: SOCIEDAD DE SERVICIOS AQUASMART SPA | AC11: 79398 | AD11: 76741387-4 | AE11: 70100165 | AF11: 70100165 | AI11: 19502062 | AJ11: GRUA ARTICULADA HIAB X-HIPRO 548 E-9 año 2022
A12: 70100166 | B12: GRUA ARTICULADA HIAB X-HIDUO 258 EP-5 | C12: =COUNTIF(U:U,A12) -> 7 | D12: 100149.5 | E12: =D12*C12 -> 701046.47 | F12: =AVERAGEIF(U:U,A12,T:T) -> 0.2777657 | H12: 2025 | I12: 12 | J12: 2512054 | K12: MAREAS AUSTRALES SPA | L12: COMERCIAL ZONA SUR | M12: IZAJE | P12: EDUARDO OÑATE | Q12: 36.015165 | R12: -27.015021 | S12: 9.0001438 | T12: 0.24989873 | U12: 70100289 | V12: GRUA ARTICULADA HIAB X-CL 23 B-4 | W12: Estrella Rodriguez | X12: 1-PROYECTO COMERCIAL | Y12: Facturas clientes - 77608032C | Z12: 463219 | AA12: 46020 | AB12: MAREAS AUSTRALES SPA | AC12: 82031 | AD12: 76410374-2 | AE12: 70100220 | AF12: 70100220 | AI12: 70100166 | AJ12: GRUA ARTICULADA HIAB X-HIDUO 258 EP-5
A13: 70100289 | B13: GRUA ARTICULADA HIAB X-CL 23 B-4 | C13: =COUNTIF(U:U,A13) -> 5 | D13: 37372.974 | E13: =D13*C13 -> 186864.87 | F13: =AVERAGEIF(U:U,A13,T:T) -> 0.27832846 | H13: 2026 | I13: 3 | J13: 2603063 | K13: VICTOR HUGO ITURRA ZUNIGA ARRIENDO DE VEHICULOS Y TRANSPORTE DE PASAJ | L13: CANAL PROPIO | M13: IZAJE | O13: ZONA CENTRO - SANTIAGO | P13: CARLOS SOTO | Q13: 142.06115 | R13: -108.5682 | S13: 33.492949 | T13: 0.23576431 | U13: 70100275 | V13: GRUA ARTICULADA HIAB X HIPRO 558 EP6 | W13: Estrella Rodriguez | X13: 1-PROYECTO COMERCIAL | Y13: RECLASIFICA PREVENTA MANTENCION CLIENTE VICTOR ITURRA | Z13: 504186 | AA13: 46122 | AB13: VICTOR HUGO ITURRA ZUNIGA ARRIENDO DE VEHICULOS Y TRANSPORTE DE PASAJ | AC13: 88938 | AD13: 76238635-6 | AE13: 70100221 | AF13: 70100221 | AI13: 70100289 | AJ13: GRUA ARTICULADA HIAB X-CL 23 B-4
A14: 70100212 | B14: GRUA ARTICULADA HIAB X-HIPRO 638 E-9 | C14: =COUNTIF(U:U,A14) -> 7 | D14: 194022.49 | E14: =D14*C14 -> 1358157.4 | F14: =AVERAGEIF(U:U,A14,T:T) -> 0.093299565 | H14: 2026 | I14: 5 | J14: 2603701 | K14: G.T.A. CHILE SPA | L14: CANAL PROPIO | M14: IZAJE | P14: EDGARDO URREA | Q14: 176.81475 | R14: -245.24964 | S14: -68.434887 | T14: -0.38704286 | U14: 70100275 | V14: GRUA ARTICULADA HIAB X HIPRO 558 EP6 | W14: Estrella Rodriguez | X14: 1-PROYECTO COMERCIAL | Y14: Orden fabricación: 81310205 | Z14: 529941 | AA14: 46178 | AB14: G.T.A. CHILE SPA | AC14: 94488 | AD14: 96572360-9 | AE14: 70100206 | AF14: 70100206 | AI14: 70100212 | AJ14: GRUA ARTICULADA HIAB X-HIPRO 638 E-9
A15: 70100200 | B15: GRUA ARTICULADA HIAB X-CLX 248 EP-4 MARINA | C15: =COUNTIF(U:U,A15) -> 1 | D15: 43944.303 | E15: =D15*C15 -> 43944.303 | F15: =AVERAGEIF(U:U,A15,T:T) -> 0.2007608 | H15: 2026 | I15: 5 | J15: 2603702 | K15: G.T.A. CHILE SPA | L15: CANAL PROPIO | M15: IZAJE | P15: EDGARDO URREA | Q15: 176.81475 | R15: -15.163274 | S15: 161.65148 | T15: 0.91424203 | U15: 70100275 | V15: GRUA ARTICULADA HIAB X HIPRO 558 EP6 | W15: Estrella Rodriguez | X15: 1-PROYECTO COMERCIAL | Y15: Orden fabricación: 81310205 | Z15: 529924 | AA15: 46178 | AB15: G.T.A. CHILE SPA | AC15: 94231 | AD15: 91502000-3 | AE15: 70100171 | AF15: 70100171 | AI15: 70100200 | AJ15: GRUA ARTICULADA HIAB X-CLX 248 EP-4 MARINA
A16: 70100195 | B16: GRUA ARTICULADA HIAB X-CLX 288 EP-4 MARINA | C16: =COUNTIF(U:U,A16) -> 1 | D16: 53504.385 | E16: =D16*C16 -> 53504.385 | F16: =AVERAGEIF(U:U,A16,T:T) -> 0.16841542 | H16: 2025 | I16: 10 | J16: 2509575 | K16: SALINAS Y FABRES SOCIEDAD ANONIMA | L16: COMERCIAL ZONA CENTRO | M16: IZAJE | P16: CARLOS SOTO | Q16: 170.0204 | R16: -121.93444 | S16: 48.085959 | T16: 0.28282465 | U16: 70100275 | V16: GRUA ARTICULADA HIAB X HIPRO 558 EP6 | W16: Javier Ballesteros | X16: 1-PROYECTO COMERCIAL | Y16: Orden fabricación: 70100275 | Z16: 435487 | AA16: 45960 | AB16: SALINAS Y FABRES SOCIEDAD ANONIMA | AC16: 77135 | AD16: 91502000-3 | AE16: 70100171 | AF16: 70100171 | AI16: 70100195 | AJ16: GRUA ARTICULADA HIAB X-CLX 288 EP-4 MARINA
A17: 70100173 | B17: CAMION GRUA ARTICULADA HIAB X-HIPRO 418 EP-5 | C17: =COUNTIF(U:U,A17) -> 4 | D17: 309614.95 | E17: =D17*C17 -> 1238459.8 | F17: =AVERAGEIF(U:U,A17,T:T) -> 0.14202945 | H17: 2025 | I17: 11 | J17: 2508638 | K17: CONSTRUCTORA SALFA S A | L17: COMERCIAL ZONA CENTRO | M17: IZAJE | P17: CARLOS SOTO | Q17: 164.54634 | R17: -130.11366 | S17: 34.432683 | T17: 0.20925827 | U17: 70100275 | V17: GRUA ARTICULADA HIAB X HIPRO 558 EP6 | W17: Estrella Rodriguez | X17: 1-PROYECTO COMERCIAL | Y17: Orden fabricación: 70100206 | Z17: 446921 | AA17: 45987 | AB17: CONSTRUCTORA SALFA S A | AC17: 79164 | AD17: 96572360-9 | AE17: 70100164 | AF17: 70100164 | AI17: 70100173 | AJ17: CAMION GRUA ARTICULADA HIAB X-HIPRO 418 EP-5
A18: 70100205 | B18: GRUA ARTICULADA HIAB X-HIPRO 548 E-9 | C18: =COUNTIF(U:U,A18) -> 3 | D18: 189094.54 | E18: =D18*C18 -> 567283.62 | F18: =AVERAGEIF(U:U,A18,T:T) -> 0.19410197 | H18: 2025 | I18: 12 | J18: 2510654 | K18: COMERCIAL KAUFMANN S.A. | L18: COMERCIAL ZONA CENTRO | M18: IZAJE | P18: CARLOS SOTO | Q18: 179.56754 | R18: -118.14962 | S18: 61.41792 | T18: 0.34203243 | U18: 70100275 | V18: GRUA ARTICULADA HIAB X HIPRO 558 EP6 | W18: Estrella Rodriguez | X18: 1-PROYECTO COMERCIAL | Y18: Orden fabricación: 70100275 | Z18: 464746 | AA18: 46021 | AB18: COMERCIAL KAUFMANN S.A. | AC18: 81437 | AD18: 96572360-9 | AE18: 19502062 | AF18: 19502062 | AI18: 70100205 | AJ18: GRUA ARTICULADA HIAB X-HIPRO 548 E-9
A19: 70100167 | B19: GRUA ARTICULADA HIAB X-HIDUO 298 EP-5 | C19: =COUNTIF(U:U,A19) -> 4 | D19: 111290.72 | E19: =D19*C19 -> 445162.88 | F19: =AVERAGEIF(U:U,A19,T:T) -> 0.23659897 | H19: 2026 | I19: 3 | J19: 2511052 | K19: COMERCIAL KAUFMANN S.A. | L19: CANAL KAUFMANN | M19: IZAJE | O19: ZONA CENTRO - SANTIAGO | P19: KEVIN FLEFEL | Q19: 184.27065 | R19: -152.9253 | S19: 31.345342 | T19: 0.17010491 | U19: 70100267 | V19: GRUA ARTICULADA HIAB X-HIPRO 548 E-9 año 2022 | W19: Estrella Rodriguez | X19: 1-PROYECTO COMERCIAL | Y19: RECLASIFICA VENTA POR SERV DE MANTENCION | Z19: 502243 | AA19: 46120 | AB19: COMERCIAL KAUFMANN S.A. | AC19: 88913 | AD19: 76496130-7 | AE19: 70100166 | AF19: 70100166 | AI19: 70100167 | AJ19: GRUA ARTICULADA HIAB X-HIDUO 298 EP-5
A20: 70100275 | B20: GRUA ARTICULADA HIAB X HIPRO 558 EP6 | C20: =COUNTIF(U:U,A20) -> 6 | D20: 168304.15 | E20: =D20*C20 -> 1009824.9 | F20: =AVERAGEIF(U:U,A20,T:T) -> 0.26617981 | H20: 2025 | I20: 12 | J20: 2509339 | K20: WORLD CLASS MINING SERVICES Y COMPANIA LTDA | L20: COMERCIAL ZONA NORTE | M20: IZAJE | P20: EDGARDO URREA | Q20: 291.25626 | R20: -240.59842 | S20: 50.657838 | T20: 0.17392875 | U20: 70100259 | V20: CAMION GRUA ARTICULADA HIAB X-HIDUO 188 E5 | W20: Estrella Rodriguez | X20: 1-PROYECTO COMERCIAL | Y20: Orden fabricación: 70100259 | Z20: 460505 | AA20: 46013 | AB20: CONSTRUCCIÓN E INGENIERÍA ELÉCTRICA HÉCTOR DAVID QUISBERT VARGAS E.I.R | AC20: 82014 | AD20: 76178493-5 | AE20: 70100165 | AF20: 70100165 | AI20: 70100275 | AJ20: GRUA ARTICULADA HIAB X HIPRO 558 EP6
A21: 70100225 | B21: GRUA ARTICULADA HIAB X-CLX 088 E-4 | C21: =COUNTIF(U:U,A21) -> 1 | D21: 65629.41 | E21: =D21*C21 -> 65629.41 | F21: =AVERAGEIF(U:U,A21,T:T) -> 0.16464444 | H21: 2026 | I21: 1 | J21: 2601519 | K21: SOCIEDAD DE TRANSPORTE MARITIMO Y TERRESTRE BAHAMONDE Y CIA LTDA | L21: CANAL PROPIO | M21: IZAJE | P21: EDUARDO OÑATE | Q21: 72.468825 | R21: -60.417549 | S21: 12.051276 | T21: 0.16629601 | U21: 70100253 | V21: GRUA HIAB X-CLX 388 EP5 | W21: Estrella Rodriguez | X21: 1-PROYECTO COMERCIAL | Y21: Facturas clientes - 76039220C | Z21: 478109 | AA21: 46052 | AB21: SOCIEDAD DE TRANSPORTE MARITIMO Y TERRESTRE BAHAMONDE Y CIA LTDA | AC21: 84280 | AD21: 97036000-K | AE21: 70100171 | AF21: 70100171 | AI21: 70100225 | AJ21: GRUA ARTICULADA HIAB X-CLX 088 E-4
A22: 70100249 | B22: GRUA ARTICULADA HIAB X-CLX 178 E-4 | C22: =COUNTIF(U:U,A22) -> 9 | D22: 89855.865 | E22: =D22*C22 -> 808702.79 | F22: =AVERAGEIF(U:U,A22,T:T) -> 0.20109067 | H22: 2026 | I22: 2 | J22: 2602337 | K22: MANUEL BARRIENTOS RETAMAL | L22: CANAL PROPIO | M22: IZAJE | P22: EDUARDO OÑATE | Q22: 72.946097 | R22: -59.836219 | S22: 13.109878 | T22: 0.17972007 | U22: 70100253 | V22: GRUA HIAB X-CLX 388 EP5 | W22: Estrella Rodriguez | X22: 1-PROYECTO COMERCIAL | Y22: Facturas clientes - 6097476C | Z22: 486303 | AA22: 46079 | AB22: MANUEL BARRIENTOS RETAMAL | AC22: 86184 | AD22: 12524230-8 | AE22: 70100289 | AF22: 70100289 | AI22: 70100249 | AJ22: GRUA ARTICULADA HIAB X-CLX 178 E-4
A23: 70100259 | B23: CAMION GRUA ARTICULADA HIAB X-HIDUO 188 E5 | C23: =COUNTIF(U:U,A23) -> 1 | D23: 291256.26 | E23: =D23*C23 -> 291256.26 | F23: =AVERAGEIF(U:U,A23,T:T) -> 0.17392875 | H23: 2026 | I23: 3 | J23: 2602274 | K23: COMERCIAL KAUFMANN S.A. | L23: CANAL KAUFMANN | M23: IZAJE | O23: ZONA CENTRO - SANTIAGO | P23: KEVIN FLEFEL | Q23: 87.277857 | R23: -65.724378 | S23: 21.553479 | T23: 0.24695243 | U23: 70100251 | V23: GRUA ARTICULADA HIAB X-HIDUO 188 E-5 | W23: Estrella Rodriguez | X23: 1-PROYECTO COMERCIAL | Y23: Facturas clientes - 96572360C | Z23: 500442 | AA23: 46112 | AB23: COMERCIAL KAUFMANN S.A. | AC23: 88910 | AD23: 76238635-6 | AE23: 70100221 | AF23: 70100221 | AI23: 70100259 | AJ23: CAMION GRUA ARTICULADA HIAB X-HIDUO 188 E5
A24: 70100247 | B24: GRUA ARTICULADA HIAB IQ 1188 E-9 JIB | C24: =COUNTIF(U:U,A24) -> 1 | D24: 378014.06 | E24: =D24*C24 -> 378014.06 | F24: =AVERAGEIF(U:U,A24,T:T) -> 0.21285273 | H24: 2026 | I24: 5 | J24: 2604264 | K24: TRANSPORTES BELLO E HIJOS Y LTDA. | L24: CANAL PROPIO | M24: IZAJE | P24: FRANCO MODINGER | Q24: 92.631368 | R24: -70.22552 | S24: 22.405849 | T24: 0.24188187 | U24: 70100249 | V24: GRUA ARTICULADA HIAB X-CLX 178 E-4 | W24: Estrella Rodriguez | X24: 1-PROYECTO COMERCIAL | Y24: Orden fabricación: 70100249 | Z24: 520725 | AA24: 46156 | AB24: TRANSPORTES BELLO E HIJOS Y LTDA. | AC24: 92938 | AD24: 76238635-6 | AE24: 70100212 | AF24: 70100212 | AI24: 70100247 | AJ24: GRUA ARTICULADA HIAB IQ 1188 E-9 JIB
A25: 70100157 | B25: GRUA HIAB X-CL 8 B3 | C25: =COUNTIF(U:U,A25) -> 1 | D25: 72256.158 | E25: =D25*C25 -> 72256.158 | F25: =AVERAGEIF(U:U,A25,T:T) -> 0.20010266 | H25: 2026 | I25: 5 | J25: 2604501 | K25: CULTIVOS CARLOS ÁLVARO RAIN MACÍAS E.I.R.L | L25: CANAL PROPIO | M25: IZAJE | P25: EDUARDO OÑATE | Q25: 73.944917 | R25: -55.85713 | S25: 18.087787 | T25: 0.24461164 | U25: 70100249 | V25: GRUA ARTICULADA HIAB X-CLX 178 E-4 | W25: Estrella Rodriguez | X25: 1-PROYECTO COMERCIAL | Y25: Entregas - 78002854C | Z25: 529956 | AA25: 46178 | AB25: CULTIVOS CARLOS ÁLVARO RAIN MACÍAS E.I.R.L | AC25: 95287 | AD25: 76386938-5 | AE25: 70100200 | AF25: 70100200 | AI25: 70100157 | AJ25: GRUA HIAB X-CL 8 B3
A26: 70100294 | B26: GRUA HIAB CL 16 B-3 MARINA | C26: =COUNTIF(U:U,A26) -> 5 | D26: 25727.359 | E26: =D26*C26 -> 128636.8 | F26: =AVERAGEIF(U:U,A26,T:T) -> 0.26505418 | H26: 2025 | I26: 11 | J26: 2509155 | K26: AGENCIAS UNIVERSALES S A | L26: COMERCIAL ZONA CENTRO | M26: IZAJE | P26: BENJAMIN FUENZALIDA | Q26: 91.732357 | R26: -74.575502 | S26: 17.156855 | T26: 0.18703166 | U26: 70100249 | V26: GRUA ARTICULADA HIAB X-CLX 178 E-4 | W26: Estrella Rodriguez | X26: 1-PROYECTO COMERCIAL | Y26: Orden fabricación: 70100249 | Z26: 446105 | AA26: 45985 | AB26: AGENCIAS UNIVERSALES S A | AC26: 78961 | AD26: 77789445-5 | AE26: 70100195 | AF26: 70100195 | AI26: 70100294 | AJ26: GRUA HIAB CL 16 B-3 MARINA
A27: 70100174 | B27: CAMION GRUA ARTICULADA HIAB X-HIPRO 558 EP-5 | C27: =COUNTIF(U:U,A27) -> 2 | D27: 337867.94 | E27: =D27*C27 -> 675735.88 | F27: =AVERAGEIF(U:U,A27,T:T) -> 0.15732089 | H27: 2025 | I27: 11 | J27: 2509156 | K27: AGENCIAS UNIVERSALES S A | L27: COMERCIAL ZONA CENTRO | M27: IZAJE | P27: BENJAMIN FUENZALIDA | Q27: 91.732357 | R27: -72.72675 | S27: 19.005607 | T27: 0.20718543 | U27: 70100249 | V27: GRUA ARTICULADA HIAB X-CLX 178 E-4 | W27: Estrella Rodriguez | X27: 1-PROYECTO COMERCIAL | Y27: Orden fabricación: 70100249 | Z27: 448717 | AA27: 45989 | AB27: AGENCIAS UNIVERSALES S A | AC27: 79379 | AD27: 97006000-6 | AE27: 70100173 | AF27: 70100173 | AI27: 70100174 | AJ27: CAMION GRUA ARTICULADA HIAB X-HIPRO 558 EP-5
A28: 70100267 | B28: GRUA ARTICULADA HIAB X-HIPRO 548 E-9 año 2022 | C28: =COUNTIF(U:U,A28) -> 1 | D28: 184270.65 | E28: =D28*C28 -> 184270.65 | F28: =AVERAGEIF(U:U,A28,T:T) -> 0.17010491 | H28: 2025 | I28: 11 | J28: 2509157 | K28: AGENCIAS UNIVERSALES S A | L28: COMERCIAL ZONA CENTRO | M28: IZAJE | P28: BENJAMIN FUENZALIDA | Q28: 91.732357 | R28: -72.819033 | S28: 18.913324 | T28: 0.20617942 | U28: 70100249 | V28: GRUA ARTICULADA HIAB X-CLX 178 E-4 | W28: Estrella Rodriguez | X28: 1-PROYECTO COMERCIAL | Y28: Orden fabricación: 70100249 | Z28: 447719 | AA28: 45988 | AB28: AGENCIAS UNIVERSALES S A | AC28: 79374 | AD28: 10201610-6 | AE28: 70100164 | AF28: 70100164 | AI28: 70100267 | AJ28: GRUA ARTICULADA HIAB X-HIPRO 548 E-9 año 2022
A29: 70100169 | B29: GRUA ARTICULADA HIAB X-HIPRO 302 E-8 | C29: =COUNTIF(U:U,A29) -> 1 | D29: 141626.23 | E29: =D29*C29 -> 141626.23 | F29: =AVERAGEIF(U:U,A29,T:T) -> 0.32849697 | H29: 2025 | I29: 11 | J29: 2509158 | K29: AGENCIAS UNIVERSALES S A | L29: COMERCIAL ZONA CENTRO | M29: IZAJE | P29: BENJAMIN FUENZALIDA | Q29: 91.732357 | R29: -75.360313 | S29: 16.372044 | T29: 0.17847621 | U29: 70100249 | V29: GRUA ARTICULADA HIAB X-CLX 178 E-4 | W29: Estrella Rodriguez | X29: 1-PROYECTO COMERCIAL | Y29: Orden fabricación: 70100249 | Z29: 445538 | AA29: 45982 | AB29: AGENCIAS UNIVERSALES S A | AC29: 78973 | AD29: 76367961-6 | AE29: 70100206 | AF29: 70100206 | AI29: 70100169 | AJ29: GRUA ARTICULADA HIAB X-HIPRO 302 E-8
A30: 70100159 | B30: GRUA ARTICULADA HIAB X-HIPRO 362 EP-5 EVO | C30: =COUNTIF(U:U,A30) -> 13 | D30: 111962.9 | E30: =D30*C30 -> 1455517.7 | F30: =AVERAGEIF(U:U,A30,T:T) -> -0.0068320273 | H30: 2025 | I30: 11 | J30: 2509159 | K30: AGENCIAS UNIVERSALES S A | L30: COMERCIAL ZONA CENTRO | M30: IZAJE | P30: BENJAMIN FUENZALIDA | Q30: 91.732357 | R30: -75.12157 | S30: 16.610787 | T30: 0.18107882 | U30: 70100249 | V30: GRUA ARTICULADA HIAB X-CLX 178 E-4 | W30: Estrella Rodriguez | X30: 1-PROYECTO COMERCIAL | Y30: Orden fabricación: 70100249 | Z30: 441152 | AA30: 45978 | AB30: AGENCIAS UNIVERSALES S A | AC30: 78381 | AD30: 76367961-6 | AE30: 70100206 | AF30: 70100206 | AI30: 70100159 | AJ30: GRUA ARTICULADA HIAB X-HIPRO 362 EP-5 EVO
A31: 70100160 | B31: GRUA ARTICULADA HIAB X-HIPRO 558 EP-6 EVO | C31: =COUNTIF(U:U,A31) -> 3 | D31: 142118.08 | E31: =D31*C31 -> 426354.25 | F31: =AVERAGEIF(U:U,A31,T:T) -> -0.015329346 | H31: 2025 | I31: 11 | J31: 2509160 | K31: AGENCIAS UNIVERSALES S A | L31: COMERCIAL ZONA CENTRO | M31: IZAJE | P31: BENJAMIN FUENZALIDA | Q31: 91.732357 | R31: -74.850121 | S31: 16.882236 | T31: 0.18403796 | U31: 70100249 | V31: GRUA ARTICULADA HIAB X-CLX 178 E-4 | W31: Estrella Rodriguez | X31: 1-PROYECTO COMERCIAL | Y31: Orden fabricación: 70100249 | Z31: 447190 | AA31: 45987 | AB31: AGENCIAS UNIVERSALES S A | AC31: 79151 | AD31: 76367961-6 | AE31: 70100206 | AF31: 70100206 | AI31: 70100160 | AJ31: GRUA ARTICULADA HIAB X-HIPRO 558 EP-6 EVO
A32: 13171059 | B32: GRUA ARTICULADA HIAB X-CLX 288 EP-5 MARINA | C32: =COUNTIF(U:U,A32) -> 1 | D32: =Q145*1000 -> 53393.206 | E32: =D32*C32 -> 53393.206 | F32: =AVERAGEIF(U:U,A32,T:T) -> 0.18185622 | H32: 2025 | I32: 11 | J32: 2509162 | K32: AGENCIAS UNIVERSALES S A | L32: COMERCIAL ZONA CENTRO | M32: IZAJE | P32: BENJAMIN FUENZALIDA | Q32: 91.732357 | R32: -75.281719 | S32: 16.450638 | T32: 0.17933299 | U32: 70100249 | V32: GRUA ARTICULADA HIAB X-CLX 178 E-4 | W32: Estrella Rodriguez | X32: 1-PROYECTO COMERCIAL | Y32: Orden fabricación: 70100249 | Z32: 444594 | AA32: 45980 | AB32: AGENCIAS UNIVERSALES S A | AC32: 78604 | AD32: 91502000-3 | AE32: 70100212 | AF32: 70100212 | AI32: 13171059 | AJ32: GRUA ARTICULADA HIAB X-CLX 288 EP-5 MARINA
A33: 70100253 | B33: GRUA HIAB X-CLX 388 EP5 | C33: =COUNTIF(U:U,A33) -> 2 | D33: 72707.461 | E33: =D33*C33 -> 145414.92 | F33: =AVERAGEIF(U:U,A33,T:T) -> 0.17300804 | H33: 2025 | I33: 12 | J33: 2510159 | K33: SWITCH CHILE SERVICIOS LIMITADA | L33: COMERCIAL ZONA CENTRO | M33: IZAJE | P33: CARLOS SOTO | Q33: 378.01406 | R33: -297.55274 | S33: 80.461326 | T33: 0.21285273 | U33: 70100247 | V33: GRUA ARTICULADA HIAB IQ 1188 E-9 JIB | W33: Estrella Rodriguez | X33: 1-PROYECTO COMERCIAL | Y33: Orden fabricación: 70100247 | Z33: 464828 | AA33: 46021 | AB33: SWITCH CHILE SERVICIOS LIMITADA | AC33: 81827 | AD33: 96572360-9 | AE33: 70100164 | AF33: 70100164 | AI33: 70100253 | AJ33: GRUA HIAB X-CLX 388 EP5
A34: 70100043 | B34: GRUA HIAB X-CL 12 B3 | C34: =COUNTIF(U:U,A34) -> 1 | D34: 54843.88 | E34: =D34*C34 -> 54843.88 | F34: =AVERAGEIF(U:U,A34,T:T) -> 0.039361899 | H34: 2025 | I34: 12 | J34: 2509149 | K34: AGENCIAS UNIVERSALES S A | L34: COMERCIAL ZONA CENTRO | M34: IZAJE | P34: BENJAMIN FUENZALIDA | Q34: 65.62941 | R34: -54.823893 | S34: 10.805517 | T34: 0.16464444 | U34: 70100225 | V34: GRUA ARTICULADA HIAB X-CLX 088 E-4 | W34: Gloria ZuÃ±iga | X34: 1-PROYECTO COMERCIAL | Y34: reconoce Difiere Facturas clientes - 96566940C(Anulación) - 450552 | Z34: 467531 | AA34: 46028 | AB34: AGENCIAS UNIVERSALES S A | AC34: 80056 | AD34: 97023000-9 | AE34: 70100205 | AF34: 70100205 | AI34: 70100043 | AJ34: GRUA HIAB X-CL 12 B3
A35: 70100251 | B35: GRUA ARTICULADA HIAB X-HIDUO 188 E-5 | C35: =COUNTIF(U:U,A35) -> 1 | D35: 87277.857 | E35: =D35*C35 -> 87277.857 | F35: =AVERAGEIF(U:U,A35,T:T) -> 0.24695243 | H35: 2026 | I35: 1 | J35: 2509556 | K35: SALINAS Y FABRES SOCIEDAD ANONIMA | L35: CANAL PROPIO | M35: IZAJE | O35: ZONA NORTE - ANTOFAGASTA | P35: EDGARDO URREA | Q35: 257.14699 | R35: -175.01746 | S35: 82.129529 | T35: 0.31938748 | U35: 70100221 | V35: GRUA ARTICULADA HIAB X-HIPRO 858 E-8 | W35: Cristina Fuentes | X35: 1-PROYECTO COMERCIAL | Y35: Difiere Facturas clientes - 91502000C(Anulación) - 468090 | Z35: 481470 | AA35: 46076 | AB35: SOC CONTRACTUAL MINERA EL ABRA | AC35: 82197 | AD35: 96572360-9 | AE35: 70100167 | AF35: 70100167 | AI35: 70100251 | AJ35: GRUA ARTICULADA HIAB X-HIDUO 188 E-5
A36: 70100196 | B36: GRUA ARTICULADA HIAB X-CLX 288 EP-5 MARINA | C36: =COUNTIF(U:U,A36) -> 1 | D36: 55288.111 | E36: =D36*C36 -> 55288.111 | F36: =AVERAGEIF(U:U,A36,T:T) -> 0.19975132 | H36: 2026 | I36: 4 | J36: 2512452 | K36: VIA PENTAGRAMA SPA | L36: CANAL PROPIO | M36: IZAJE | O36: ZONA CENTRO - SANTIAGO | P36: CARLOS SOTO | Q36: 204.61182 | R36: -186.29028 | S36: 18.321537 | T36: 0.089542905 | U36: 70100221 | V36: GRUA ARTICULADA HIAB X-HIPRO 858 E-8 | W36: Estrella Rodriguez | X36: 1-PROYECTO COMERCIAL | Y36: RECONOCE INGRESO FACT-94192 VIA PENTAGRAMA - 502054 | Z36: 517357 | AA36: 46147 | AB36: VIA PENTAGRAMA SPA | AC36: 91640 | AD36: 96572360-9 | AE36: 70100167 | AF36: 70100167 | AI36: 70100196 | AJ36: GRUA ARTICULADA HIAB X-CLX 288 EP-5 MARINA
A37: 70100209 | B37: GRUA ARTICULADA HIAB X-CLX 328 EP-5 | C37: =COUNTIF(U:U,A37) -> 1 | D37: 107285.32 | E37: =D37*C37 -> 107285.32 | F37: =AVERAGEIF(U:U,A37,T:T) -> 0.23405326 | H37: 2026 | I37: 4 | J37: 2601252 | K37: VIA PENTAGRAMA SPA | L37: CANAL PROPIO | M37: IZAJE | O37: ZONA CENTRO - SANTIAGO | P37: CARLOS SOTO | Q37: 204.61182 | R37: -179.67154 | S37: 24.940281 | T37: 0.12189071 | U37: 70100221 | V37: GRUA ARTICULADA HIAB X-HIPRO 858 E-8 | W37: Estrella Rodriguez | X37: 1-PROYECTO COMERCIAL | Y37: RECONOCE VTA FE-94194 VIA PENTAGRAMA - 502060 | Z37: 517358 | AA37: 46147 | AB37: VIA PENTAGRAMA SPA | AC37: 91639 | AD37: 96572360-9 | AE37: 70100171 | AF37: 70100171 | AI37: 70100209 | AJ37: GRUA ARTICULADA HIAB X-CLX 328 EP-5
A38: 70901021 | B38: GRUA ARTICULADA HIAB X-HIPRO 362 EP-5 | C38: =COUNTIF(U:U,A38) -> 2 | D38: 140000 | E38: =D38*C38 -> 280000 | F38: =AVERAGEIF(U:U,A38,T:T) -> 0.30669003 | H38: 2026 | I38: 4 | J38: 2602439 | K38: BESALCO MAQUINARIAS S A | L38: CANAL PROPIO | M38: IZAJE | O38: ZONA CENTRO - SANTIAGO | P38: RICARDO SANCHEZ | Q38: 229.493 | R38: -182.42653 | S38: 47.06647 | T38: 0.20508892 | U38: 70100221 | V38: GRUA ARTICULADA HIAB X-HIPRO 858 E-8 | W38: Estrella Rodriguez | X38: 1-PROYECTO COMERCIAL | Y38: Facturas clientes - 79633220C | Z38: 515552 | AA38: 46141 | AB38: BESALCO MAQUINARIAS S A | AC38: 91629 | AD38: 96572360-9 | AE38: 70100171 | AF38: 70100171 | AI38: 70901021 | AJ38: GRUA ARTICULADA HIAB X-HIPRO 362 EP-5
A39: 70100206 | B39: GRUA ARTICULADA HIAB X-HIPRO 558 EP-5 | C39: =COUNTIF(U:U,A39) -> 11 | D39: 168000 | E39: =D39*C39 -> 1848000 | F39: =AVERAGEIF(U:U,A39,T:T) -> 0.25234891 | H39: 2026 | I39: 5 | J39: 2512453 | K39: VIA PENTAGRAMA SPA | L39: CANAL PROPIO | M39: IZAJE | O39: ZONA CENTRO - SANTIAGO | P39: CARLOS SOTO | Q39: 204.61182 | R39: -186.03063 | S39: 18.581188 | T39: 0.090811898 | U39: 70100221 | V39: GRUA ARTICULADA HIAB X-HIPRO 858 E-8 | W39: Cristina Fuentes | X39: 1-PROYECTO COMERCIAL | Y39: RECONOCE COSTOS GD 118854Entregas - 77201495C(Anulación) - 518879 | Z39: 530815 | AA39: 46181 | AB39: VIA PENTAGRAMA SPA | AC39: 94566 | AD39: 96572360-9 | AE39: 70100221 | AF39: 70100221 | AI39: 70100206 | AJ39: GRUA ARTICULADA HIAB X-HIPRO 558 EP-5
A40: 70100247 | C40: =SUM(C2:C39) -> 155 | E40: =SUM(E2:E39) -> 23116635 | F40: =AVERAGE(F2:F39) -> 0.20648841 | H40: 2026 | I40: 5 | J40: 2601525 | K40: Pesco Rental S.A. | L40: CANAL PROPIO | M40: IZAJE | O40: ZONA CENTRO - SANTIAGO | P40: CARLOS SOTO | Q40: 248.38497 | R40: -185.2887 | S40: 63.09627 | T40: 0.25402612 | U40: 70100221 | V40: GRUA ARTICULADA HIAB X-HIPRO 858 E-8 | W40: Gloria ZuÃ±iga | X40: 1-PROYECTO COMERCIAL | Y40: Revalorización de inventario | Z40: 527710 | AA40: 46171 | AB40: PESCO RENTAL S.A. | AC40: 94590 | AD40: 93659000-4 | AE40: 70100206 | AF40: 70100206
A41: 70100221 | H41: 2025 | I41: 7 | J41: 2505107 | K41: Pesco Rental S.A. | L41: COMERCIAL ZONA NORTE | M41: EQUIPOS ESPECIALES | N41: EQ. ESPECIALES - ASPIRACION | P41: DANIEL GAIOLI | Q41: 249.00299 | R41: -175.6961 | S41: 73.306892 | T41: 0.29440166 | U41: 70100221 | V41: GRUA ARTICULADA HIAB X-HIPRO 858 E-8 | W41: Estrella Rodriguez | X41: 1-PROYECTO COMERCIAL | Y41: Facturas clientes - 96912590C | Z41: 384488 | AA41: 45859 | AB41: PESCO RENTAL S.A. | AC41: 68131 | AD41: 93659000-4 | AE41: 70100275 | AF41: 70100275
A42: 70100211 | H42: 2025 | I42: 11 | J42: 2507296 | K42: Pesco Rental S.A. | L42: COMERCIAL ZONA CENTRO | M42: IZAJE | P42: CARLOS SOTO | Q42: 248.9014 | R42: -175.51765 | S42: 73.383748 | T42: 0.2948306 | U42: 70100221 | V42: GRUA ARTICULADA HIAB X-HIPRO 858 E-8 | W42: Estrella Rodriguez | X42: 1-PROYECTO COMERCIAL | Y42: Orden fabricación: 70100221 | Z42: 445418 | AA42: 45982 | AB42: PESCO RENTAL S.A. | AC42: 79156 | AD42: 97006000-6 | AE42: 70100170 | AF42: 70100170
A43: 70100206 | H43: 2025 | I43: 12 | J43: 2508636 | K43: COMERCIAL KAUFMANN S.A. | L43: COMERCIAL ZONA CENTRO | M43: IZAJE | P43: CARLOS SOTO | Q43: 240.70274 | R43: -175.02729 | S43: 65.675453 | T43: 0.2728488 | U43: 70100221 | V43: GRUA ARTICULADA HIAB X-HIPRO 858 E-8 | W43: Gloria ZuÃ±iga | X43: 1-PROYECTO COMERCIAL | Y43: reconoce activa Entregas - 96572360C(Anulación) - 451067 | Z43: 467747 | AA43: 46029 | AB43: COMERCIAL KAUFMANN S.A. | AC43: 81434 | AD43: 96566940-K | AE43: 70100225 | AF43: 70100225
A44: 70100275 | H44: 2025 | I44: 6 | J44: 2505102 | K44: SISTEMA DE TRANSMISION DEL NORTE S.A | L44: COMERCIAL ZONA CENTRO | M44: EQUIPOS ESPECIALES | N44: EQ. ESPECIALES - ELECTRICIDAD | P44: FRANCO MODINGER | Q44: 259.96954 | R44: -197.93137 | S44: 62.038174 | T44: 0.23863632 | U44: 70100220 | V44: CAMION GRUA ARTICULADA HIAB X-HIPRO 352 E-6 | W44: Estrella Rodriguez | X44: 1-PROYECTO COMERCIAL | Y44: Facturas clientes - 76410374C | Z44: 376174 | AA44: 45838 | AB44: SISTEMA DE TRANSMISION DEL NORTE S.A | AC44: 66957 | AD44: 96566940-K | AE44: 70100249 | AF44: 70100249
A45: 19502062 | H45: 2026 | I45: 3 | J45: 2510683 | K45: BANCO DE CREDITO E INVERSIONES | L45: CANAL PROPIO | M45: IZAJE | P45: EDGARDO URREA | Q45: 198.70417 | R45: -165.10126 | S45: 33.602915 | T45: 0.16911026 | U45: 70100212 | V45: GRUA ARTICULADA HIAB X-HIPRO 638 E-9 | W45: Estrella Rodriguez | X45: 1-PROYECTO COMERCIAL | Y45: Facturas clientes - 97006000C | Z45: 493153 | AA45: 46098 | AB45: EMPRESA DE SERVICIOS MISCKANTI LIMITADA | AC45: 89175 | AD45: 96566940-K | AE45: 70100249 | AF45: 70100249
A46: 70100165 | H46: 2026 | I46: 5 | J46: 2601524 | K46: Pesco Rental S.A. | L46: CANAL PROPIO | M46: IZAJE | O46: ZONA CENTRO - SANTIAGO | P46: CARLOS SOTO | Q46: 223.03366 | R46: -174.46045 | S46: 48.573202 | T46: 0.21778418 | U46: 70100212 | V46: GRUA ARTICULADA HIAB X-HIPRO 638 E-9 | W46: Estrella Rodriguez | X46: 1-PROYECTO COMERCIAL | Y46: Notas de crédito clientes - 97036000C | Z46: 526506 | AA46: 46170 | AB46: PESCO RENTAL S.A. | AC46: 94591 | AD46: 96566940-K | AE46: 70100249 | AF46: 70100249
A47: 70100173 | H47: 2025 | I47: 9 | J47: 2507299 | K47: Pesco Rental S.A. | L47: COMERCIAL ZONA CENTRO | M47: IZAJE | P47: CARLOS SOTO | Q47: 220.9314 | R47: -148.54707 | S47: 72.384328 | T47: 0.32763259 | U47: 70100212 | V47: GRUA ARTICULADA HIAB X-HIPRO 638 E-9 | W47: Estrella Rodriguez | X47: 1-PROYECTO COMERCIAL | Y47: Orden fabricación: 49970100167 | Z47: 421302 | AA47: 45930 | AB47: PESCO RENTAL S.A. | AC47: 74505 | AD47: 96566940-K | AE47: 70100249 | AF47: 70100249
A48: 70100253 | H48: 2025 | I48: 11 | J48: 2508472 | K48: SALINAS Y FABRES SOCIEDAD ANONIMA | L48: COMERCIAL ZONA CENTRO | M48: IZAJE | P48: CARLOS SOTO | Q48: 193.7658 | R48: -148.41184 | S48: 45.353965 | T48: 0.23406589 | U48: 70100212 | V48: GRUA ARTICULADA HIAB X-HIPRO 638 E-9 | W48: Gloria ZuÃ±iga | X48: 1-PROYECTO COMERCIAL | Y48: reconoce Difiere Facturas clientes - 91502000C(Anulación) - 423581 | Z48: 450129 | AA48: 45993 | AB48: SALINAS Y FABRES SOCIEDAD ANONIMA | AC48: 79154 | AD48: 96566940-K | AE48: 70100249 | AF48: 70100249
A49: 70100169 | H49: 2025 | I49: 11 | J49: 2509369 | K49: SOCIEDAD TRANSPORTES THOMAS LIMITADA | L49: COMERCIAL ZONA CENTRO | M49: EQUIPOS ESPECIALES | N49: EQ. ESPEC. - MANEJO RESIDUOS | P49: JOSE CERDA | Q49: 119.07484 | R49: -196.49063 | S49: -77.415791 | T49: -0.65014397 | U49: 70100212 | V49: GRUA ARTICULADA HIAB X-HIPRO 638 E-9 | W49: Estrella Rodriguez | X49: 1-PROYECTO COMERCIAL | Y49: Orden fabricación: 70100212 | Z49: 448740 | AA49: 45989 | AB49: SOCIEDAD TRANSPORTES THOMAS LIMITADA | AC49: 79284 | AD49: 96566940-K | AE49: 70100249 | AF49: 70100249
A50: 70100167 | H50: 2025 | I50: 12 | J50: 2509306 | K50: BANCO DE CREDITO E INVERSIONES | L50: COMERCIAL ZONA NORTE | M50: IZAJE | P50: EDGARDO URREA | Q50: 198.72271 | R50: -167.22189 | S50: 31.500822 | T50: 0.15851647 | U50: 70100212 | V50: GRUA ARTICULADA HIAB X-HIPRO 638 E-9 | W50: Estrella Rodriguez | X50: 1-PROYECTO COMERCIAL | Y50: Orden fabricación: 70100212 | Z50: 457352 | AA50: 46007 | AB50: BANCO DE CREDITO E INVERSIONES | AC50: 82013 | AD50: 96566940-K | AE50: 70100249 | AF50: 70100249
A51: 13171059 | H51: 2025 | I51: 12 | J51: 2509321 | K51: SALINAS Y FABRES SOCIEDAD ANONIMA | L51: COMERCIAL ZONA CENTRO | M51: IZAJE | P51: CARLOS SOTO | Q51: 203.92484 | R51: -163.92875 | S51: 39.996091 | T51: 0.19613153 | U51: 70100212 | V51: GRUA ARTICULADA HIAB X-HIPRO 638 E-9 | W51: Estrella Rodriguez | X51: 1-PROYECTO COMERCIAL | Y51: Orden fabricación: 70100212 | Z51: 458454 | AA51: 46008 | AB51: SALINAS Y FABRES SOCIEDAD ANONIMA | AC51: 81435 | AD51: 96566940-K | AE51: 70100166 | AF51: 70100166
A52: 70100195 | H52: 2025 | I52: 8 | J52: 2502419 | K52: COMERCIAL KAUFMANN S.A. | L52: COMERCIAL ZONA CENTRO | M52: CANAL KAUFMANN | P52: KEVIN FLEFEL | Q52: 266.1782 | R52: -199.6115 | S52: 66.566696 | T52: 0.2500832 | U52: 70100211 | V52: GRUA ARTICULADA HIAB X-HIPRO 858 E-10 | W52: Estrella Rodriguez | X52: 1-PROYECTO COMERCIAL | Y52: Facturas clientes - 96572360C | Z52: 401476 | AA52: 45896 | AB52: COMERCIAL KAUFMANN S.A. | AC52: 71737 | AD52: 96566940-K | AE52: 70100166 | AF52: 70100166
A53: 70100166 | H53: 2026 | I53: 6 | J53: 2604537 | K53: DELFIN ECEQUEL VARGAS CARDENAS | L53: CANAL PROPIO | M53: IZAJE | P53: EDUARDO OÑATE | Q53: 107.28532 | R53: -82.174842 | S53: 25.110479 | T53: 0.23405326 | U53: 70100209 | V53: GRUA ARTICULADA HIAB X-CLX 328 EP-5 | W53: Estrella Rodriguez | X53: 1-PROYECTO COMERCIAL | Y53: Orden fabricación: 70100209 | Z53: 533974 | AA53: 46185 | AB53: SERVICIOS SERVISUR LIMITADA | AC53: 97275 | AD53: 96566940-K | AE53: 70100166 | AF53: 70100166
A54: 70100200 | H54: 2025 | I54: 7 | J54: 2505173 | K54: COMERCIAL KAUFMANN S.A. | L54: COMERCIAL ZONA NORTE | M54: CANAL KAUFMANN | P54: KEVIN FLEFEL | Q54: 178.72652 | R54: -120.72381 | S54: 58.002718 | T54: 0.32453335 | U54: 70100206 | V54: GRUA ARTICULADA HIAB X-HIPRO 558 EP-5 | W54: Estrella Rodriguez | X54: 1-PROYECTO COMERCIAL | Y54: Facturas clientes - 96572360C | Z54: 386528 | AA54: 45863 | AB54: COMERCIAL KAUFMANN S.A. | AC54: 68858 | AD54: 97004000-5 | AE54: 70100166 | AF54: 70100166
A55: 70100259 | H55: 2025 | I55: 10 | J55: 2508422 | K55: SOCIEDAD DE SERVICIOS GENERALES RJ LIMITADA | L55: COMERCIAL ZONA CENTRO | M55: IZAJE | P55: BENJAMIN FUENZALIDA | Q55: 163.44329 | R55: -126.80831 | S55: 36.634979 | T55: 0.2241449 | U55: 70100206 | V55: GRUA ARTICULADA HIAB X-HIPRO 558 EP-5 | W55: George Illanes | X55: 1-PROYECTO COMERCIAL | Y55: Orden fabricación: 4999990001 | Z55: 429574 | AA55: 45946 | AB55: SOCIEDAD DE SERVICIOS GENERALES RJ LIMITADA | AC55: 75787 | AD55: 96572360-9 | AE55: 70100164 | AF55: 70100164
A56: 70100251 | H56: 2025 | I56: 10 | J56: 2508423 | K56: SOCIEDAD DE SERVICIOS GENERALES RJ LIMITADA | L56: COMERCIAL ZONA CENTRO | M56: IZAJE | P56: BENJAMIN FUENZALIDA | Q56: 163.48102 | R56: -125.6953 | S56: 37.785726 | T56: 0.23113219 | U56: 70100206 | V56: GRUA ARTICULADA HIAB X-HIPRO 558 EP-5 | W56: George Illanes | X56: 1-PROYECTO COMERCIAL | Y56: Orden fabricación: 4999990001 | Z56: 432288 | AA56: 45953 | AB56: SOCIEDAD DE SERVICIOS GENERALES RJ LIMITADA | AC56: 76358 | AD56: 97006000-6 | AE56: 70100212 | AF56: 70100212
A57: 70100249 | H57: 2025 | I57: 10 | J57: 2508424 | K57: SOCIEDAD DE SERVICIOS GENERALES RJ LIMITADA | L57: COMERCIAL ZONA CENTRO | M57: IZAJE | P57: BENJAMIN FUENZALIDA | Q57: 163.55245 | R57: -126.52498 | S57: 37.027467 | T57: 0.22639507 | U57: 70100206 | V57: GRUA ARTICULADA HIAB X-HIPRO 558 EP-5 | W57: George Illanes | X57: 1-PROYECTO COMERCIAL | Y57: Orden fabricación: 4999990001 | Z57: 431670 | AA57: 45952 | AB57: SOCIEDAD DE SERVICIOS GENERALES RJ LIMITADA | AC57: 76210 | AD57: 91502000-3 | AE57: 70100212 | AF57: 70100212
A58: 70100225 | H58: 2025 | I58: 10 | J58: 2510269 | K58: PORSCHE CHILE SPA | L58: COMERCIAL ZONA CENTRO | M58: IZAJE | P58: CARLOS SOTO | Q58: 165.15269 | R58: -124.56217 | S58: 40.590517 | T58: 0.24577569 | U58: 70100206 | V58: GRUA ARTICULADA HIAB X-HIPRO 558 EP-5 | W58: Estrella Rodriguez | X58: 1-PROYECTO COMERCIAL | Y58: Facturas clientes - 76245828C | Z58: 432080 | AA58: 46000 | AB58: PORSCHE CHILE SPA | AD58: 76132627-9 | AE58: 70100259 | AF58: 70100259
A59: 70100289 | H59: 2025 | I59: 11 | J59: 2505064 | K59: G.T.A. CHILE SPA | L59: COMERCIAL ZONA NORTE | M59: IZAJE | P59: EDGARDO URREA | Q59: 156.93957 | R59: -116.73806 | S59: 40.201503 | T59: 0.25615913 | U59: 70100206 | V59: GRUA ARTICULADA HIAB X-HIPRO 558 EP-5 | W59: George Illanes | X59: 1-PROYECTO COMERCIAL | Y59: Orden fabricación: 70100206 | Z59: 447704 | AA59: 45988 | AB59: G.T.A. CHILE SPA | AC59: 79505 | AD59: 76030114-0 | AE59: 70100212 | AF59: 70100212
A60: 70100294 | H60: 2025 | I60: 11 | J60: 2508637 | K60: CONSTRUCTORA SALFA S A | L60: COMERCIAL ZONA CENTRO | M60: IZAJE | P60: CARLOS SOTO | Q60: 165.95061 | R60: -129.39673 | S60: 36.553886 | T60: 0.22026967 | U60: 70100206 | V60: GRUA ARTICULADA HIAB X-HIPRO 558 EP-5 | W60: Estrella Rodriguez | X60: 1-PROYECTO COMERCIAL | Y60: Orden fabricación: 70100206 | Z60: 446500 | AA60: 45986 | AB60: CONSTRUCTORA SALFA S A | AC60: 79163 | AD60: 91502000-3 | AE60: 70100221 | AF60: 70100221
H61: 2025 | I61: 12 | J61: 2505065 | K61: G.T.A. CHILE SPA | L61: COMERCIAL ZONA CENTRO | M61: IZAJE | P61: EDGARDO URREA | Q61: 166.33857 | R61: -122.62013 | S61: 43.718447 | T61: 0.26282808 | U61: 70100206 | V61: GRUA ARTICULADA HIAB X-HIPRO 558 EP-5 | W61: Estrella Rodriguez | X61: 1-PROYECTO COMERCIAL | Y61: Facturas clientes - 76284920C | Z61: 460284 | AA61: 46013 | AB61: G.T.A. CHILE SPA | AC61: 81060 | AD61: 91502000-3 | AE61: 70100275 | AF61: 70100275
H62: 2025 | I62: 12 | J62: 2505066 | K62: G.T.A. CHILE SPA | L62: COMERCIAL ZONA CENTRO | M62: IZAJE | P62: EDGARDO URREA | Q62: 166.33857 | R62: -122.93826 | S62: 43.40031 | T62: 0.26091549 | U62: 70100206 | V62: GRUA ARTICULADA HIAB X-HIPRO 558 EP-5 | W62: Estrella Rodriguez | X62: 1-PROYECTO COMERCIAL | Y62: Facturas clientes - 76284920C | Z62: 460312 | AA62: 46013 | AB62: G.T.A. CHILE SPA | AC62: 81069 | AD62: 77117942-8 | AE62: 70100247 | AF62: 70100247
H63: 2025 | I63: 12 | J63: 2505067 | K63: G.T.A. CHILE SPA | L63: COMERCIAL ZONA CENTRO | M63: IZAJE | P63: EDGARDO URREA | Q63: 166.33857 | R63: -122.14433 | S63: 44.194241 | T63: 0.26568847 | U63: 70100206 | V63: GRUA ARTICULADA HIAB X-HIPRO 558 EP-5 | W63: Estrella Rodriguez | X63: 1-PROYECTO COMERCIAL | Y63: Facturas clientes - 76284920C | Z63: 460377 | AA63: 46013 | AB63: G.T.A. CHILE SPA | AC63: 81125 | AD63: 96572360-9 | AE63: 70100165 | AF63: 70100165
H64: 2026 | I64: 2 | J64: 2510396 | K64: COMERCIAL KAUFMANN S.A. | L64: CANAL KAUFMANN | M64: IZAJE | O64: ZONA CENTRO - SANTIAGO | P64: CARLOS SOTO | Q64: 189.67353 | R64: -145.09672 | S64: 44.576809 | T64: 0.23501861 | U64: 70100205 | V64: GRUA ARTICULADA HIAB X-HIPRO 548 E-9 | W64: Estrella Rodriguez | X64: 1-PROYECTO COMERCIAL | Y64: RECONOCE COSTOS GRUA ARTICULADA HIAB X-HIPRO 548 | Z64: 488427 | AA64: 46090 | AB64: HIAB FINLAND OY | AC64: 86515 | AD64: 96572360-9 | AE64: 70100165 | AF64: 70100165
H65: 2025 | I65: 11 | J65: 2508541 | K65: BANCO ITAU CHILE | L65: COMERCIAL ZONA NORTE | M65: IZAJE | P65: EDGARDO URREA | Q65: 188.08668 | R65: -142.84569 | S65: 45.240989 | T65: 0.24053266 | U65: 70100205 | V65: GRUA ARTICULADA HIAB X-HIPRO 548 E-9 | W65: George Illanes | X65: 1-PROYECTO COMERCIAL | Y65: Orden fabricación: 70100205 | Z65: 445794 | AA65: 45985 | AB65: TRANSPORTES AVA LIMITADA | AC65: 79506 | AD65: 91502000-3 | AE65: 70100164 | AF65: 70100164
H66: 2025 | I66: 12 | J66: 2510395 | K66: COMERCIAL KAUFMANN S.A. | L66: COMERCIAL ZONA CENTRO | M66: IZAJE | P66: CARLOS SOTO | Q66: 189.52342 | R66: -169.29092 | S66: 20.232502 | T66: 0.10675463 | U66: 70100205 | V66: GRUA ARTICULADA HIAB X-HIPRO 548 E-9 | W66: Javier Ballesteros | X66: 1-PROYECTO COMERCIAL | Y66: Orden fabricación: 70100205 | Z66: 465718 | AA66: 46022 | AB66: COMERCIAL KAUFMANN S.A. | AC66: 81836 | AD66: 76245828-4 | AE66: 70100206 | AF66: 70100206
H67: 2025 | I67: 7 | J67: 2507580 | K67: TRANSPORTE MARITIMO RUIZ-ISLA LIMITADA | L67: COMERCIAL ZONA SUR | M67: IZAJE | P67: EDUARDO OÑATE | Q67: 43.944303 | R67: -35.122009 | S67: 8.8222936 | T67: 0.2007608 | U67: 70100200 | V67: GRUA ARTICULADA HIAB X-CLX 248 EP-4 MARINA | W67: Estrella Rodriguez | X67: 1-PROYECTO COMERCIAL | Y67: Facturas clientes - 76386938C | Z67: 388818 | AA67: 45868 | AB67: TRANSPORTE MARITIMO RUIZ-ISLA LIMITADA | AC67: 69465 | AD67: 96566940-K | AE67: 70100157 | AF67: 70100157
H68: 2026 | I68: 2 | J68: 2602388 | K68: DETROIT S.A. | L68: CANAL PROPIO | M68: IZAJE | P68: EDUARDO OÑATE | Q68: 55.288111 | R68: -44.244238 | S68: 11.043873 | T68: 0.19975132 | U68: 70100196 | V68: GRUA ARTICULADA HIAB X-CLX 288 EP-5 MARINA | W68: Estrella Rodriguez | X68: 1-PROYECTO COMERCIAL | Y68: Facturas clientes - 81271100C | Z68: 486333 | AA68: 46079 | AB68: DETROIT S.A. | AC68: 86183 | AD68: 76615380-1 | AE68: 70100289 | AF68: 70100289
H69: 2025 | I69: 8 | J69: 2508021 | K69: SERVICIOS MARÍTIMOS, TRANSPORTE, ASESORÍA Y CONSTRUCCIÓN SPA | L69: COMERCIAL ZONA SUR | M69: IZAJE | P69: EDUARDO OÑATE | Q69: 53.504385 | R69: -44.493421 | S69: 9.0109633 | T69: 0.16841542 | U69: 70100195 | V69: GRUA ARTICULADA HIAB X-CLX 288 EP-4 MARINA | W69: Estrella Rodriguez | X69: 1-PROYECTO COMERCIAL | Y69: Facturas clientes - 77789445C | Z69: 390679 | AA69: 45873 | AB69: SERVICIOS MARÍTIMOS, TRANSPORTE, ASESORÍA Y CONSTRUCCIÓN SPA | AC69: 69462 | AD69: 96572360-9 | AE69: 70100205 | AF69: 70100205
H70: 2025 | I70: 12 | J70: 2511006 | K70: SOCIEDAD RODERIK AVILA Y COMPANIA LIMITADA | L70: COMERCIAL ZONA NORTE | M70: EQUIPOS ESPECIALES | N70: EQ. ESPEC. - MANEJO RESIDUOS | P70: BENJAMIN FUENZALIDA | Q70: 337.86794 | R70: -284.32959 | S70: 53.538354 | T70: 0.15845941 | U70: 70100174 | V70: CAMION GRUA ARTICULADA HIAB X-HIPRO 558 EP-5 | W70: Estrella Rodriguez | X70: 1-PROYECTO COMERCIAL | Y70: Notas de crédito clientes - 97030000C | Z70: 453893 | AA70: 46003 | AB70: SOCIEDAD RODERIK AVILA Y COMPANIA LIMITADA | AC70: 80384 | AD70: 96572360-9 | AE70: 70100205 | AF70: 70100205
H71: 2025 | I71: 12 | J71: 2511007 | K71: SOCIEDAD RODERIK AVILA Y COMPANIA LIMITADA | L71: COMERCIAL ZONA NORTE | M71: EQUIPOS ESPECIALES | N71: EQ. ESPEC. - MANEJO RESIDUOS | P71: BENJAMIN FUENZALIDA | Q71: 337.86794 | R71: -285.09892 | S71: 52.769018 | T71: 0.15618238 | U71: 70100174 | V71: CAMION GRUA ARTICULADA HIAB X-HIPRO 558 EP-5 | W71: Estrella Rodriguez | X71: 1-PROYECTO COMERCIAL | Y71: Notas de crédito clientes - 97030000C | Z71: 453895 | AA71: 46003 | AB71: SOCIEDAD RODERIK AVILA Y COMPANIA LIMITADA | AC71: 80383 | AD71: 97030000-7 | AE71: 70100166 | AF71: 70100166
H72: 2026 | I72: 1 | J72: 2511182 | K72: MAQ RENT SPA | L72: CANAL PROPIO | M72: IZAJE | O72: ZONA NORTE - ANTOFAGASTA | P72: EDGARDO URREA | Q72: 319.9127 | R72: -291.84381 | S72: 28.068895 | T72: 0.087739232 | U72: 70100173 | V72: CAMION GRUA ARTICULADA HIAB X-HIPRO 418 EP-5 | W72: Cristina Fuentes | X72: 1-PROYECTO COMERCIAL | Y72: REVERSA INGRESO DIFERIDO PROY 2511182 | Z72: 481468 | AA72: 46076 | AB72: MAQ RENT SPA | AC72: 82199 | AD72: 16842281-4 | AE72: 70100294 | AF72: 70100294
H73: 2026 | I73: 1 | J73: 2511183 | K73: MAQ RENT SPA | L73: CANAL PROPIO | M73: IZAJE | O73: ZONA NORTE - ANTOFAGASTA | P73: EDGARDO URREA | Q73: 319.9127 | R73: -283.49566 | S73: 36.417042 | T73: 0.11383431 | U73: 70100173 | V73: CAMION GRUA ARTICULADA HIAB X-HIPRO 418 EP-5 | W73: Cristina Fuentes | X73: 1-PROYECTO COMERCIAL | Y73: REVERSA INGRESO DIFERIDO PROY 2511183 | Z73: 481469 | AA73: 46076 | AB73: MAQ RENT SPA | AC73: 82195 | AD73: 96572360-9 | AE73: 70100275 | AF73: 70100275
H74: 2025 | I74: 11 | J74: 2508103 | K74: BANCO DE CREDITO E INVERSIONES | L74: COMERCIAL ZONA NORTE | M74: IZAJE | P74: EDGARDO URREA | Q74: 276.6621 | R74: -220.65111 | S74: 56.010987 | T74: 0.20245269 | U74: 70100173 | V74: CAMION GRUA ARTICULADA HIAB X-HIPRO 418 EP-5 | W74: George Illanes | X74: 1-PROYECTO COMERCIAL | Y74: Orden fabricación: 81310217 | Z74: 449009 | AA74: 45992 | AB74: CONSTRUCCIÓN E INGENIERÍA ELÉCTRICA HÉCTOR DAVID QUISBERT VARGAS E.I.R | AC74: 79507 | AD74: 97006000-6 | AE74: 70100212 | AF74: 70100212
H75: 2025 | I75: 12 | J75: 2512466 | K75: SOCIEDAD DE SERVICIOS GENERALES RJ LIMITADA | L75: COMERCIAL ZONA NORTE | M75: EQUIPOS ESPECIALES | N75: EQ. ESPEC. - MANEJO RESIDUOS | P75: BENJAMIN FUENZALIDA | Q75: 321.97228 | R75: -269.13935 | S75: 52.832933 | T75: 0.16409156 | U75: 70100173 | V75: CAMION GRUA ARTICULADA HIAB X-HIPRO 418 EP-5 | W75: Estrella Rodriguez | X75: 1-PROYECTO COMERCIAL | Y75: Facturas clientes - 76367961C | Z75: 462798 | AA75: 46017 | AB75: SOCIEDAD RODERIK AVILA Y COMPANIA LIMITADA | AC75: 82209 | AD75: 78130200-7 | AE75: 70100174 | AF75: 70100174
H76: 2026 | I76: 3 | J76: 2601405 | K76: COMERCIAL KAUFMANN S.A. | L76: CANAL PROPIO | M76: IZAJE | O76: ZONA CENTRO - SANTIAGO | P76: CARLOS SOTO | Q76: 127.94624 | R76: -96.773789 | S76: 31.172453 | T76: 0.24363711 | U76: 70100171 | V76: GRUA ARTICULADA HIAB X-HIPRO 362 EP-5 | W76: Estrella Rodriguez | X76: 1-PROYECTO COMERCIAL | Y76: Facturas clientes - 96572360C | Z76: 499281 | AA76: 46111 | AB76: COMERCIAL KAUFMANN S.A. | AC76: 88777 | AD76: 78130200-7 | AE76: 70100174 | AF76: 70100174
H77: 2026 | I77: 3 | J77: 2601407 | K77: COMERCIAL KAUFMANN S.A. | L77: CANAL PROPIO | M77: IZAJE | O77: ZONA CENTRO - SANTIAGO | P77: CARLOS SOTO | Q77: 127.94624 | R77: -97.286086 | S77: 30.660156 | T77: 0.23963311 | U77: 70100171 | V77: GRUA ARTICULADA HIAB X-HIPRO 362 EP-5 | W77: Estrella Rodriguez | X77: 1-PROYECTO COMERCIAL | Y77: Facturas clientes - 96572360C | Z77: 499293 | AA77: 46111 | AB77: COMERCIAL KAUFMANN S.A. | AC77: 88778 | AD77: 96572360-9 | AE77: 70100167 | AF77: 70100167
H78: 2026 | I78: 4 | J78: 2601414 | K78: COMERCIAL KAUFMANN S.A. | L78: CANAL PROPIO | M78: IZAJE | O78: ZONA CENTRO - SANTIAGO | P78: CARLOS SOTO | Q78: 127.95274 | R78: -97.232087 | S78: 30.72065 | T78: 0.24009373 | U78: 70100171 | V78: GRUA ARTICULADA HIAB X-HIPRO 362 EP-5 | W78: Nicolas Moreno | X78: 1-PROYECTO COMERCIAL | Y78: Facturas clientes - 96572360C | Z78: 514073 | AA78: 46140 | AB78: COMERCIAL KAUFMANN S.A. | AC78: 91714 | AD78: 96572360-9 | AE78: 70100267 | AF78: 70100267
H79: 2026 | I79: 4 | J79: 2602378 | K79: COMERCIAL KAUFMANN S.A. | L79: CANAL KAUFMANN | M79: IZAJE | O79: ZONA CENTRO - SANTIAGO | P79: KEVIN FLEFEL | Q79: 136.30801 | R79: -103.13083 | S79: 33.177183 | T79: 0.24339863 | U79: 70100171 | V79: GRUA ARTICULADA HIAB X-HIPRO 362 EP-5 | W79: Estrella Rodriguez | X79: 1-PROYECTO COMERCIAL | Y79: RECONOCE COSTOS GD 115092(Anulación) - 502959 | Z79: 518840 | AA79: 46152 | AB79: COMERCIAL KAUFMANN S.A. | AC79: 91909 | AD79: 77208238-K | AE79: 70100289 | AF79: 70100289
H80: 2026 | I80: 4 | J80: 2603411 | K80: BANCO DE CREDITO E INVERSIONES | L80: CANAL PROPIO | M80: IZAJE | O80: ZONA CENTRO - SANTIAGO | P80: CARLOS SOTO | Q80: 138.00715 | R80: -94.896559 | S80: 43.110594 | T80: 0.31237942 | U80: 70100171 | V80: GRUA ARTICULADA HIAB X-HIPRO 362 EP-5 | W80: Estrella Rodriguez | X80: 1-PROYECTO COMERCIAL | Y80: Facturas clientes - 97006000C | Z80: 516077 | AA80: 46142 | AB80: CONSTRUCTORA SALFA S A | AC80: 91882 | AD80: 76307553-2 | AE80: 70100169 | AF80: 70100169
H81: 2025 | I81: 6 | J81: 2505249 | K81: SALINAS Y FABRES SOCIEDAD ANONIMA | L81: COMERCIAL ZONA CENTRO | M81: IZAJE | P81: CARLOS SOTO | Q81: 132.0404 | R81: -99.446144 | S81: 32.594256 | T81: 0.24685063 | U81: 70100171 | V81: GRUA ARTICULADA HIAB X-HIPRO 362 EP-5 | W81: Pedro Hernandez | X81: 1-PROYECTO COMERCIAL | Y81: Orden fabricación: 70115008 | Z81: 376030 | AA81: 45838 | AB81: SALINAS Y FABRES SOCIEDAD ANONIMA | AC81: 66987 | AD81: 76307553-2 | AE81: 70100171 | AF81: 70100171
H82: 2025 | I82: 6 | J82: 2506058 | K82: SALINAS Y FABRES SOCIEDAD ANONIMA | L82: COMERCIAL ZONA NORTE | M82: IZAJE | P82: EDGARDO URREA | Q82: 133.99054 | R82: 0 | S82: 133.99054 | T82: 1 | U82: 70100171 | V82: GRUA ARTICULADA HIAB X-HIPRO 362 EP-5 | W82: Estrella Rodriguez | X82: 1-PROYECTO COMERCIAL | Y82: Facturas clientes - 91502000C | Z82: 375243 | AA82: 45838 | AB82: SOC CONTRACTUAL MINERA EL ABRA | AC82: 66400 | AD82: 93659000-4 | AE82: 70100165 | AF82: 70100165
H83: 2025 | I83: 9 | J83: 2507042 | K83: BANCO SANTANDER CHILE | L83: COMERCIAL ZONA CENTRO | M83: IZAJE | P83: CARLOS SOTO | Q83: 136.91982 | R83: -96.437226 | S83: 40.482589 | T83: 0.2956664 | U83: 70100171 | V83: GRUA ARTICULADA HIAB X-HIPRO 362 EP-5 | W83: Estrella Rodriguez | X83: 1-PROYECTO COMERCIAL | Y83: Orden fabricación: 81310200 | Z83: 420346 | AA83: 45929 | AB83: INGENIERÍA Y TECNOLOGÍA SPA | AC83: 74507 | AD83: 93659000-4 | AE83: 70100165 | AF83: 70100165
H84: 2025 | I84: 10 | J84: 2508634 | K84: COMERCIAL KAUFMANN S.A. | L84: COMERCIAL ZONA CENTRO | M84: IZAJE | P84: CARLOS SOTO | Q84: 127.96972 | R84: -91.999927 | S84: 35.969791 | T84: 0.28108049 | U84: 70100171 | V84: GRUA ARTICULADA HIAB X-HIPRO 362 EP-5 | W84: Estrella Rodriguez | X84: 1-PROYECTO COMERCIAL | Y84: Orden fabricación: 70100171 | Z84: 435676 | AA84: 45960 | AB84: COMERCIAL KAUFMANN S.A. | AC84: 77016 | AD84: 93659000-4 | AE84: 70100165 | AF84: 70100165
H85: 2025 | I85: 10 | J85: 2508635 | K85: COMERCIAL KAUFMANN S.A. | L85: COMERCIAL ZONA CENTRO | M85: IZAJE | P85: CARLOS SOTO | Q85: 127.96972 | R85: -91.838985 | S85: 36.130733 | T85: 0.28233815 | U85: 70100171 | V85: GRUA ARTICULADA HIAB X-HIPRO 362 EP-5 | W85: Estrella Rodriguez | X85: 1-PROYECTO COMERCIAL | Y85: Orden fabricación: 70100171 | Z85: 435732 | AA85: 45960 | AB85: COMERCIAL KAUFMANN S.A. | AC85: 77017 | AD85: 93659000-4 | AE85: 70100165 | AF85: 70100165
H86: 2025 | I86: 12 | J86: 2511064 | K86: BK SPA | L86: COMERCIAL ZONA CENTRO | M86: EQUIPOS ESPECIALES | N86: EQ. ESPECIALES - ELECTRICIDAD | P86: FRANCO MODINGER | Q86: 151.38016 | R86: -93.624879 | S86: 57.755283 | T86: 0.38152478 | U86: 70100171 | V86: GRUA ARTICULADA HIAB X-HIPRO 362 EP-5 | W86: Estrella Rodriguez | X86: 1-PROYECTO COMERCIAL | Y86: Orden fabricación: 70100171 | Z86: 465835 | AA86: 46022 | AB86: ENEL DISTRIBUCION CHILE S.A. | AC86: 82205 | AD86: 96942440-1 | AE86: 70100167 | AF86: 70100167
H87: 2025 | I87: 12 | J87: 2511475 | K87: AUTOMOTORA ALAMEDA SPA | L87: COMERCIAL ZONA CENTRO | M87: IZAJE | P87: CARLOS SOTO | Q87: 136.60532 | R87: -109.11269 | S87: 27.492626 | T87: 0.2012559 | U87: 70100171 | V87: GRUA ARTICULADA HIAB X-HIPRO 362 EP-5 | W87: Estrella Rodriguez | X87: 1-PROYECTO COMERCIAL | Y87: Orden fabricación: 70100171 | Z87: 465999 | AA87: 46022 | AB87: AUTOMOTORA ALAMEDA SPA | AC87: 82037 | AD87: 76522179-K | AE87: 70100173 | AF87: 70100173
H88: 2025 | I88: 8 | J88: 2504625 | K88: ASTILLEROS Y MAESTRANZAS DE LA ARMADA | L88: COMERCIAL ZONA CENTRO | M88: INSTITUCIONALES | P88: CARLOS SOTO | Q88: 172.10084 | R88: -156.17291 | S88: 15.927928 | T88: 0.092549972 | U88: 70100170 | V88: CAMION GRUA ARTICULADA HIAB X-HIDUO 258 EP-5 | W88: Pedro Hernandez | X88: 1-PROYECTO COMERCIAL | Y88: Orden fabricación: 70100170 | Z88: 392421 | AA88: 45876 | AB88: ASTILLEROS Y MAESTRANZAS DE LA ARMADA | AC88: 69872 | AD88: 76522179-K | AE88: 70100173 | AF88: 70100173
H89: 2025 | I89: 10 | J89: 2509061 | K89: BANCO DE CREDITO E INVERSIONES | L89: COMERCIAL ZONA CENTRO | M89: IZAJE | P89: CARLOS SOTO | Q89: 194.99001 | R89: -159.4992 | S89: 35.490805 | T89: 0.18201345 | U89: 70100170 | V89: CAMION GRUA ARTICULADA HIAB X-HIDUO 258 EP-5 | W89: Gloria ZuÃ±iga | X89: 1-PROYECTO COMERCIAL | Y89: Reconoce Facturas clientes - 97006000C(Anulación) - 423871 | Z89: 437396 | AA89: 45967 | AB89: BANCO DE CREDITO E INVERSIONES | AC89: 77134 | AD89: 76086679-2 | AE89: 70100166 | AF89: 70100166
H90: 2025 | I90: 12 | J90: 2511063 | K90: BK SPA | L90: COMERCIAL ZONA CENTRO | M90: EQUIPOS ESPECIALES | N90: EQ. ESPECIALES - ELECTRICIDAD | P90: FRANCO MODINGER | Q90: 141.62623 | R90: -95.102444 | S90: 46.523788 | T90: 0.32849697 | U90: 70100169 | V90: GRUA ARTICULADA HIAB X-HIPRO 302 E-8 | W90: Estrella Rodriguez | X90: 1-PROYECTO COMERCIAL | Y90: Orden fabricación: 4999990001 | Z90: 465775 | AA90: 46022 | AB90: ENEL DISTRIBUCION CHILE S.A. | AC90: 82111 | AD90: 76009541-9 | AE90: 70100159 | AF90: 70100159
H91: 2025 | I91: 12 | J91: 2508632 | K91: COMERCIAL KAUFMANN S.A. | L91: COMERCIAL ZONA CENTRO | M91: IZAJE | P91: CARLOS SOTO | Q91: 110.65605 | R91: -85.833298 | S91: 24.822747 | T91: 0.22432346 | U91: 70100167 | V91: GRUA ARTICULADA HIAB X-HIDUO 298 EP-5 | W91: Estrella Rodriguez | X91: 1-PROYECTO COMERCIAL | Y91: Orden fabricación: 70100167 | Z91: 457942 | AA91: 46007 | AB91: COMERCIAL KAUFMANN S.A. | AC91: 81431 | AD91: 76009541-9 | AE91: 70100159 | AF91: 70100159
H92: 2025 | I92: 12 | J92: 2508633 | K92: COMERCIAL KAUFMANN S.A. | L92: COMERCIAL ZONA CENTRO | M92: IZAJE | P92: CARLOS SOTO | Q92: 110.65605 | R92: -85.833298 | S92: 24.822747 | T92: 0.22432346 | U92: 70100167 | V92: GRUA ARTICULADA HIAB X-HIDUO 298 EP-5 | W92: Estrella Rodriguez | X92: 1-PROYECTO COMERCIAL | Y92: Orden fabricación: 70100167 | Z92: 457934 | AA92: 46007 | AB92: COMERCIAL KAUFMANN S.A. | AC92: 81426 | AD92: 76009541-9 | AE92: 70100159 | AF92: 70100159
H93: 2025 | I93: 12 | J93: 2511032 | K93: COMERCIAL KAUFMANN S.A. | L93: COMERCIAL ZONA CENTRO | M93: IZAJE | P93: CARLOS SOTO | Q93: 110.65378 | R93: -85.303945 | S93: 25.34984 | T93: 0.22909148 | U93: 70100167 | V93: GRUA ARTICULADA HIAB X-HIDUO 298 EP-5 | W93: Estrella Rodriguez | X93: 1-PROYECTO COMERCIAL | Y93: Orden fabricación: 70100167 | Z93: 464771 | AA93: 46021 | AB93: COMERCIAL KAUFMANN S.A. | AC93: 81830 | AD93: 76009541-9 | AE93: 70100159 | AF93: 70100159
H94: 2025 | I94: 12 | J94: 2511149 | K94: GESTION VIAL S.A. | L94: COMERCIAL ZONA CENTRO | M94: IZAJE | P94: CARLOS SOTO | Q94: 113.197 | R94: -82.78578 | S94: 30.41122 | T94: 0.26865747 | U94: 70100167 | V94: GRUA ARTICULADA HIAB X-HIDUO 298 EP-5 | W94: Estrella Rodriguez | X94: 1-PROYECTO COMERCIAL | Y94: Orden fabricación: 70100167 | Z94: 460147 | AA94: 46013 | AB94: GESTION VIAL S.A. | AC94: 81423 | AD94: 76009541-9 | AE94: 70100159 | AF94: 70100159
H95: 2026 | I95: 1 | J95: 2511238 | K95: TRANSPORTES SILVIA EDITH OJEDA BARRIENTOS E.I.R.L. | L95: CANAL PROPIO | M95: IZAJE | O95: ZONA SUR - PTO MONTT | P95: EDUARDO OÑATE | Q95: 85.98842 | R95: -70.366299 | S95: 15.622121 | T95: 0.18167704 | U95: 70100166 | V95: GRUA ARTICULADA HIAB X-HIDUO 258 EP-5 | W95: Estrella Rodriguez | X95: 1-PROYECTO COMERCIAL | Y95: Entregas - 77274948C | Z95: 480238 | AA95: 46069 | AB95: ANTONIA SPA | AC95: 84282 | AD95: 76009541-9 | AE95: 70100159 | AF95: 70100159
H96: 2025 | I96: 7 | J96: 2506403 | K96: SOCIEDAD CONCESIONARIA COSTANERA NORTE S.A. | L96: COMERCIAL ZONA CENTRO | M96: IZAJE | P96: CARLOS SOTO | Q96: 108.01139 | R96: -66.468155 | S96: 41.543237 | T96: 0.38461903 | U96: 70100166 | V96: GRUA ARTICULADA HIAB X-HIDUO 258 EP-5 | W96: Pedro Hernandez | X96: 1-PROYECTO COMERCIAL | Y96: Orden fabricación: 70100166 | Z96: 382998 | AA96: 45853 | AB96: SOCIEDAD CONCESIONARIA COSTANERA NORTE S.A. | AC96: 69473 | AD96: 76009541-9 | AE96: 70100159 | AF96: 70100159
H97: 2025 | I97: 10 | J97: 2509203 | K97: BANCO DE CHILE | L97: COMERCIAL ZONA SUR | M97: IZAJE | P97: EDUARDO OÑATE | Q97: 87.011545 | R97: -66.025725 | S97: 20.98582 | T97: 0.24118431 | U97: 70100166 | V97: GRUA ARTICULADA HIAB X-HIDUO 258 EP-5 | W97: Gloria ZuÃ±iga | X97: 1-PROYECTO COMERCIAL | Y97: reconoce Facturas clientes - 97004000C(Anulación) - 423590 | Z97: 436776 | AA97: 45988 | AB97: INGENIERIA Y CONSTRUCION ELESUR SPA | AC97: 76984 | AD97: 76009541-9 | AE97: 70100159 | AF97: 70100159
H98: 2025 | I98: 11 | J98: 2509163 | K98: AGENCIAS UNIVERSALES S A | L98: COMERCIAL ZONA CENTRO | M98: IZAJE | P98: BENJAMIN FUENZALIDA | Q98: 105.33989 | R98: -77.818599 | S98: 27.521295 | T98: 0.26126184 | U98: 70100166 | V98: GRUA ARTICULADA HIAB X-HIDUO 258 EP-5 | W98: Estrella Rodriguez | X98: 1-PROYECTO COMERCIAL | Y98: Orden fabricación: 70100166 | Z98: 440897 | AA98: 45978 | AB98: AGENCIAS UNIVERSALES S A | AC98: 78139 | AD98: 76009541-9 | AE98: 70100159 | AF98: 70100159
H99: 2025 | I99: 11 | J99: 2509164 | K99: AGENCIAS UNIVERSALES S A | L99: COMERCIAL ZONA CENTRO | M99: IZAJE | P99: BENJAMIN FUENZALIDA | Q99: 105.33989 | R99: -78.034775 | S99: 27.305119 | T99: 0.25920967 | U99: 70100166 | V99: GRUA ARTICULADA HIAB X-HIDUO 258 EP-5 | W99: Estrella Rodriguez | X99: 1-PROYECTO COMERCIAL | Y99: Orden fabricación: 70100166 | Z99: 440172 | AA99: 45974 | AB99: AGENCIAS UNIVERSALES S A | AC99: 78380 | AD99: 76009541-9 | AE99: 70100159 | AF99: 70100159
H100: 2025 | I100: 11 | J100: 2509165 | K100: AGENCIAS UNIVERSALES S A | L100: COMERCIAL ZONA CENTRO | M100: IZAJE | P100: BENJAMIN FUENZALIDA | Q100: 105.33989 | R100: -77.757369 | S100: 27.582525 | T100: 0.2618431 | U100: 70100166 | V100: GRUA ARTICULADA HIAB X-HIDUO 258 EP-5 | W100: Estrella Rodriguez | X100: 1-PROYECTO COMERCIAL | Y100: Orden fabricación: 70100166 | Z100: 440947 | AA100: 45978 | AB100: AGENCIAS UNIVERSALES S A | AC100: 78140 | AD100: 76009541-9 | AE100: 70100159 | AF100: 70100159
...

Sheet Entregado (2026)
A1: Código | B1: Descripción | C1: Cantidad | D1: Precio de venta | E1: Costo Total | G1: Año | H1: NroMes | I1: Proyecto | J1: CodArticuloMayor | K1: Last DescripcionArticuloMayor | L1: Venta Real ML | M1: Cantidad Entregas | N1: Entrega Oportuna | O1: KPI Entrega Oportuna | P1: GuiaAdjunta | Q1: Fecha Comprometida
A2: 70100164 | B2: GRUA ARTICULADA HIAB X-HIPRO 408 E-8 | C2: =COUNTIF(J:J,A2) -> 5 | D2: =AVERAGEIF(J:J,A2,L:L) -> 157587.74 | E2: =D2*C2 -> 787938.69 | G2: 2026 | H2: 1 | I2: 2401483 | J2: 70100293 | K2: GRUA HIAB X-CL 16 B-3 | L2: -29370.639 | M2: -1 | N2: 0 | O2: 0 | P2: 28088 | Q2: 45351
A3: 70100221 | B3: GRUA ARTICULADA HIAB X-HIPRO 858 E-8 | C3: =COUNTIF(J:J,A3) -> 6 | D3: =AVERAGEIF(J:J,A3,L:L) -> 224810.07 | E3: =D3*C3 -> 1348860.4 | G3: 2026 | H3: 1 | I3: 2509556 | J3: 70100221 | K3: GRUA ARTICULADA HIAB X-HIPRO 858 E-8 | L3: 257146.99 | M3: 1 | N3: 1 | O3: 1 | P3: 82197 | Q3: 46081
A4: 70100267 | B4: GRUA ARTICULADA HIAB X-HIPRO 548 E-9 año 2022 | C4: =COUNTIF(J:J,A4) -> 2 | D4: =AVERAGEIF(J:J,A4,L:L) -> 56540.439 | E4: =D4*C4 -> 113080.88 | G4: 2026 | H4: 1 | I4: 2511123 | J4: 70100165 | K4: GRUA ARTICULADA HIAB X-HIPRO 418 EP-5 | L4: 136941.79 | M4: 1 | N4: 0 | O4: 0 | P4: 83316 | Q4: 46022
A5: 70100205 | B5: GRUA ARTICULADA HIAB X-HIPRO 548 E-9 | C5: =COUNTIF(J:J,A5) -> 1 | D5: =AVERAGEIF(J:J,A5,L:L) -> 189673.53 | E5: =D5*C5 -> 189673.53 | G5: 2026 | H5: 1 | I5: 2511124 | J5: 70100165 | K5: GRUA ARTICULADA HIAB X-HIPRO 418 EP-5 | L5: 136941.79 | M5: 1 | N5: 0 | O5: 0 | P5: 83317 | Q5: 46022
A6: 70100212 | B6: GRUA ARTICULADA HIAB X-HIPRO 638 E-9 | C6: =COUNTIF(J:J,A6) -> 2 | D6: =AVERAGEIF(J:J,A6,L:L) -> 210868.91 | E6: =D6*C6 -> 421737.83 | G6: 2026 | H6: 1 | I6: 2511182 | J6: 70100173 | K6: CAMION GRUA ARTICULADA HIAB X-HIPRO 418 EP-5 | L6: 319912.7 | M6: 1 | N6: 0 | O6: 0 | P6: 82199 | Q6: 46022
A7: 70100165 | B7: GRUA ARTICULADA HIAB X-HIPRO 418 EP-5 | C7: =COUNTIF(J:J,A7) -> 4 | D7: =AVERAGEIF(J:J,A7,L:L) -> 148800.28 | E7: =D7*C7 -> 595201.12 | G7: 2026 | H7: 1 | I7: 2511183 | J7: 70100173 | K7: CAMION GRUA ARTICULADA HIAB X-HIPRO 418 EP-5 | L7: 319912.7 | M7: 1 | N7: 0 | O7: 0 | P7: 82195 | Q7: 46022
A8: 70100173 | B8: CAMION GRUA ARTICULADA HIAB X-HIPRO 418 EP-5 | C8: =COUNTIF(J:J,A8) -> 2 | D8: =AVERAGEIF(J:J,A8,L:L) -> 319912.7 | E8: =D8*C8 -> 639825.41 | G8: 2026 | H8: 1 | I8: 2511238 | J8: 70100166 | K8: GRUA ARTICULADA HIAB X-HIDUO 258 EP-5 | L8: 85988.42 | M8: 1 | N8: 0 | O8: 0 | P8: 84282 | Q8: 45991
A9: 70100166 | B9: GRUA ARTICULADA HIAB X-HIDUO 258 EP-5 | C9: =COUNTIF(J:J,A9) -> 1 | D9: =AVERAGEIF(J:J,A9,L:L) -> 85988.42 | E9: =D9*C9 -> 85988.42 | G9: 2026 | H9: 1 | I9: 2511462 | J9: 70100164 | K9: GRUA ARTICULADA HIAB X-HIPRO 408 E-8 | L9: 155182.62 | M9: 1 | N9: 1 | O9: 1 | P9: 83429 | Q9: 46081
A10: 70100159 | B10: GRUA ARTICULADA HIAB X-HIPRO 362 EP-5 EVO | C10: =COUNTIF(J:J,A10) -> 13 | D10: =AVERAGEIF(J:J,A10,L:L) -> 111962.9 | E10: =D10*C10 -> 1455517.7 | G10: 2026 | H10: 1 | I10: 2601273 | J10: 70100289 | K10: GRUA ARTICULADA HIAB X-CL 23 B-4 | L10: 39031.678 | M10: 1 | N10: 1 | O10: 1 | P10: 84283 | Q10: 46053
A11: 70100160 | B11: GRUA ARTICULADA HIAB X-HIPRO 558 EP-6 EVO | C11: =COUNTIF(J:J,A11) -> 3 | D11: =AVERAGEIF(J:J,A11,L:L) -> 142118.08 | E11: =D11*C11 -> 426354.25 | G11: 2026 | H11: 1 | I11: 2601519 | J11: 70100253 | K11: GRUA HIAB X-CLX 388 EP5 | L11: 72468.825 | M11: 1 | N11: 1 | O11: 1 | P11: 84280 | Q11: 46053
A12: 70100289 | B12: GRUA ARTICULADA HIAB X-CL 23 B-4 | C12: =COUNTIF(J:J,A12) -> 1 | D12: =AVERAGEIF(J:J,A12,L:L) -> 39031.678 | E12: =D12*C12 -> 39031.678 | G12: 2026 | H12: 2 | I12: 2510396 | J12: 70100205 | K12: GRUA ARTICULADA HIAB X-HIPRO 548 E-9 | L12: 189673.53 | M12: 1 | N12: 0 | O12: 0 | P12: 86515 | Q12: 46022
A13: 70100171 | B13: GRUA ARTICULADA HIAB X-HIPRO 362 EP-5 | C13: =COUNTIF(J:J,A13) -> 5 | D13: =AVERAGEIF(J:J,A13,L:L) -> 131632.08 | E13: =D13*C13 -> 658160.39 | G13: 2026 | H13: 2 | I13: 2602197 | J13: 70100294 | K13: GRUA HIAB CL 16 B-3 MARINA | L13: 25586.496 | M13: 1 | N13: 1 | O13: 1 | P13: 86182 | Q13: 46081
... A15: 70100294 | B15: GRUA HIAB CL 16 B-3 MARINA | C15: =COUNTIF(J:J,A15) -> 3 | D15: =AVERAGEIF(J:J,A15,L:L) -> 25632.768 | E15: =D15*C15 -> 76898.305 | G15: 2026 | H15: 2 | I15: 2602388 | J15: 70100196 | K15: GRUA ARTICULADA HIAB X-CLX 288 EP-5 MARINA | L15: 55288.111 | M15: 1 | N15: 1 | O15: 1 | P15: 86183 | Q15: 46081
A16: 70100043 | B16: GRUA HIAB X-CL 12 B3 | C16: =COUNTIF(J:J,A16) -> 1 | D16: =AVERAGEIF(J:J,A16,L:L) -> 54843.88 | E16: =D16*C16 -> 54843.88 | G16: 2026 | H16: 3 | I16: 2506210 | J16: 70100164 | K16: GRUA ARTICULADA HIAB X-HIPRO 408 E-8 | L16: 160043.53 | M16: 1 | N16: 0 | O16: 0 | Q16: 45869
A17: 70100251 | B17: GRUA ARTICULADA HIAB X-HIDUO 188 E-5 | C17: =COUNTIF(J:J,A17) -> 1 | D17: =AVERAGEIF(J:J,A17,L:L) -> 87277.857 | E17: =D17*C17 -> 87277.857 | G17: 2026 | H17: 3 | I17: 2510072 | J17: 70100267 | K17: GRUA ARTICULADA HIAB X-HIPRO 548 E-9 año 2022 | L17: -89832.768 | M17: -1 | N17: 0 | O17: 0 | P17: 81417 | Q17: 45961
A18: 70100196 | B18: GRUA ARTICULADA HIAB X-CLX 288 EP-5 MARINA | C18: =COUNTIF(J:J,A18) -> 1 | D18: =AVERAGEIF(J:J,A18,L:L) -> 55288.111 | E18: =D18*C18 -> 55288.111 | G18: 2026 | H18: 3 | I18: 2510683 | J18: 70100212 | K18: GRUA ARTICULADA HIAB X-HIPRO 638 E-9 | L18: 198704.17 | M18: 1 | N18: 0 | O18: 0 | P18: 89175 | Q18: 46022
A19: 70100275 | B19: GRUA ARTICULADA HIAB X HIPRO 558 EP6 | C19: =COUNTIF(J:J,A19) -> 3 | D19: =AVERAGEIF(J:J,A19,L:L) -> 167462.22 | E19: =D19*C19 -> 502386.65 | G19: 2026 | H19: 3 | I19: 2511052 | J19: 70100267 | K19: GRUA ARTICULADA HIAB X-HIPRO 548 E-9 año 2022 | L19: 202913.65 | M19: 1 | N19: 0 | O19: 0 | P19: 88913 | Q19: 46022
A20: 70100249 | B20: GRUA ARTICULADA HIAB X-CLX 178 E-4 | C20: =COUNTIF(J:J,A20) -> 2 | D20: =AVERAGEIF(J:J,A20,L:L) -> 83288.143 | E20: =D20*C20 -> 166576.29 | G20: 2026 | H20: 3 | I20: 2511461 | J20: 70100164 | K20: GRUA ARTICULADA HIAB X-HIPRO 408 E-8 | L20: 155101.99 | M20: 1 | N20: 0 | O20: 0 | P20: 88814 | Q20: 46081
A21: 70100209 | B21: GRUA ARTICULADA HIAB X-CLX 328 EP-5 | C21: =COUNTIF(J:J,A21) -> 1 | D21: =AVERAGEIF(J:J,A21,L:L) -> 107285.32 | E21: =D21*C21 -> 107285.32 | G21: 2026 | H21: 3 | I21: 2511465 | J21: 70100164 | K21: GRUA ARTICULADA HIAB X-HIPRO 408 E-8 | L21: 155101.99 | M21: 1 | N21: 0 | O21: 0 | P21: 88848 | Q21: 46081
C22: =SUM(C2:C19) -> 56 | E22: =SUM(E2:E19) -> 7683480 | G22: 2026 | H22: 3 | I22: 2601405 | J22: 70100171 | K22: GRUA ARTICULADA HIAB X-HIPRO 362 EP-5 | L22: 127946.24 | M22: 1 | N22: 0 | O22: 0 | P22: 88777 | Q22: 46081
A23: 70100221 | G23: 2026 | H23: 3 | I23: 2601407 | J23: 70100171 | K23: GRUA ARTICULADA HIAB X-HIPRO 362 EP-5 | L23: 127946.24 | M23: 1 | N23: 0 | O23: 0 | P23: 88778 | Q23: 46081
A24: 70100275 | G24: 2026 | H24: 3 | I24: 2602264 | J24: 70100043 | K24: GRUA HIAB X-CL 12 B3 | L24: 54843.88 | M24: 1 | N24: 0 | O24: 0 | Q24: 46081
A25: 70100165 | G25: 2026 | H25: 3 | I25: 2602274 | J25: 70100251 | K25: GRUA ARTICULADA HIAB X-HIDUO 188 E-5 | L25: 87277.857 | M25: 1 | N25: 1 | O25: 1 | P25: 88910 | Q25: 46112
A26: 70100173 | G26: 2026 | H26: 3 | I26: 2603063 | J26: 70100275 | K26: GRUA ARTICULADA HIAB X HIPRO 558 EP6 | L26: 148757.15 | M26: 1 | N26: 1 | O26: 1 | P26: 88938 | Q26: 46112
A27: 70100253 | G27: 2026 | H27: 4 | I27: 2512452 | J27: 70100221 | K27: GRUA ARTICULADA HIAB X-HIPRO 858 E-8 | L27: 204611.82 | M27: 1 | N27: 0 | O27: 0 | P27: 91640 | Q27: 46053
A28: 70100166 | G28: 2026 | H28: 4 | I28: 2601252 | J28: 70100221 | K28: GRUA ARTICULADA HIAB X-HIPRO 858 E-8 | L28: 204611.82 | M28: 1 | N28: 0 | O28: 0 | P28: 91639 | Q28: 46081
A29: 70100251 | G29: 2026 | H29: 4 | I29: 2601259 | J29: 70100165 | K29: GRUA ARTICULADA HIAB X-HIPRO 418 EP-5 | L29: 166395.97 | M29: 1 | N29: 0 | O29: 0 | P29: 91888 | Q29: 46081
A30: 70100249 | G30: 2026 | H30: 4 | I30: 2601414 | J30: 70100171 | K30: GRUA ARTICULADA HIAB X-HIPRO 362 EP-5 | L30: 127952.74 | M30: 1 | N30: 0 | O30: 0 | P30: 91714 | Q30: 46081
A31: 70100289 | G31: 2026 | H31: 4 | I31: 2602378 | J31: 70100171 | K31: GRUA ARTICULADA HIAB X-HIPRO 362 EP-5 | L31: 136308.01 | M31: 1 | N31: 0 | O31: 0 | P31: 91909 | Q31: 46112
A32: 70100294 | G32: 2026 | H32: 4 | I32: 2602439 | J32: 70100221 | K32: GRUA ARTICULADA HIAB X-HIPRO 858 E-8 | L32: 229493 | M32: 1 | N32: 0 | O32: 0 | P32: 91629 | Q32: 46112
G33: 2026 | H33: 4 | I33: 2603411 | J33: 70100171 | K33: GRUA ARTICULADA HIAB X-HIPRO 362 EP-5 | L33: 138007.15 | M33: 1 | N33: 1 | O33: 1 | P33: 91882 | Q33: 46142
G34: 2026 | H34: 4 | I34: 2604201 | J34: 70100294 | K34: GRUA HIAB CL 16 B-3 MARINA | L34: 25774.664 | M34: 1 | N34: 1 | O34: 1 | P34: 91861 | Q34: 46142
G35: 2026 | H35: 4 | I35: 2604204 | J35: 70100294 | K35: GRUA HIAB CL 16 B-3 MARINA | L35: 25537.146 | M35: 1 | N35: 1 | O35: 1 | P35: 91859 | Q35: 46142
G36: 2026 | H36: 5 | I36: 2511427 | J36: 70100159 | K36: GRUA ARTICULADA HIAB X-HIPRO 362 EP-5 EVO | L36: 113863.64 | M36: 1 | N36: 0 | O36: 0 | P36: 94344 | Q36: 46142
G37: 2026 | H37: 5 | I37: 2511428 | J37: 70100159 | K37: GRUA ARTICULADA HIAB X-HIPRO 362 EP-5 EVO | L37: 112687.46 | M37: 1 | N37: 0 | O37: 0 | P37: 94326 | Q37: 46142
G38: 2026 | H38: 5 | I38: 2511429 | J38: 70100159 | K38: GRUA ARTICULADA HIAB X-HIPRO 362 EP-5 EVO | L38: 113863.64 | M38: 1 | N38: 0 | O38: 0 | P38: 94333 | Q38: 46142
G39: 2026 | H39: 5 | I39: 2511430 | J39: 70100159 | K39: GRUA ARTICULADA HIAB X-HIPRO 362 EP-5 EVO | L39: 112687.46 | M39: 1 | N39: 0 | O39: 0 | P39: 94331 | Q39: 46142
G40: 2026 | H40: 5 | I40: 2511434 | J40: 70100159 | K40: GRUA ARTICULADA HIAB X-HIPRO 362 EP-5 EVO | L40: 113863.64 | M40: 1 | N40: 1 | O40: 1 | P40: 94358 | Q40: 46173
G41: 2026 | H41: 5 | I41: 2511437 | J41: 70100159 | K41: GRUA ARTICULADA HIAB X-HIPRO 362 EP-5 EVO | L41: 113863.64 | M41: 1 | N41: 1 | O41: 1 | P41: 94352 | Q41: 46173
G42: 2026 | H42: 5 | I42: 2511438 | J42: 70100159 | K42: GRUA ARTICULADA HIAB X-HIPRO 362 EP-5 EVO | L42: 113805.19 | M42: 1 | N42: 1 | O42: 1 | P42: 94329 | Q42: 46173
G43: 2026 | H43: 5 | I43: 2511448 | J43: 70100160 | K43: GRUA ARTICULADA HIAB X-HIPRO 558 EP-6 EVO | L43: 145230.16 | M43: 1 | N43: 1 | O43: 1 | P43: 94356 | Q43: 46173
G44: 2026 | H44: 5 | I44: 2512453 | J44: 70100221 | K44: GRUA ARTICULADA HIAB X-HIPRO 858 E-8 | L44: 204611.82 | M44: 1 | N44: 0 | O44: 0 | P44: 94566 | Q44: 46053
... G61: 2026 | H61: 6 | I61: 2604537 | J61: 70100209 | K61: GRUA ARTICULADA HIAB X-CLX 328 EP-5 | L61: 107285.32 | M61: 1 | N61: 0 | O61: 0 | P61: 97275 | Q61: 46173

Sheet Backlog
A1: Código | B1: Descripción | C1: Cantidad | D1: Costo unitario promedio | E1: Total | G1: Trimestre | H1: Ejecutivo Responsable | I1: Departamento | J1: PC | K1: Cliente | L1: Código | M1: Equipos | N1: SAP | O1: Monto en moneda de Venta | P1: Moneda de Venta | Q1: Traspaso a USD | R1: USD - FILTRO | S1: Itemcode | T1: Descripcion | U1: Venta Estimada | V1: Fecha entrega proy | W1: Año | X1: Moneda | Y1: Backlog | Z1: tramo | AA1: Backlog Proyectado | AB1: DocStatus | AC1: RelacionPCProy | AD1: Código | AE1: Equipos | AF1: Descripcion
A2: 13171051 | B2: GRUA ARTICULADA HIAB IQ 1188 E-9 JIB | C2: =COUNTIF(M:M,B2) -> 2 | D2: =AVERAGEIF(M:M,B2,O:O) -> 295030 | E2: =D2*C2 -> 590060 | G2: 3 | H2: Bruno Ferrari | I2: CANAL PROPIO | J2: 2604641 | K2: TRANSPORTES MIGUEL ANGEL TORO HENRIQUEZ E.I.R.L | L2: 13171051 | M2: GRUA ARTICULADA HIAB IQ 1188 E-9 JIB | N2: OK | O2: 295030 | P2: USD | Q2: 295030 | R2: 295030
B3: CAMION GRUA ARTICULADA HIAB X-HIPRO 558 EP-5 | C3: =COUNTIF(M:M,B3) -> 1 | D3: =AVERAGEIF(M:M,B3,O:O) -> 382998 | E3: =D3*C3 -> 382998 | G3: 3 | H3: Bruno Ferrari | I3: CANAL PROPIO | J3: 2604646 | K3: GRUAS TORO SUR SPA | L3: 13171051 | M3: GRUA ARTICULADA HIAB IQ 1188 E-9 JIB | N3: OK | O3: 295030 | P3: USD | Q3: 295030 | R3: 295030
B4: CAMION GRUA ARTICULADA HIAB IQ 708 HIPRO E8 JIB 155Q-6 | C4: =COUNTIF(M:M,B4) -> 1 | D4: =AVERAGEIF(M:M,B4,O:O) -> 626373 | E4: =D4*C4 -> 626373 | G4: 3 | H4: Edgardo Urrea | I4: CANAL PROPIO | J4: 2604407 | K4: MAQ RENT SPA | L4: 0 | M4: CAMION GRUA ARTICULADA HIAB X-HIPRO 558 EP-5 | N4: OK | O4: 382998 | P4: USD | Q4: 382998 | R4: 382998
A5: 13171039 | B5: GRUA ARTICULADA HIAB X-HIDUO 188 E-5 | C5: =COUNTIF(M:M,B5) -> 3 | D5: =AVERAGEIF(M:M,B5,O:O) -> 91882 | E5: =D5*C5 -> 275646 | G5: 4 | H5: Franco Modinger | I5: CANAL PROPIO | J5: 2605175 | K5: SISTEMA DE TRANSMISION DEL SUR S.A. | L5: #N/A | M5: CAMION GRUA ARTICULADA HIAB IQ 708 HIPRO E8 JIB 155Q-6 | N5: OK | O5: 626373 | P5: USD | Q5: 626373 | R5: 626373
A6: 70100169 | B6: GRUA ARTICULADA HIAB X-HIPRO 302 E-8 | C6: =COUNTIF(M:M,B6) -> 2 | D6: =AVERAGEIF(M:M,B6,O:O) -> 125579.5 | E6: =D6*C6 -> 251159 | G6: 3 | H6: Carlos Soto | I6: CANAL PROPIO | J6: 2606593 | K6: BANCO DE CREDITO E INVERSIONES // GRANDLEASING | L6: 13171039 | M6: GRUA ARTICULADA HIAB X-HIDUO 188 E-5 | N6: OK | O6: 91882 | P6: USD | Q6: 91882 | R6: 91882
A7: 13171020 | B7: GRUA ARTICULADA HIAB X-HIPRO 362 EP-5 | C7: =COUNTIF(M:M,B7) -> 3 | D7: =AVERAGEIF(M:M,B7,O:O) -> 131679.33 | E7: =D7*C7 -> 395038 | G7: 3 | H7: Carlos Soto | I7: CANAL PROPIO | J7: 2606595 | K7: BANCO DE CREDITO E INVERSIONES // GRANDLEASING | L7: 13171039 | M7: GRUA ARTICULADA HIAB X-HIDUO 188 E-5 | N7: OK | O7: 91882 | P7: USD | Q7: 91882 | R7: 91882
A8: 70100205 | B8: GRUA ARTICULADA HIAB X-HIPRO 548 E-9 | C8: =COUNTIF(M:M,B8) -> 2 | D8: =AVERAGEIF(M:M,B8,O:O) -> 169832 | E8: =D8*C8 -> 339664 | G8: 3 | H8: Carlos Soto | I8: CANAL PROPIO | J8: 2606596 | K8: BANCO DE CREDITO E INVERSIONES // GRANDLEASING | L8: 13171039 | M8: GRUA ARTICULADA HIAB X-HIDUO 188 E-5 | N8: OK | O8: 91882 | P8: USD | Q8: 91882 | R8: 91882
A9: 70100165 | B9: GRUA ARTICULADA HIAB X-HIPRO 418 EP-5 | C9: =COUNTIF(M:M,B9) -> 2 | D9: =AVERAGEIF(M:M,B9,O:O) -> 159500 | E9: =D9*C9 -> 319000 | G9: 3 | H9: Carlos Soto | I9: CANAL PROPIO | J9: 2606598 | K9: BANCO DE CREDITO E INVERSIONES // GRANDLEASING | L9: 70100169 | M9: GRUA ARTICULADA HIAB X-HIPRO 302 E-8 | N9: OK | O9: 123429 | P9: USD | Q9: 123429 | R9: 123429
A10: 70100166 | B10: GRUA ARTICULADA HIAB X-HIDUO 258 EP-5 | C10: =COUNTIF(M:M,B10) -> 10 | D10: =AVERAGEIF(M:M,B10,O:O) -> 87840 | E10: =D10*C10 -> 878400 | G10: 3 | H10: Carlos Soto | I10: CANAL PROPIO | J10: 2606599 | K10: BANCO DE CREDITO E INVERSIONES // GRANDLEASING | L10: 13171020 | M10: GRUA ARTICULADA HIAB X-HIPRO 362 EP-5 | N10: OK | O10: 115400 | P10: USD | Q10: 115400 | R10: 115400
A11: 70100275 | B11: GRUA ARTICULADA HIAB X HIPRO 558 EP6 | C11: =COUNTIF(M:M,B11) -> 8 | D11: =AVERAGEIF(M:M,B11,O:O) -> 152640 | E11: =D11*C11 -> 1221120 | G11: 3 | H11: Carlos Soto | I11: CANAL PROPIO | J11: 2606606 | K11: BANCO DE CREDITO E INVERSIONES // GRANDLEASING | L11: 70100205 | M11: GRUA ARTICULADA HIAB X-HIPRO 548 E-9 | N11: OK | O11: 169832 | P11: USD | Q11: 169832 | R11: 169832
A12: 70100212 | B12: GRUA ARTICULADA HIAB X-HIPRO 638 E-9 | C12: =COUNTIF(M:M,B12) -> 1 | D12: =AVERAGEIF(M:M,B12,O:O) -> 222950 | E12: =D12*C12 -> 222950 | G12: 3 | H12: Carlos Soto | I12: CANAL PROPIO | J12: 2606608 | K12: BANCO DE CREDITO E INVERSIONES // GRANDLEASING | L12: 70100205 | M12: GRUA ARTICULADA HIAB X-HIPRO 548 E-9 | N12: OK | O12: 169832 | P12: USD | Q12: 169832 | R12: 169832
A13: 13171012 | B13: GRUA ARTICULADA HIAB X-HIPRO 858 E-8 | C13: =COUNTIF(M:M,B13) -> 1 | D13: =AVERAGEIF(M:M,B13,O:O) -> 246404 | E13: =D13*C13 -> 246404 | G13: 3 | H13: Carlos Soto | I13: CANAL PROPIO | J13: 2605228 | K13: METSO CHILE SPA | L13: 70100165 | M13: GRUA ARTICULADA HIAB X-HIPRO 418 EP-5 | N13: OK | O13: 159500 | P13: USD | Q13: 159500 | R13: 159500
A14: 70100160 | B14: GRUA ARTICULADA HIAB X-HIPRO 558 EP-6 EVO | C14: =COUNTIF(M:M,B14) -> 7 | D14: =AVERAGEIF(M:M,B14,O:O) -> 149080 | E14: =D14*C14 -> 1043560 | G14: 3 | H14: Carlos Soto | I14: CANAL PROPIO | J14: 2605229 | K14: METSO CHILE SPA | L14: 70100165 | M14: GRUA ARTICULADA HIAB X-HIPRO 418 EP-5 | N14: OK | O14: 159500 | P14: USD | Q14: 159500 | R14: 159500
A15: 70100159 | B15: GRUA ARTICULADA HIAB X-HIPRO 362 EP-5 EVO | C15: =COUNTIF(M:M,B15) -> 5 | D15: =AVERAGEIF(M:M,B15,O:O) -> 116822 | E15: =D15*C15 -> 584110 | G15: 3 | H15: Carlos Soto | I15: CANAL PROPIO | J15: 2605211 | K15: BANCO INTERNACIONAL // CONSTRUCTORA SALFA | L15: 13171020 | M15: GRUA ARTICULADA HIAB X-HIPRO 362 EP-5 | N15: OK | O15: 139819 | P15: USD | Q15: 139819 | R15: 139819
A16: 70100164 | B16: GRUA ARTICULADA HIAB X-HIPRO 408 E-8 | C16: =COUNTIF(M:M,B16) -> 1 | D16: =AVERAGEIF(M:M,B16,O:O) -> 155168 | E16: =D16*C16 -> 155168 | G16: 3 | H16: Carlos Soto | I16: CANAL PROPIO | J16: 2605212 | K16: BANCO INTERNACIONAL // CONSTRUCTORA SALFA | L16: 13171020 | M16: GRUA ARTICULADA HIAB X-HIPRO 362 EP-5 | N16: OK | O16: 139819 | P16: USD | Q16: 139819 | R16: 139819
C17: =SUM(C2:C16) -> 49 | E17: =SUM(E2:E16) -> 7531650 | G17: 3 | H17: Carlos Soto | I17: CANAL PROPIO | J17: 2605043 | K17: BESALCO MINERÍA S A | L17: 70100166 | M17: GRUA ARTICULADA HIAB X-HIDUO 258 EP-5 | N17: OK | O17: 87840 | P17: USD | Q17: 87840 | R17: 87840
G18: 3 | H18: Carlos Soto | I18: CANAL PROPIO | J18: 2605044 | K18: BESALCO MINERÍA S A | L18: 70100166 | M18: GRUA ARTICULADA HIAB X-HIDUO 258 EP-5 | N18: OK | O18: 87840 | P18: USD | Q18: 87840 | R18: 87840
G19: 3 | H19: Carlos Soto | I19: CANAL PROPIO | J19: 2605045 | K19: BESALCO MINERÍA S A | L19: 70100166 | M19: GRUA ARTICULADA HIAB X-HIDUO 258 EP-5 | N19: OK | O19: 87840 | P19: USD | Q19: 87840 | R19: 87840
G20: 3 | H20: Carlos Soto | I20: CANAL PROPIO | J20: 2605046 | K20: BESALCO MINERÍA S A | L20: 70100166 | M20: GRUA ARTICULADA HIAB X-HIDUO 258 EP-5 | N20: OK | O20: 87840 | P20: USD | Q20: 87840 | R20: 87840
G21: 3 | H21: Carlos Soto | I21: CANAL PROPIO | J21: 2605047 | K21: BESALCO MINERÍA S A | L21: 70100166 | M21: GRUA ARTICULADA HIAB X-HIDUO 258 EP-5 | N21: OK | O21: 87840 | P21: USD | Q21: 87840 | R21: 87840
G22: 3 | H22: Carlos Soto | I22: CANAL PROPIO | J22: 2605048 | K22: BESALCO MINERÍA S A | L22: 70100166 | M22: GRUA ARTICULADA HIAB X-HIDUO 258 EP-5 | N22: OK | O22: 87840 | P22: USD | Q22: 87840 | R22: 87840
G23: 3 | H23: Carlos Soto | I23: CANAL PROPIO | J23: 2605049 | K23: BESALCO MINERÍA S A | L23: 70100166 | M23: GRUA ARTICULADA HIAB X-HIDUO 258 EP-5 | N23: OK | O23: 87840 | P23: USD | Q23: 87840 | R23: 87840
G24: 3 | H24: Carlos Soto | I24: CANAL PROPIO | J24: 2605050 | K24: BESALCO MINERÍA S A | L24: 70100166 | M24: GRUA ARTICULADA HIAB X-HIDUO 258 EP-5 | N24: OK | O24: 87840 | P24: USD | Q24: 87840 | R24: 87840
G25: 3 | H25: Carlos Soto | I25: CANAL PROPIO | J25: 2605051 | K25: BESALCO MINERÍA S A | L25: 70100166 | M25: GRUA ARTICULADA HIAB X-HIDUO 258 EP-5 | N25: OK | O25: 87840 | P25: USD | Q25: 87840 | R25: 87840
G26: 3 | H26: Carlos Soto | I26: CANAL PROPIO | J26: 2605052 | K26: BESALCO MINERÍA S A | L26: 70100166 | M26: GRUA ARTICULADA HIAB X-HIDUO 258 EP-5 | N26: OK | O26: 87840 | P26: USD | Q26: 87840 | R26: 87840
G27: 3 | H27: Carlos Soto | I27: CANAL PROPIO | J27: 2605053 | K27: BESALCO MINERÍA S A | L27: 70100275 | M27: GRUA ARTICULADA HIAB X HIPRO 558 EP6 | N27: OK | O27: 152640 | P27: USD | Q27: 152640 | R27: 152640
G28: 3 | H28: Carlos Soto | I28: CANAL PROPIO | J28: 2605054 | K28: BESALCO MINERÍA S A | L28: 70100275 | M28: GRUA ARTICULADA HIAB X HIPRO 558 EP6 | N28: OK | O28: 152640 | P28: USD | Q28: 152640 | R28: 152640
G29: 3 | H29: Carlos Soto | I29: CANAL PROPIO | J29: 2605055 | K29: BESALCO MINERÍA S A | L29: 70100275 | M29: GRUA ARTICULADA HIAB X HIPRO 558 EP6 | N29: OK | O29: 152640 | P29: USD | Q29: 152640 | R29: 152640
G30: 3 | H30: Carlos Soto | I30: CANAL PROPIO | J30: 2605056 | K30: BESALCO MINERÍA S A | L30: 70100275 | M30: GRUA ARTICULADA HIAB X HIPRO 558 EP6 | N30: OK | O30: 152640 | P30: USD | Q30: 152640 | R30: 152640
E31: =SUM(E2:E10) -> 4058338 | G31: 4 | H31: Carlos Soto | I31: CANAL PROPIO | J31: 2605057 | K31: BESALCO MINERÍA S A | L31: 70100275 | M31: GRUA ARTICULADA HIAB X HIPRO 558 EP6 | N31: OK | O31: 152640 | P31: USD | Q31: 152640 | R31: 152640
G32: 4 | H32: Carlos Soto | I32: CANAL PROPIO | J32: 2605058 | K32: BESALCO MINERÍA S A | L32: 70100275 | M32: GRUA ARTICULADA HIAB X HIPRO 558 EP6 | N32: OK | O32: 152640 | P32: USD | Q32: 152640 | R32: 152640
G33: 4 | H33: Carlos Soto | I33: CANAL PROPIO | J33: 2605059 | K33: BESALCO MINERÍA S A | L33: 70100275 | M33: GRUA ARTICULADA HIAB X HIPRO 558 EP6 | N33: OK | O33: 152640 | P33: USD | Q33: 152640 | R33: 152640
G34: 4 | H34: Carlos Soto | I34: CANAL PROPIO | J34: 2605060 | K34: BESALCO MINERÍA S A | L34: 70100275 | M34: GRUA ARTICULADA HIAB X HIPRO 558 EP6 | N34: OK | O34: 152640 | P34: USD | Q34: 152640 | R34: 152640
G35: 3 | H35: Carlos Soto | I35: CANAL PROPIO | J35: 2607094 | K35: PESCO RENTAL S.A. | L35: 70100212 | M35: GRUA ARTICULADA HIAB X-HIPRO 638 E-9 | N35: OK | O35: 222950 | P35: USD | Q35: 222950 | R35: 222950
G36: 3 | H36: Carlos Soto | I36: CANAL PROPIO | J36: 2607095 | K36: PESCO RENTAL S.A. | L36: 13171012 | M36: GRUA ARTICULADA HIAB X-HIPRO 858 E-8 | N36: OK | O36: 246404 | P36: USD | Q36: 246404 | R36: 246404
G37: 3 | H37: Jose Cerda | I37: CANAL PROPIO | J37: 2511440 | K37: SOCIEDAD SERVICIOS INGENIERIA Y MANTENCION INTEGRAL MPM LIMITADA | L37: 70100160 | M37: GRUA ARTICULADA HIAB X-HIPRO 558 EP-6 EVO | N37: OK | O37: 149080 | P37: USD | Q37: 149080 | R37: 149080
G38: 3 | H38: Jose Cerda | I38: CANAL PROPIO | J38: 2511441 | K38: SOCIEDAD SERVICIOS INGENIERIA Y MANTENCION INTEGRAL MPM LIMITADA | L38: 70100160 | M38: GRUA ARTICULADA HIAB X-HIPRO 558 EP-6 EVO | N38: OK | O38: 149080 | P38: USD | Q38: 149080 | R38: 149080
G39: 3 | H39: Jose Cerda | I39: CANAL PROPIO | J39: 2511442 | K39: SOCIEDAD SERVICIOS INGENIERIA Y MANTENCION INTEGRAL MPM LIMITADA | L39: 70100160 | M39: GRUA ARTICULADA HIAB X-HIPRO 558 EP-6 EVO | N39: OK | O39: 149080 | P39: USD | Q39: 149080 | R39: 149080
G40: 3 | H40: Jose Cerda | I40: CANAL PROPIO | J40: 2511443 | K40: SOCIEDAD SERVICIOS INGENIERIA Y MANTENCION INTEGRAL MPM LIMITADA | L40: 70100160 | M40: GRUA ARTICULADA HIAB X-HIPRO 558 EP-6 EVO | N40: OK | O40: 149080 | P40: USD | Q40: 149080 | R40: 149080
G41: 3 | H41: Jose Cerda | I41: CANAL PROPIO | J41: 2511445 | K41: SOCIEDAD SERVICIOS INGENIERIA Y MANTENCION INTEGRAL MPM LIMITADA | L41: 70100160 | M41: GRUA ARTICULADA HIAB X-HIPRO 558 EP-6 EVO | N41: OK | O41: 149080 | P41: USD | Q41: 149080 | R41: 149080
G42: 3 | H42: Jose Cerda | I42: CANAL PROPIO | J42: 2511446 | K42: SOCIEDAD SERVICIOS INGENIERIA Y MANTENCION INTEGRAL MPM LIMITADA | L42: 70100160 | M42: GRUA ARTICULADA HIAB X-HIPRO 558 EP-6 EVO | N42: OK | O42: 149080 | P42: USD | Q42: 149080 | R42: 149080
G43: 3 | H43: Jose Cerda | I43: CANAL PROPIO | J43: 2511447 | K43: SOCIEDAD SERVICIOS INGENIERIA Y MANTENCION INTEGRAL MPM LIMITADA | L43: 70100160 | M43: GRUA ARTICULADA HIAB X-HIPRO 558 EP-6 EVO | N43: OK | O43: 149080 | P43: USD | Q43: 149080 | R43: 149080
G44: 3 | H44: Jose Cerda | I44: CANAL PROPIO | J44: 2511431 | K44: SOCIEDAD SERVICIOS INGENIERIA Y MANTENCION INTEGRAL MPM LIMITADA | L44: 70100159 | M44: GRUA ARTICULADA HIAB X-HIPRO 362 EP-5 EVO | N44: OK | O44: 116822 | P44: USD | Q44: 116822 | R44: 116822
G45: 3 | H45: Jose Cerda | I45: CANAL PROPIO | J45: 2511435 | K45: SOCIEDAD SERVICIOS INGENIERIA Y MANTENCION INTEGRAL MPM LIMITADA | L45: 70100159 | M45: GRUA ARTICULADA HIAB X-HIPRO 362 EP-5 EVO | N45: OK | O45: 116822 | P45: USD | Q45: 116822 | R45: 116822
G46: 3 | H46: Jose Cerda | I46: CANAL PROPIO | J46: 2511421 | K46: SOCIEDAD SERVICIOS INGENIERIA Y MANTENCION INTEGRAL MPM LIMITADA | L46: 70100159 | M46: GRUA ARTICULADA HIAB X-HIPRO 362 EP-5 EVO | N46: OK | O46: 116822 | P46: USD | Q46: 116822 | R46: 116822
... G48: 3 | H48: Jose Cerda | I48: CANAL PROPIO | J48: 2511426 | K48: SOCIEDAD SERVICIOS INGENIERIA Y MANTENCION INTEGRAL MPM LIMITADA | L48: 70100159 | M48: GRUA ARTICULADA HIAB X-HIPRO 362 EP-5 EVO | N48: OK | O48: 116822 | P48: USD | Q48: 116822 | R48: 116822
G49: 3 | H49: Jose Cerda | I49: CANAL PROPIO | J49: 2511460 | K49: SOCIEDAD TRANSPORTES THOMAS LIMITADA | L49: 70100169 | M49: GRUA ARTICULADA HIAB X-HIPRO 302 E-8 | N49: OK | O49: 127730 | P49: USD | Q49: 127730 | R49: 127730
G50: 3 | H50: Jose Cerda | I50: CANAL PROPIO | J50: 2511464 | K50: SOCIEDAD TRANSPORTES THOMAS LIMITADA | L50: 70100164 | M50: GRUA ARTICULADA HIAB X-HIPRO 408 E-8 | N50: OK | O50: 155168 | P50: USD | Q50: 155168 | R50: 155168

Sheet Stock
A1: ItemCode | B1: ItemName | C1: Cantidad | D1: Costo unitario | E1: Costo total | H1: NombreGrupoArticulos | I1: ItemCode | J1: ItemName | K1: Serial | L1: Indate | M1: Días en inventario | N1: Antiguedad Años | O1: Cantidad | P1: Costo Unit | Q1: Costo Total | R1: Categoria Antiguedad | T1: ItemCode | U1: ItemName
A2: 13171051 | B2: GRUA ARTICULADA HIAB IQ1188 E-9 JIB | C2: =COUNTIF(I:I,A2) -> 1 | D2: =AVERAGEIF(I:I,A2,P:P) -> 252902.12 | E2: =D2*C2 -> 252902.12 | H2: EQUIPOS IZAJE | I2: 70100276 | J2: CAMION GRUA ARTICULADA HIAB X-CLX 178 E-4 | K2: BL178CX00845 | L2: 46119 | M2: =365*N2 -> 94 | N2: 0.25753425 | O2: 1 | P2: 157628.61 | Q2: 157628.61 | R2: < 1 año
A3: 70100259 | B3: CAMION GRUA ARTICULADA HIAB X-HIDUO 188 E5 | C3: =COUNTIF(I:I,A3) -> 1 | D3: =AVERAGEIF(I:I,A3,P:P) -> 240598.42 | E3: =D3*C3 -> 240598.42 | H3: EQUIPOS IZAJE | I3: 70100259 | J3: CAMION GRUA ARTICULADA HIAB X-HIDUO 188 E5 | K3: BL188HD03882 | L3: 45756 | M3: =365*N3 -> 457 | N3: 1.2520548 | O3: 1 | P3: 240598.42 | Q3: 240598.42 | R3: >= 1 año
A4: 13171068 | B4: GRUA ARTICULADA HIAB IQ 1188 E-8 HIPRO EVO | C4: =COUNTIF(I:I,A4) -> 4 | D4: =AVERAGEIF(I:I,A4,P:P) -> 175584.79 | E4: =D4*C4 -> 702339.15 | H4: EQUIPOS IZAJE | I4: 13171068 | J4: GRUA ARTICULADA HIAB IQ 1188 E-8 HIPRO EVO | K4: 11880232 | L4: 46181 | M4: =365*N4 -> 32 | N4: 0.087671233 | O4: 1 | P4: 175584.79 | Q4: 175584.79 | R4: < 1 año
A5: 70100276 | B5: CAMION GRUA ARTICULADA HIAB X-CLX 178 E-4 | C5: =COUNTIF(I:I,A5) -> 1 | D5: =AVERAGEIF(I:I,A5,P:P) -> 157628.61 | E5: =D5*C5 -> 157628.61 | H5: EQUIPOS IZAJE | I5: 13171068 | J5: GRUA ARTICULADA HIAB IQ 1188 E-8 HIPRO EVO | K5: 11880233 | L5: 46181 | M5: =365*N5 -> 32 | N5: 0.087671233 | O5: 1 | P5: 175584.79 | Q5: 175584.79 | R5: < 1 año
A6: 13171012 | B6: GRUA ARTICULADA HIAB X-HIPRO 858 E-8 | C6: =COUNTIF(I:I,A6) -> 1 | D6: =AVERAGEIF(I:I,A6,P:P) -> 153744.77 | E6: =D6*C6 -> 153744.77 | H6: EQUIPOS IZAJE | I6: 13171068 | J6: GRUA ARTICULADA HIAB IQ 1188 E-8 HIPRO EVO | K6: 11880234 | L6: 46181 | M6: =365*N6 -> 32 | N6: 0.087671233 | O6: 1 | P6: 175584.79 | Q6: 175584.79 | R6: < 1 año
A7: 13171033 | B7: GRUA ARTICULADA HIAB X-HIPRO 638 E-9 | C7: =COUNTIF(I:I,A7) -> 2 | D7: =AVERAGEIF(I:I,A7,P:P) -> 149553.31 | E7: =D7*C7 -> 299106.62 | H7: EQUIPOS IZAJE | I7: 13171068 | J7: GRUA ARTICULADA HIAB IQ 1188 E-8 HIPRO EVO | K7: 11880235 | L7: 46181 | M7: =365*N7 -> 32 | N7: 0.087671233 | O7: 1 | P7: 175584.79 | Q7: 175584.79 | R7: < 1 año
A8: 19502062 | B8: GRUA ARTICULADA HIAB X-HIPRO 548 E-9 año 2022 | C8: =COUNTIF(I:I,A8) -> 1 | D8: =AVERAGEIF(I:I,A8,P:P) -> 145127.51 | E8: =D8*C8 -> 145127.51 | H8: EQUIPOS IZAJE | I8: 13171051 | J8: GRUA ARTICULADA HIAB IQ1188 E-9 JIB | K8: 11880248 | L8: 46181 | M8: =365*N8 -> 32 | N8: 0.087671233 | O8: 1 | P8: 252902.12 | Q8: 252902.12 | R8: < 1 año
A9: 13171066 | B9: HIAB 638 EP9 (EVO) | C9: =COUNTIF(I:I,A9) -> 2 | D9: =AVERAGEIF(I:I,A9,P:P) -> 141079.09 | E9: =D9*C9 -> 282158.18 | H9: EQUIPOS IZAJE | I9: 13171054 | J9: GRUA ARTICULADA HIAB SEA CRANE 201-3 | K9: S201000135 | L9: 44963 | M9: =365*N9 -> 1250 | N9: 3.4246575 | O9: 1 | P9: 53205.641 | Q9: 53205.641 | R9: < 1 año
A10: 19502041 | B10: HIAB X-HIPRO 548 E-9 | C10: =COUNTIF(I:I,A10) -> 3 | D10: =AVERAGEIF(I:I,A10,P:P) -> 125996 | E10: =D10*C10 -> 377988 | H10: EQUIPOS IZAJE | I10: 70100293 | J10: GRUA ARTICULADA HIAB X-CL 16 B-4 | K10: BLXCL1600351 | L10: 45342 | M10: =365*N10 -> 871 | N10: 2.3863014 | O10: 1 | P10: 18637.461 | Q10: 18637.461 | R10: < 1 año
A11: 13171064 | B11: Hiab 558 EP6 - EVO | C11: =COUNTIF(I:I,A11) -> 1 | D11: =AVERAGEIF(I:I,A11,P:P) -> 122572.44 | E11: =D11*C11 -> 122572.44 | H11: EQUIPOS IZAJE | I11: 13171024 | J11: GRUA ARTICULADA HIAB X-CLX 288 EP-4 MARINA | K11: BL288CX00271 | L11: 45621 | M11: =365*N11 -> 592 | N11: 1.6219178 | O11: 1 | P11: 43938.202 | Q11: 43938.202 | R11: < 1 año
A12: 13171065 | B12: HIAB 548 EP 9 (EVO) | C12: =COUNTIF(I:I,A12) -> 2 | D12: =AVERAGEIF(I:I,A12,P:P) -> 118916.29 | E12: =D12*C12 -> 237832.58 | H12: EQUIPOS IZAJE | I12: 13171059 | J12: GRUA ARTICULADA HIAB X-CLX 288 EP-5 MARINA | K12: BL288CX00231 | L12: 45244 | M12: =365*N12 -> 969 | N12: 2.6547945 | O12: 1 | P12: 44356.263 | Q12: 44356.263 | R12: >= 1 año
A13: 13171021 | B13: HIAB X-HIPRO 408 E-8 | C13: =COUNTIF(I:I,A13) -> 2 | D13: =AVERAGEIF(I:I,A13,P:P) -> 104802.54 | E13: =D13*C13 -> 209605.09 | H13: EQUIPOS IZAJE | I13: 13171059 | J13: GRUA ARTICULADA HIAB X-CLX 288 EP-5 MARINA | K13: BL288CX00253 | L13: 45342 | M13: =365*N13 -> 871 | N13: 2.3863014 | O13: 1 | P13: 44356.263 | Q13: 44356.263 | R13: < 1 año
... A24: 70100293 | B24: GRUA ARTICULADA HIAB X-CL 16 B-4 | C24: =COUNTIF(I:I,A24) -> 1 | D24: =AVERAGEIF(I:I,A24,P:P) -> 18637.461 | E24: =D24*C24 -> 18637.461 | H24: EQUIPOS IZAJE | I24: 13171063 | J24: Hiab 362 EP5 - EVO | K24: 3620650 | L24: 46126 | M24: =365*N24 -> 87 | N24: 0.23835616 | O24: 1 | P24: 90705.499 | Q24: 90705.499 | R24: < 1 año
C25: =SUM(C2:C24) -> 49 | E25: =SUM(E2:E23) -> 5166241.3 | H25: EQUIPOS IZAJE | I25: 13171063 | J25: Hiab 362 EP5 - EVO | K25: 3620652 | L25: 46150 | M25: =365*N25 -> 63 | N25: 0.17260274 | O25: 1 | P25: 90705.499 | Q25: 90705.499 | R25: < 1 año
H26: EQUIPOS IZAJE | I26: 13171063 | J26: Hiab 362 EP5 - EVO | K26: 3620656 | L26: 46150 | M26: =365*N26 -> 63 | N26: 0.17260274 | O26: 1 | P26: 90705.499 | Q26: 90705.499 | R26: < 1 año
H27: EQUIPOS IZAJE | I27: 13171063 | J27: Hiab 362 EP5 - EVO | K27: 3620659 | L27: 46181 | M27: =365*N27 -> 32 | N27: 0.087671233 | O27: 1 | P27: 90705.499 | Q27: 90705.499 | R27: < 1 año
H28: EQUIPOS IZAJE | I28: 13171063 | J28: Hiab 362 EP5 - EVO | K28: 3620660 | L28: 46181 | M28: =365*N28 -> 32 | N28: 0.087671233 | O28: 1 | P28: 90705.499 | Q28: 90705.499 | R28: < 1 año
A29: Código | B29: Descripción | H29: EQUIPOS IZAJE | I29: 13171063 | J29: Hiab 362 EP5 - EVO | K29: 3620661 | L29: 46181 | M29: =365*N29 -> 32 | N29: 0.087671233 | O29: 1 | P29: 90705.499 | Q29: 90705.499 | R29: < 1 año
A30: 13171068 | B30: GRUA ARTICULADA HIAB IQ 1188 E-8 HIPRO EVO | H30: EQUIPOS IZAJE | I30: 13171063 | J30: Hiab 362 EP5 - EVO | K30: 3620662 | L30: 46181 | M30: =365*N30 -> 32 | N30: 0.087671233 | O30: 1 | P30: 90705.499 | Q30: 90705.499 | R30: < 1 año
A31: 13171012 | B31: GRUA ARTICULADA HIAB X-HIPRO 858 E-8 | H31: EQUIPOS IZAJE | I31: 13171063 | J31: Hiab 362 EP5 - EVO | K31: 3620663 | L31: 46181 | M31: =365*N31 -> 32 | N31: 0.087671233 | O31: 1 | P31: 90705.499 | Q31: 90705.499 | R31: < 1 año
A32: 13171033 | B32: GRUA ARTICULADA HIAB X-HIPRO 638 E-9 | H32: EQUIPOS IZAJE | I32: 13171063 | J32: Hiab 362 EP5 - EVO | K32: 3620664 | L32: 46181 | M32: =365*N32 -> 32 | N32: 0.087671233 | O32: 1 | P32: 90705.499 | Q32: 90705.499 | R32: < 1 año
A33: 13171066 | B33: HIAB 638 EP9 (EVO) | H33: EQUIPOS IZAJE | I33: 13171065 | J33: HIAB 548 EP 9 (EVO) | K33: 5480513 | L33: 46181 | M33: =365*N33 -> 32 | N33: 0.087671233 | O33: 1 | P33: 118916.29 | Q33: 118916.29 | R33: < 1 año
A34: 19601024 | B34: HIAB X-HIPRO 558 EP-5 | H34: EQUIPOS IZAJE | I34: 13171065 | J34: HIAB 548 EP 9 (EVO) | K34: 5480515 | L34: 46181 | M34: =365*N34 -> 32 | N34: 0.087671233 | O34: 1 | P34: 118916.29 | Q34: 118916.29 | R34: < 1 año
A35: 13171064 | B35: Hiab 558 EP5 - EVO | H35: EQUIPOS IZAJE | I35: 13171064 | J35: Hiab 558 EP6 - EVO | K35: 5580532 | L35: 46181 | M35: =365*N35 -> 32 | N35: 0.087671233 | O35: 1 | P35: 122572.44 | Q35: 122572.44 | R35: < 1 año
A36: 19502062 | B36: GRUA ARTICULADA HIAB X-HIPRO 548 E-9 año 2022 | H36: EQUIPOS IZAJE | I36: 13171066 | J36: HIAB 638 EP9 (EVO) | K36: 6380504 | L36: 46181 | M36: =365*N36 -> 32 | N36: 0.087671233 | O36: 1 | P36: 141079.09 | Q36: 141079.09 | R36: < 1 año
A37: 13171065 | B37: HIAB 548 EP 9 (EVO) | H37: EQUIPOS IZAJE | I37: 13171066 | J37: HIAB 638 EP9 (EVO) | K37: 6380505 | L37: 46181 | M37: =365*N37 -> 32 | N37: 0.087671233 | O37: 1 | P37: 141079.09 | Q37: 141079.09 | R37: < 1 año
A38: 13171022 | B38: HIAB X-HIPRO 418 EP-5 | H38: EQUIPOS IZAJE | I38: 13171027 | J38: HIAB iX188 EP-5 | K38: BLX188HD0489 | L38: 46181 | M38: =365*N38 -> 32 | N38: 0.087671233 | O38: 1 | P38: 55192.327 | Q38: 55192.327 | R38: >= 1 año
A39: 13171021 | B39: HIAB X-HIPRO 408 E-8 | H39: EQUIPOS IZAJE | I39: 13171025 | J39: HIAB iX258 EP-5 | K39: BLX258HD0146 | L39: 46181 | M39: =365*N39 -> 32 | N39: 0.087671233 | O39: 1 | P39: 64770.205 | Q39: 64770.205 | R39: < 1 año
A40: 13171063 | B40: Hiab 362 EP5 - EVO | H40: EQUIPOS IZAJE | I40: 13171025 | J40: HIAB iX258 EP-5 | K40: BLX258HD0147 | L40: 46181 | M40: =365*N40 -> 32 | N40: 0.087671233 | O40: 1 | P40: 64770.205 | Q40: 64770.205 | R40: < 1 año
... A48: 13171061 | B48: GRÚA HIAB X-CL 8 B3 | H48: EQUIPOS IZAJE | I48: 19502041 | J48: HIAB X-HIPRO 548 E-9 | K48: 5480493 | L48: 46083 | M48: =365*N48 -> 130 | N48: 0.35616438 | O48: 1 | P48: 125996 | Q48: 125996 | R48: < 1 año
H49: EQUIPOS IZAJE | I49: 19502041 | J49: HIAB X-HIPRO 548 E-9 | K49: 5480494 | L49: 46097 | M49: =365*N49 -> 116 | N49: 0.31780822 | O49: 1 | P49: 125996 | Q49: 125996 | R49: < 1 año
H50: EQUIPOS IZAJE | I50: 19601024 | J50: HIAB X-HIPRO 558 EP-5 | K50: 5580410 | L50: 45656 | M50: =365*N50 -> 557 | N50: 1.5260274 | O50: 1 | P50: 103767.05 | Q50: 103767.05 | R50: >= 1 año
P51: =SUM(P2:P50) -> 5184878.8

Sheet Tránsito
C1: Tránsito total | H1: ItemCode | I1: Dscription | J1: ItemCode | K1: CardName | L1: MesEntrega | M1: Año | N1: PrecioUnitUsd | O1: OpenQty | P1: TotalUsd | Q1: Documento | R1: Tipo Transito | S1: N_GrupoArticulos | T1: DocDate | U1: Nro_OC | V1: Count of Nro_OC | W1: Fecha_OC | X1: Fecha Entrega | Y1: Tipo Compra | Z1: IsCommited | AA1: Currency | AB1: Rate | AC1: Rate | AD1: Backlog | AE1: CondiciondePago | AF1: CencoMarcaBI
A2: Código | B2: Descripción | C2: 1. TRANSITO REAL | D2: 2. TRANSITO PROYECTADO | E2: Costo unitario promedio | F2: Total | H2: 19601090 | I2: GRUA ARTICULADA HIAB iQ.708 E8 JIB 155Q | J2: 19601090 | K2: HIAB FINLAND OY | L2: 9 | M2: 2026 | N2: 235700.4 | O2: 1 | P2: 235700.4 | Q2: PO 2605076 | R2: 2. TRANSITO PROYECTADO | S2: EQUIPOS IZAJE | T2: 46147 | U2: 2605076 | V2: 1 | W2: 46147 | X2: 46283 | Y2: STOCK | Z2: 1 | AA2: EUR | AB2: 1.169317
A3: 19601090 | B3: GRUA ARTICULADA HIAB iQ.708 E8 JIB 155Q | C3: =SUMIFS(O:O,H:H,A3,R:R,$C$2) -> 0 | D3: =SUMIFS(O:O,H:H,A3,R:R,$D$2) -> 1 | E3: =AVERAGEIF(H:H,A3,N:N) -> 235700.4 | F3: =(E3*C3)+(E3*D3) -> 235700.4 | H3: 13171051 | I3: GRUA ARTICULADA HIAB IQ1188 E-9 JIB | J3: 13171051 | K3: HIAB FINLAND OY | L3: 7 | M3: 2026 | N3: 217868.34 | O3: 2 | P3: 435736.67 | Q3: PO 2603686 | R3: 2. TRANSITO PROYECTADO | S3: EQUIPOS IZAJE | T3: 46108 | U3: 2603686 | V3: 1 | W3: 46108 | X3: 46227 | Y3: STOCK | Z3: 2 | AA3: EUR | AB3: 2.306266
A4: 13171051 | B4: GRUA ARTICULADA HIAB IQ1188 E-9 JIB | C4: =SUMIFS(O:O,H:H,A4,R:R,$C$2) -> 0 | D4: =SUMIFS(O:O,H:H,A4,R:R,$D$2) -> 2 | E4: =AVERAGEIF(H:H,A4,N:N) -> 217868.34 | F4: =(E4*C4)+(E4*D4) -> 435736.67 | H4: 13171068 | I4: GRUA ARTICULADA HIAB IQ 1188 E-8 HIPRO EVO | J4: 13171068 | K4: HIAB FINLAND OY | L4: 7 | M4: 2026 | N4: 171125.65 | O4: 1 | P4: 171125.65 | Q4: TT 68692 | R4: 1. TRANSITO REAL | S4: EQUIPOS IZAJE | T4: 46209 | U4: 2511541 | V4: 1 | W4: 45986 | X4: 46213 | Y4: STOCK | Z4: 0 | AA4: EUR | AB4: 1.13779
A5: 13171068 | B5: GRUA ARTICULADA HIAB IQ 1188 E-8 HIPRO EVO | C5: =SUMIFS(O:O,H:H,A5,R:R,$C$2) -> 1 | D5: =SUMIFS(O:O,H:H,A5,R:R,$D$2) -> 2 | E5: =AVERAGEIF(H:H,A5,N:N) -> 169750.2 | F5: =(E5*C5)+(E5*D5) -> 509250.59 | H5: 13171068 | I5: GRUA ARTICULADA HIAB IQ 1188 E-8 HIPRO EVO | J5: 13171068 | K5: HIAB FINLAND OY | L5: 7 | M5: 2026 | N5: 168374.74 | O5: 2 | P5: 336749.48 | Q5: PO 2511541 | R5: 2. TRANSITO PROYECTADO | S5: EQUIPOS IZAJE | T5: 45986 | U5: 2511541 | V5: 1 | W5: 45986 | X5: 46213 | Y5: STOCK | Z5: 0 | AA5: EUR | AB5: 2.303096
A6: 13171012 | B6: GRUA ARTICULADA HIAB X-HIPRO 858 E-8 | C6: =SUMIFS(O:O,H:H,A6,R:R,$C$2) -> 4 | D6: =SUMIFS(O:O,H:H,A6,R:R,$D$2) -> 2 | E6: =AVERAGEIF(H:H,A6,N:N) -> 154661.29 | F6: =(E6*C6)+(E6*D6) -> 927967.77 | H6: 13171012 | I6: GRUA ARTICULADA HIAB X-HIPRO 858 E-8 | J6: 13171012 | K6: HIAB FINLAND OY | L6: 7 | M6: 2026 | N6: 155874.28 | O6: 1 | P6: 155874.28 | Q6: TT 67659 | R6: 1. TRANSITO REAL | S6: EQUIPOS IZAJE | T6: 46197 | U6: 2512686 | V6: 1 | W6: 46017 | X6: 46181 | Y6: CALZADO | Z6: 0 | AA6: EUR | AB6: 1.166453
A7: 13171070 | B7: GRÚA ARTICULADA HIAB IQ 708 HIPRO E9 | C7: =SUMIFS(O:O,H:H,A7,R:R,$C$2) -> 0 | D7: =SUMIFS(O:O,H:H,A7,R:R,$D$2) -> 1 | E7: =AVERAGEIF(H:H,A7,N:N) -> 152102.48 | F7: =(E7*C7)+(E7*D7) -> 152102.48 | H7: 13171012 | I7: GRUA ARTICULADA HIAB X-HIPRO 858 E-8 | J7: 13171012 | K7: HIAB FINLAND OY | L7: 7 | M7: 2026 | N7: 155874.28 | O7: 1 | P7: 155874.28 | Q7: TT 67669 | R7: 1. TRANSITO REAL | S7: EQUIPOS IZAJE | T7: 46197 | U7: 2512686 | V7: 1 | W7: 46017 | X7: 46181 | Y7: CALZADO | Z7: 0 | AA7: EUR | AB7: 1.166453
A8: 13171033 | B8: GRUA ARTICULADA HIAB X-HIPRO 638 E-9 | C8: =SUMIFS(O:O,H:H,A8,R:R,$C$2) -> 5 | D8: =SUMIFS(O:O,H:H,A8,R:R,$D$2) -> 0 | E8: =AVERAGEIF(H:H,A8,N:N) -> 144216.57 | F8: =(E8*C8)+(E8*D8) -> 721082.84 | H8: 13171012 | I8: GRUA ARTICULADA HIAB X-HIPRO 858 E-8 | J8: 13171012 | K8: HIAB FINLAND OY | L8: 7 | M8: 2026 | N8: 155874.28 | O8: 1 | P8: 155874.28 | Q8: TT 67673 | R8: 1. TRANSITO REAL | S8: EQUIPOS IZAJE | T8: 46197 | U8: 2512686 | V8: 1 | W8: 46017 | X8: 46181 | Y8: CALZADO | Z8: 0 | AA8: EUR | AB8: 1.166453
A9: 19502041 | B9: HIAB X-HIPRO 548 E-9 | C9: =SUMIFS(O:O,H:H,A9,R:R,$C$2) -> 4 | D9: =SUMIFS(O:O,H:H,A9,R:R,$D$2) -> 0 | E9: =AVERAGEIF(H:H,A9,N:N) -> 120219.75 | F9: =(E9*C9)+(E9*D9) -> 480878.99 | H9: 13171012 | I9: GRUA ARTICULADA HIAB X-HIPRO 858 E-8 | J9: 13171012 | K9: HIAB FINLAND OY | L9: 7 | M9: 2026 | N9: 155402.83 | O9: 1 | P9: 155402.83 | Q9: TT 66206 | R9: 1. TRANSITO REAL | S9: EQUIPOS IZAJE | T9: 46170 | U9: 2512686 | V9: 1 | W9: 46017 | X9: 46181 | Y9: CALZADO | Z9: 0 | AA9: EUR | AB9: 1.162925
A10: 19601036 | B10: HIAB X-HIPRO 558 EP-6 | C10: =SUMIFS(O:O,H:H,A10,R:R,$C$2) -> 7 | D10: =SUMIFS(O:O,H:H,A10,R:R,$D$2) -> 14 | E10: =AVERAGEIF(H:H,A10,N:N) -> 104534.47 | F10: =(E10*C10)+(E10*D10) -> 2195223.8 | H10: 13171070 | I10: GRÚA ARTICULADA HIAB IQ 708 HIPRO E9 | J10: 13171070 | K10: HIAB FINLAND OY | L10: 7 | M10: 2026 | N10: 152102.48 | O10: 1 | P10: 152102.48 | Q10: PO 2602478 | R10: 2. TRANSITO PROYECTADO | S10: EQUIPOS IZAJE | T10: 46078 | U10: 2602478 | V10: 1 | W10: 46078 | X10: 46206 | Y10: STOCK | Z10: 0 | AA10: EUR | AB10: 1.17855
A11: 13171021 | B11: HIAB X-HIPRO 408 E-8 | C11: =SUMIFS(O:O,H:H,A11,R:R,$C$2) -> 6 | D11: =SUMIFS(O:O,H:H,A11,R:R,$D$2) -> 0 | E11: =AVERAGEIF(H:H,A11,N:N) -> 100697.51 | F11: =(E11*C11)+(E11*D11) -> 604185.03 | H11: 13171012 | I11: GRUA ARTICULADA HIAB X-HIPRO 858 E-8 | J11: 13171012 | K11: HIAB FINLAND OY | L11: 7 | M11: 2026 | N11: 150280.8 | O11: 2 | P11: 300561.6 | Q11: PO 2512686 | R11: 2. TRANSITO PROYECTADO | S11: EQUIPOS IZAJE | T11: 46017 | U11: 2512686 | V11: 1 | W11: 46017 | X11: 46227 | Y11: CALZADO | Z11: 0 | AA11: EUR | AB11: 2.35572
A12: 13171045 | B12: GRUA ARTICULADA HIAB X-HIPRO 352 E-8 | C12: =SUMIFS(O:O,H:H,A12,R:R,$C$2) -> 0 | D12: =SUMIFS(O:O,H:H,A12,R:R,$D$2) -> 2 | E12: =AVERAGEIF(H:H,A12,N:N) -> 90920.061 | F12: =(E12*C12)+(E12*D12) -> 181840.12 | H12: 13171033 | I12: GRUA ARTICULADA HIAB X-HIPRO 638 E-9 | J12: 13171033 | K12: HIAB FINLAND OY | L12: 7 | M12: 2026 | N12: 147236.7 | O12: 1 | P12: 147236.7 | Q12: TT 67654 | R12: 1. TRANSITO REAL | S12: EQUIPOS IZAJE | T12: 46197 | U12: 2512724 | V12: 1 | W12: 46020 | X12: 46178 | Y12: STOCK | Z12: 1 | AA12: EUR | AB12: 1.166453
A13: 13171022 | B13: HIAB X-HIPRO 418 EP-5 | C13: =SUMIFS(O:O,H:H,A13,R:R,$C$2) -> 4 | D13: =SUMIFS(O:O,H:H,A13,R:R,$D$2) -> 5 | E13: =AVERAGEIF(H:H,A13,N:N) -> 88927.063 | F13: =(E13*C13)+(E13*D13) -> 800343.57 | H13: 13171033 | I13: GRUA ARTICULADA HIAB X-HIPRO 638 E-9 | J13: 13171033 | K13: HIAB FINLAND OY | L13: 7 | M13: 2026 | N13: 146550.61 | O13: 1 | P13: 146550.61 | Q13: TT 66820 | R13: 1. TRANSITO REAL | S13: EQUIPOS IZAJE | T13: 46173 | U13: 2512724 | V13: 1 | W13: 46020 | X13: 46178 | Y13: STOCK | Z13: 1 | AA13: EUR | AB13: 1.161036
A14: 13171029 | B14: HIAB eX302 EP-8 | C14: =SUMIFS(O:O,H:H,A14,R:R,$C$2) -> 3 | D14: =SUMIFS(O:O,H:H,A14,R:R,$D$2) -> 0 | E14: =AVERAGEIF(H:H,A14,N:N) -> 78160.91 | F14: =(E14*C14)+(E14*D14) -> 234482.73 | H14: 13171033 | I14: GRUA ARTICULADA HIAB X-HIPRO 638 E-9 | J14: 13171033 | K14: HIAB FINLAND OY | L14: 7 | M14: 2026 | N14: 142712.57 | O14: 1 | P14: 142712.57 | Q14: TT 67683 | R14: 1. TRANSITO REAL | S14: EQUIPOS IZAJE | T14: 46197 | U14: 2606263 | V14: 1 | W14: 46181 | X14: 46181 | Y14: CALZADO | Z14: 1 | AA14: EUR | AB14: 1.177856
... A23: 13171060 | B23: GRUA ARTICULADA HIAB X-CL 16 B-3 | C23: =SUMIFS(O:O,H:H,A23,R:R,$C$2) -> 2 | D23: =SUMIFS(O:O,H:H,A23,R:R,$D$2) -> 2 | E23: =AVERAGEIF(H:H,A23,N:N) -> 20854.828 | F23: =(E23*C23)+(E23*D23) -> 83419.311 | H23: 19601036 | I23: HIAB X-HIPRO 558 EP-6 | J23: 19601036 | K23: HIAB FINLAND OY | L23: 7 | M23: 2026 | N23: 106830.29 | O23: 1 | P23: 106830.29 | Q23: TT 65787 | R23: 1. TRANSITO REAL | S23: EQUIPOS IZAJE | T23: 46167 | U23: 2512676 | V23: 1 | W23: 46017 | X23: 46162 | Y23: STOCK | Z23: 8 | AA23: EUR | AB23: 1.173706
C24: =SUM(C3:C23) -> 50 | D24: =SUM(D3:D23) -> 64 | F24: =SUM(F3:F23) -> 10405716 | H24: 19601036 | I24: HIAB X-HIPRO 558 EP-6 | J24: 19601036 | K24: HIAB FINLAND OY | L24: 7 | M24: 2026 | N24: 106830.29 | O24: 1 | P24: 106830.29 | Q24: TT 65790 | R24: 1. TRANSITO REAL | S24: EQUIPOS IZAJE | T24: 46167 | U24: 2512676 | V24: 1 | W24: 46017 | X24: 46162 | Y24: STOCK | Z24: 8 | AA24: EUR | AB24: 1.173706
H25: 19601036 | I25: HIAB X-HIPRO 558 EP-6 | J25: 19601036 | K25: HIAB FINLAND OY | L25: 7 | M25: 2026 | N25: 105824.15 | O25: 1 | P25: 105824.15 | Q25: TT 66884 | R25: 1. TRANSITO REAL | S25: EQUIPOS IZAJE | T25: 46172 | U25: 2512726 | V25: 1 | W25: 46020 | X25: 46178 | Y25: STOCK | Z25: 8 | AA25: EUR | AB25: 1.162652
A26: 13171051 | H26: 19601036 | I26: HIAB X-HIPRO 558 EP-6 | J26: 19601036 | K26: HIAB FINLAND OY | L26: 7 | M26: 2026 | N26: 104754.46 | O26: 1 | P26: 104754.46 | Q26: TT 65783 | R26: 1. TRANSITO REAL | S26: EQUIPOS IZAJE | T26: 46167 | U26: 2512684 | V26: 1 | W26: 46017 | X26: 46162 | Y26: CALZADO | Z26: 8 | AA26: EUR | AB26: 1.173706
A27: 13171068 | H27: 19601036 | I27: HIAB X-HIPRO 558 EP-6 | J27: 19601036 | K27: HIAB FINLAND OY | L27: 7 | M27: 2026 | N27: 104753.34 | O27: 1 | P27: 104753.34 | Q27: TT 65788 | R27: 1. TRANSITO REAL | S27: EQUIPOS IZAJE | T27: 46167 | U27: 2512684 | V27: 1 | W27: 46017 | X27: 46162 | Y27: CALZADO | Z27: 8 | AA27: EUR | AB27: 1.173706
A28: 13171012 | H28: 19601036 | I28: HIAB X-HIPRO 558 EP-6 | J28: 19601036 | K28: HIAB FINLAND OY | L28: 7 | M28: 2026 | N28: 103767.88 | O28: 1 | P28: 103767.88 | Q28: TT 66883 | R28: 1. TRANSITO REAL | S28: EQUIPOS IZAJE | T28: 46173 | U28: 2512684 | V28: 1 | W28: 46017 | X28: 46169 | Y28: CALZADO | Z28: 8 | AA28: EUR | AB28: 1.162652
A29: 13171070 | H29: 13171021 | I29: HIAB X-HIPRO 408 E-8 | J29: 13171021 | K29: HIAB FINLAND OY | L29: 7 | M29: 2026 | N29: 102295.33 | O29: 1 | P29: 102295.33 | Q29: TT 65786 | R29: 1. TRANSITO REAL | S29: EQUIPOS IZAJE | T29: 46167 | U29: 2512679 | V29: 1 | W29: 46017 | X29: 46162 | Y29: CALZADO | Z29: 1 | AA29: EUR | AB29: 1.173706
A30: 19601036 | H30: 13171021 | I30: HIAB X-HIPRO 408 E-8 | J30: 13171021 | K30: HIAB FINLAND OY | L30: 7 | M30: 2026 | N30: 101434.63 | O30: 1 | P30: 101434.63 | Q30: TT 65596 | R30: 1. TRANSITO REAL | S30: EQUIPOS IZAJE | T30: 46161 | U30: 2512728 | V30: 1 | W30: 46020 | X30: 46161 | Y30: STOCK | Z30: 1 | AA30: EUR | AB30: 1.177856
A31: 13171022 | H31: 13171021 | I31: HIAB X-HIPRO 408 E-8 | J31: 13171021 | K31: HIAB FINLAND OY | L31: 7 | M31: 2026 | N31: 101077.24 | O31: 1 | P31: 101077.24 | Q31: TT 65789 | R31: 1. TRANSITO REAL | S31: EQUIPOS IZAJE | T31: 46167 | U31: 2512728 | V31: 1 | W31: 46020 | X31: 46161 | Y31: STOCK | Z31: 1 | AA31: EUR | AB31: 1.173706
A32: 10705003 | H32: 13171021 | I32: HIAB X-HIPRO 408 E-8 | J32: 13171021 | K32: HIAB FINLAND OY | L32: 7 | M32: 2026 | N32: 100406.68 | O32: 1 | P32: 100406.68 | Q32: TT 67185 | R32: 1. TRANSITO REAL | S32: EQUIPOS IZAJE | T32: 46188 | U32: 2602398 | V32: 1 | W32: 46073 | X32: 46188 | Y32: STOCK | Z32: 1 | AA32: EUR | AB32: 1.161711
A33: 13171020 | H33: 13171021 | I33: HIAB X-HIPRO 408 E-8 | J33: 13171021 | K33: HIAB FINLAND OY | L33: 7 | M33: 2026 | N33: 100406.68 | O33: 1 | P33: 100406.68 | Q33: TT 67186 | R33: 1. TRANSITO REAL | S33: EQUIPOS IZAJE | T33: 46188 | U33: 2602398 | V33: 1 | W33: 46073 | X33: 46182 | Y33: STOCK | Z33: 1 | AA33: EUR | AB33: 1.161711
A34: 13171045 | H34: 13171021 | I34: HIAB X-HIPRO 408 E-8 | J34: 13171021 | K34: HIAB FINLAND OY | L34: 7 | M34: 2026 | N34: 98564.472 | O34: 1 | P34: 98564.472 | Q34: TT 68693 | R34: 1. TRANSITO REAL | S34: EQUIPOS IZAJE | T34: 46209 | U34: 2602398 | V34: 1 | W34: 46073 | X34: 46206 | Y34: STOCK | Z34: 1 | AA34: EUR | AB34: 1.13779
A35: 13171023 | H35: 19601036 | I35: HIAB X-HIPRO 558 EP-6 | J35: 19601036 | K35: HIAB FINLAND OY | L35: 9 | M35: 2026 | N35: 93703.992 | O35: 12 | P35: 1124447.9 | Q35: PO 2605302 | R35: 2. TRANSITO PROYECTADO | S35: EQUIPOS IZAJE | T35: 46155 | U35: 2605302 | V35: 1 | W35: 46155 | X35: 46283 | Y35: CALZADO | Z35: 8 | AA35: EUR | AB35: 1.173706
A36: 13171050 | H36: 13171045 | I36: GRUA ARTICULADA HIAB X-HIPRO 352 E-8 | J36: 13171045 | K36: HIAB FINLAND OY | L36: 7 | M36: 2026 | N36: 90920.061 | O36: 2 | P36: 181840.12 | Q36: PO 2604774 | R36: 2. TRANSITO PROYECTADO | S36: EQUIPOS IZAJE | T36: 46142 | U36: 2604774 | V36: 1 | W36: 46142 | X36: 46234 | Y36: STOCK | Z36: 0 | AA36: EUR | AB36: 1.167273
A37: 13171057 | H37: 13171022 | I37: HIAB X-HIPRO 418 EP-5 | J37: 13171022 | K37: HIAB FINLAND OY | L37: 7 | M37: 2026 | N37: 90323.585 | O37: 2 | P37: 180647.17 | Q37: PO 2604773 | R37: 2. TRANSITO PROYECTADO | S37: EQUIPOS IZAJE | T37: 46142 | U37: 2604773 | V37: 1 | W37: 46142 | X37: 46234 | Y37: STOCK | Z37: 0 | AA37: EUR | AB37: 1.167273
A38: 13171060 | H38: 13171022 | I38: HIAB X-HIPRO 418 EP-5 | J38: 13171022 | K38: HIAB FINLAND OY | L38: 10 | M38: 2026 | N38: 90170.353 | O38: 3 | P38: 270511.06 | Q38: PO 2606571 | R38: 2. TRANSITO PROYECTADO | S38: EQUIPOS IZAJE | T38: 46190 | U38: 2606571 | V38: 1 | W38: 46190 | X38: 46304 | Y38: STOCK | Z38: 0 | AA38: EUR | AB38: 1.160897
H39: 13171022 | I39: HIAB X-HIPRO 418 EP-5 | J39: 13171022 | K39: HIAB FINLAND OY | L39: 7 | M39: 2026 | N39: 89311.18 | O39: 1 | P39: 89311.18 | Q39: TT 67189 | R39: 1. TRANSITO REAL | S39: EQUIPOS IZAJE | T39: 46188 | U39: 2602400 | V39: 1 | W39: 46073 | X39: 46182 | Y39: STOCK | Z39: 0 | AA39: EUR | AB39: 1.161711
H40: 13171022 | I40: HIAB X-HIPRO 418 EP-5 | J40: 13171022 | K40: HIAB FINLAND OY | L40: 7 | M40: 2026 | N40: 88029.91 | O40: 1 | P40: 88029.91 | Q40: TT 65784 | R40: 1. TRANSITO REAL | S40: EQUIPOS IZAJE | T40: 46167 | U40: 2512674 | V40: 1 | W40: 46017 | X40: 46162 | Y40: STOCK | Z40: 0 | AA40: EUR | AB40: 1.173706
H41: 13171022 | I41: HIAB X-HIPRO 418 EP-5 | J41: 13171022 | K41: HIAB FINLAND OY | L41: 7 | M41: 2026 | N41: 88029.91 | O41: 1 | P41: 88029.91 | Q41: TT 65785 | R41: 1. TRANSITO REAL | S41: EQUIPOS IZAJE | T41: 46167 | U41: 2512674 | V41: 1 | W41: 46017 | X41: 46162 | Y41: STOCK | Z41: 0 | AA41: EUR | AB41: 1.173706
H42: 13171022 | I42: HIAB X-HIPRO 418 EP-5 | J42: 13171022 | K42: HIAB FINLAND OY | L42: 7 | M42: 2026 | N42: 87697.44 | O42: 1 | P42: 87697.44 | Q42: TT 68694 | R42: 1. TRANSITO REAL | S42: EQUIPOS IZAJE | T42: 46209 | U42: 2602400 | V42: 1 | W42: 46073 | X42: 46206 | Y42: STOCK | Z42: 0 | AA42: EUR | AB42: 1.13779
H43: 13171029 | I43: HIAB eX302 EP-8 | J43: 13171029 | K43: HIAB FINLAND OY | L43: 7 | M43: 2026 | N43: 78936.476 | O43: 1 | P43: 78936.476 | Q43: TT 65122 | R43: 1. TRANSITO REAL | S43: EQUIPOS IZAJE | T43: 46142 | U43: 2512673 | V43: 1 | W43: 46017 | X43: 46139 | Y43: STOCK | Z43: 0 | AA43: EUR | AB43: 1.179937
H44: 13171020 | I44: HIAB X-HIPRO 362 EP-5 | J44: 13171020 | K44: HIAB FINLAND OY | L44: 7 | M44: 2026 | N44: 78783.924 | O44: 2 | P44: 157567.85 | Q44: PO 2604770 | R44: 2. TRANSITO PROYECTADO | S44: EQUIPOS IZAJE | T44: 46142 | U44: 2604770 | V44: 1 | W44: 46142 | X44: 46234 | Y44: STOCK | Z44: 2 | AA44: EUR | AB44: 1.167273
H45: 13171029 | I45: HIAB eX302 EP-8 | J45: 13171029 | K45: HIAB FINLAND OY | L45: 7 | M45: 2026 | N45: 77773.127 | O45: 1 | P45: 77773.127 | Q45: TT 66210 | R45: 1. TRANSITO REAL | S45: EQUIPOS IZAJE | T45: 46170 | U45: 2602397 | V45: 1 | W45: 46073 | X45: 46164 | Y45: STOCK | Z45: 0 | AA45: EUR | AB45: 1.167677
H46: 13171029 | I46: HIAB eX302 EP-8 | J46: 13171029 | K46: HIAB FINLAND OY | L46: 7 | M46: 2026 | N46: 77773.127 | O46: 1 | P46: 77773.127 | Q46: TT 66211 | R46: 1. TRANSITO REAL | S46: EQUIPOS IZAJE | T46: 46170 | U46: 2602397 | V46: 1 | W46: 46073 | X46: 46164 | Y46: STOCK | Z46: 0 | AA46: EUR | AB46: 1.167677
